Workbook
Name _Hlk2685582: '346_Inv053_A'!#REF!
Name _Hlk2685582: '420_Inv055_A'!#REF!
Name _Hlk2685582: '421_Inv056_A'!#REF!
Name _Hlk2685582: '73_Inv019_A'!$D$48
Name _Hlk2685582: '74_Inv020_A'!#REF!
Name _Hlk2685582: '75_Inv021_A'!#REF!
Name _Hlk2685582: '76_Inv022_A'!#REF!
Name _Hlk2685582: '77_Inv023_A'!#REF!
Name _Hlk2685582: '78_Inv024_A'!#REF!
Name _Hlk2685582: '79_Inv025_A'!#REF!
Name _Hlk2685582: '80_Inv026_A'!#REF!
Name _Hlk2685582: '81_Inv027_A'!#REF!
Name _Hlk2685582: '82_Inv028_A'!#REF!
Name _Hlk2685582: '83_Inv029_A'!#REF!
Name _Hlk2685582: '84_Inv030_A'!#REF!
Name _Hlk2685582: '85_Inv031_A'!#REF!
Name _Hlk2685582: '86_Inv032_A'!#REF!
Name _Hlk2685582: '87_Inv033_A'!#REF!
Name _Hlk2685582: '88_Inv034_A'!#REF!
Name _Hlk2685582: '89_Inv035_A'!#REF!
Name _Hlk2685582: '90_Inv036_A'!#REF!
Name _Hlk50047068: '273_LoginValidate'!$D$27
Name _Hlk50047068: '274_QueryLoginResult'!#REF!
Name _Hlk530658180: '102_Inv048_A'!#REF!
Name _Hlk530658180: '343_Inv050_A'!$D$50
Name _Hlk530658180: '344_Inv051_A'!$D$48
Name _Hlk530658180: '345_Inv052_A'!$D$50
Name _Hlk530658180: '346_Inv053_A'!#REF!
Name _Hlk530658180: '419_Inv054_A'!#REF!
Name _Hlk530658180: '420_Inv055_A'!#REF!
Name _Hlk530658180: '421_Inv056_A'!#REF!
Name _Hlk530658180: '55_Inv001_A'!#REF!
Name _Hlk530658180: '56_Inv002_A'!#REF!
Name _Hlk530658180: '57_Inv003_A'!$D$43
Name _Hlk530658180: '58_Inv004_A'!$D$46
Name _Hlk530658180: '59_Inv005_A'!$D$52
Name _Hlk530658180: '60_Inv006_A'!#REF!
Name _Hlk530658180: '61_Inv007_A'!#REF!
Name _Hlk530658180: '62_Inv008_A'!#REF!
Name _Hlk530658180: '63_Inv009_A'!#REF!
Name _Hlk530658180: '64_Inv010_A'!#REF!
Name _Hlk530658180: '65_Inv011_A'!#REF!
Name _Hlk530658180: '66_Inv012_A'!$D$43
Name _Hlk530658180: '67_Inv013_A'!$D$47
Name _Hlk530658180: '68_Inv014_A'!$D$48
Name _Hlk530658180: '69_Inv015_A'!$D$41
Name _Hlk530658180: '70_Inv016_A'!$D$44
Name _Hlk530658180: '71_Inv017_A'!$D$44
Name _Hlk530658180: '72_Inv018_A'!$D$36
Name _Hlk530658180: '73_Inv019_A'!$D$64
Name _Hlk530658180: '74_Inv020_A'!$D$37
Name _Hlk530658180: '75_Inv021_A'!#REF!
Name _Hlk530658180: '76_Inv022_A'!#REF!
Name _Hlk530658180: '77_Inv023_A'!#REF!
Name _Hlk530658180: '78_Inv024_A'!#REF!
Name _Hlk530658180: '79_Inv025_A'!#REF!
Name _Hlk530658180: '80_Inv026_A'!#REF!
Name _Hlk530658180: '81_Inv027_A'!#REF!
Name _Hlk530658180: '82_Inv028_A'!#REF!
Name _Hlk530658180: '83_Inv029_A'!#REF!

Sheet 結果
B1: 表名 | C1: K5值 | D1: L5值 | E1: M5值 | F1: K6值 | G1: L6值 | H1: M6值 | I1: K6文字 | J1: L6文字 | K1: M6文字
A2: 001 | B2: 1_RequestSpot | C2: SIT API URL | D2: UAT API URL | E2: PROD API URL | F2: http://10.11.22.126:886/ETSRateService.asm/RequestSpot | G2: http://10.11.66.160:886/ETSRateService.asm/RequestSpot | H2: http://10.16.1.11:886/ETSRateService.asm/RequestSpot | I2: =IF(ISERROR(F2), "缺SIT API URL", IF(F2=0, "缺SIT API URL", "")) | J2: =IF(ISERROR(G2), "缺UAT API URL", IF(G2=0, "缺UAT API URL", "")) | K2: =IF(ISERROR(H2), "缺PROD API URL", IF(H2=0, "缺PROD API URL", ""))
A3: 002 | B3: 2_RequestSpot2 | C3: SIT API URL | D3: UAT API URL | E3: PROD API URL | F3: http://10.11.22.126:886/ETSRateService.asm/RequestSpot2 | G3: http://10.11.66.160:886/ETSRateService.asm/RequestSpot2 | H3: http://10.16.1.11:886/ETSRateService.asm/RequestSpot2 | I3: =IF(ISERROR(F3), "缺SIT API URL", IF(F3=0, "缺SIT API URL", "")) | J3: =IF(ISERROR(G3), "缺UAT API URL", IF(G3=0, "缺UAT API URL", "")) | K3: =IF(ISERROR(H3), "缺PROD API URL", IF(H3=0, "缺PROD API URL", ""))
A4: 003 | B4: 3_InsertSpotDeal | C4: SIT API URL | D4: UAT API URL | E4: PROD API URL | F4: http://10.11.22.126:886/ETSRateService.asm/InsertSpotDeal | G4: http://10.11.66.160:886/ETSRateService.asm/InsertSpotDeal | H4: http://10.16.1.11:886/ETSRateService.asm/InsertSpotDeal | I4: =IF(ISERROR(F4), "缺SIT API URL", IF(F4=0, "缺SIT API URL", "")) | J4: =IF(ISERROR(G4), "缺UAT API URL", IF(G4=0, "缺UAT API URL", "")) | K4: =IF(ISERROR(H4), "缺PROD API URL", IF(H4=0, "缺PROD API URL", ""))
A5: 004 | B5: 4_GetReferRate | C5: SIT API URL | D5: UAT API URL | E5: PROD API URL | F5: http://10.11.22.126:886/ETSRateService.asm/GetReferRate | G5: http://10.11.66.160:886/ETSRateService.asm/GetReferRate | H5: http://10.16.1.11:886/ETSRateService.asm/GetReferRate | I5: =IF(ISERROR(F5), "缺SIT API URL", IF(F5=0, "缺SIT API URL", "")) | J5: =IF(ISERROR(G5), "缺UAT API URL", IF(G5=0, "缺UAT API URL", "")) | K5: =IF(ISERROR(H5), "缺PROD API URL", IF(H5=0, "缺PROD API URL", ""))
A6: 005 | B6: 5_FUNINSERTFXORDER | C6: SIT API URL | D6: UAT API URL | E6: PROD API URL | F6: http://10.11.35.51:8091/FxOrderWebService.asmx/funFxOrderWS | G6: http://10.11.66.136:8091/FxOrderWebService.asmx/funFxOrderWS | H6: http://10.16.1.29:8091/FxOrderWebService.asmx/funFxOrderWS | I6: =IF(ISERROR(F6), "缺SIT API URL", IF(F6=0, "缺SIT API URL", "")) | J6: =IF(ISERROR(G6), "缺UAT API URL", IF(G6=0, "缺UAT API URL", "")) | K6: =IF(ISERROR(H6), "缺PROD API URL", IF(H6=0, "缺PROD API URL", ""))
A7: 006 | B7: 6_FUNDELETEFXORDER | C7: SIT API URL | D7: UAT API URL | E7: PROD API URL | F7: http://10.11.35.51:8091/FxOrderWebService.asmx/funFxOrderWS | G7: http://10.11.66.136:8091/FxOrderWebService.asmx/funFxOrderWS | H7: http://10.16.1.29:8091/FxOrderWebService.asmx/funFxOrderWS | I7: =IF(ISERROR(F7), "缺SIT API URL", IF(F7=0, "缺SIT API URL", "")) | J7: =IF(ISERROR(G7), "缺UAT API URL", IF(G7=0, "缺UAT API URL", "")) | K7: =IF(ISERROR(H7), "缺PROD API URL", IF(H7=0, "缺PROD API URL", ""))
A8: 007 | B8: 7_MemberRegisterCheck | C8: SIT API URL | D8: UAT API URL | E8: PROD API URL | F8: http://sinopac.eweb.backend/api/Member/MemberRegisterCheck | H8: http://sinopac.eweb.backend/api/Member/MemberRegisterCheck | I8: =IF(ISERROR(F8), "缺SIT API URL", IF(F8=0, "缺SIT API URL", "")) | J8: =IF(ISERROR(G8), "缺UAT API URL", IF(G8=0, "缺UAT API URL", "")) -> 缺UAT API URL | K8: =IF(ISERROR(H8), "缺PROD API URL", IF(H8=0, "缺PROD API URL", ""))
A9: 008 | B9: 8_LatestTx | C9: SIT API URL | D9: UAT API URL | E9: PROD API URL | F9: http://sinopac.eweb.backend/api/Accounting/LatestTx | H9: http://sinopac.eweb.backend/api/Accounting/LatestTx | I9: =IF(ISERROR(F9), "缺SIT API URL", IF(F9=0, "缺SIT API URL", "")) | J9: =IF(ISERROR(G9), "缺UAT API URL", IF(G9=0, "缺UAT API URL", "")) -> 缺UAT API URL | K9: =IF(ISERROR(H9), "缺PROD API URL", IF(H9=0, "缺PROD API URL", ""))
A10: 009 | B10: 9_OutstandingDetail | C10: SIT API URL | D10: UAT API URL | E10: PROD API URL | F10: http://sinopac.eweb.backend/api/Accounting/OutstandingDetail | H10: http://sinopac.eweb.backend/api/Accounting/OutstandingDetail | I10: =IF(ISERROR(F10), "缺SIT API URL", IF(F10=0, "缺SIT API URL", "")) | J10: =IF(ISERROR(G10), "缺UAT API URL", IF(G10=0, "缺UAT API URL", "")) -> 缺UAT API URL | K10: =IF(ISERROR(H10), "缺PROD API URL", IF(H10=0, "缺PROD API URL", ""))
A11: 010 | B11: 10_RecentBill | C11: SIT API URL | D11: UAT API URL | E11: PROD API URL | F11: http://sinopac.eweb.backend/api/Accounting/RecentBill | H11: http://sinopac.eweb.backend/api/Accounting/RecentBill | I11: =IF(ISERROR(F11), "缺SIT API URL", IF(F11=0, "缺SIT API URL", "")) | J11: =IF(ISERROR(G11), "缺UAT API URL", IF(G11=0, "缺UAT API URL", "")) -> 缺UAT API URL | K11: =IF(ISERROR(H11), "缺PROD API URL", IF(H11=0, "缺PROD API URL", ""))
A12: 011 | B12: 11_OtpState | C12: SIT API URL | D12: UAT API URL | E12: PROD API URL | F12: http://10.11.37.109/OTP/Service/OtpSvc.asmx?op=OtpState | H12: http://10.16.1.28/OTP/Service/OtpSvc.asmx?op=OtpState | I12: =IF(ISERROR(F12), "缺SIT API URL", IF(F12=0, "缺SIT API URL", "")) | J12: =IF(ISERROR(G12), "缺UAT API URL", IF(G12=0, "缺UAT API URL", "")) -> 缺UAT API URL | K12: =IF(ISERROR(H12), "缺PROD API URL", IF(H12=0, "缺PROD API URL", ""))
A13: 012 | B13: 12_cardGetMain | C13: SIT API URL | D13: UAT API URL | E13: PROD API URL | F13: http://10.11.37.109/CARDWebService/MMAQueryMain/QueryMain.asmx?op=cardGetMain | H13: http://172.31.213.9/CARDWebService/MMAQueryMain/QueryMain.asmx?op=cardGetMain | I13: =IF(ISERROR(F13), "缺SIT API URL", IF(F13=0, "缺SIT API URL", "")) | J13: =IF(ISERROR(G13), "缺UAT API URL", IF(G13=0, "缺UAT API URL", "")) -> 缺UAT API URL | K13: =IF(ISERROR(H13), "缺PROD API URL", IF(H13=0, "缺PROD API URL", ""))
A14: 013 | B14: 13_getDAWHORet | C14: SIT API URL | D14: UAT API URL | E14: PROD API URL | F14: http://10.11.37.109/CARDWebService/MMAQueryMain/QueryMain.asmx?op=getDAWHORet | H14: http://172.31.213.9/CARDWebService/MMAQueryMain/QueryMain.asmx?op=getDAWHORet | I14: =IF(ISERROR(F14), "缺SIT API URL", IF(F14=0, "缺SIT API URL", "")) | J14: =IF(ISERROR(G14), "缺UAT API URL", IF(G14=0, "缺UAT API URL", "")) -> 缺UAT API URL | K14: =IF(ISERROR(H14), "缺PROD API URL", IF(H14=0, "缺PROD API URL", ""))
A15: 014 | B15: 14_getDAWHOCardStatus | C15: SIT API URL | D15: UAT API URL | E15: PROD API URL | F15: http://10.11.37.109/CARDWebService/MMAQueryMain/QueryMain.asmx?op=getDAWHOCardStatus | H15: http://172.31.213.9/CARDWebService/MMAQueryMain/QueryMain.asmx?op=getDAWHOCardStatus | I15: =IF(ISERROR(F15), "缺SIT API URL", IF(F15=0, "缺SIT API URL", "")) | J15: =IF(ISERROR(G15), "缺UAT API URL", IF(G15=0, "缺UAT API URL", "")) -> 缺UAT API URL | K15: =IF(ISERROR(H15), "缺PROD API URL", IF(H15=0, "缺PROD API URL", ""))
A16: 015 | B16: 15_getDDFlag | C16: SIT API URL | D16: UAT API URL | E16: PROD API URL | F16: http://10.11.37.109/CARDWebService/MMAQueryMain/QueryMain.asmx?op=getDDFlag | H16: http://172.31.213.9/CARDWebService/MMAQueryMain/QueryMain.asmx?op=getDDFlag | I16: =IF(ISERROR(F16), "缺SIT API URL", IF(F16=0, "缺SIT API URL", "")) | J16: =IF(ISERROR(G16), "缺UAT API URL", IF(G16=0, "缺UAT API URL", "")) -> 缺UAT API URL | K16: =IF(ISERROR(H16), "缺PROD API URL", IF(H16=0, "缺PROD API URL", ""))
A17: 016 | B17: 16_getBLHSHWithPaysum | C17: SIT API URL | D17: UAT API URL | E17: PROD API URL | F17: http://10.11.37.109/CARDWebService/MMAQueryMain/QueryMain.asmx?op=getBLHSHWithPaysum | H17: http://172.31.213.9/CARDWebService/MMAQueryMain/QueryMain.asmx?op=getBLHSHWithPaysum | I17: =IF(ISERROR(F17), "缺SIT API URL", IF(F17=0, "缺SIT API URL", "")) | J17: =IF(ISERROR(G17), "缺UAT API URL", IF(G17=0, "缺UAT API URL", "")) -> 缺UAT API URL | K17: =IF(ISERROR(H17), "缺PROD API URL", IF(H17=0, "缺PROD API URL", ""))
A18: 017 | B18: 17_getMainDcur | C18: SIT API URL | D18: UAT API URL | E18: PROD API URL | F18: http://10.11.37.109/CARDWebService/MMAQueryMain/QueryMain.asmx?op=getMainDcur | H18: http://172.31.213.9/CARDWebService/MMAQueryMain/QueryMain.asmx?op=getMainDcur | I18: =IF(ISERROR(F18), "缺SIT API URL", IF(F18=0, "缺SIT API URL", "")) | J18: =IF(ISERROR(G18), "缺UAT API URL", IF(G18=0, "缺UAT API URL", "")) -> 缺UAT API URL | K18: =IF(ISERROR(H18), "缺PROD API URL", IF(H18=0, "缺PROD API URL", ""))
A19: 018 | B19: 18_Inv01_E | C19: SIT API URL | D19: UAT API URL | E19: PROD API URL | F19: https://10.11.37.36:8080/etfAPIM/ | G19: https://10.11.66.149:8080/etfAPIM/ | H19: https://10.16.1.61:8080/etfAPIM/ | I19: =IF(ISERROR(F19), "缺SIT API URL", IF(F19=0, "缺SIT API URL", "")) | J19: =IF(ISERROR(G19), "缺UAT API URL", IF(G19=0, "缺UAT API URL", "")) | K19: =IF(ISERROR(H19), "缺PROD API URL", IF(H19=0, "缺PROD API URL", ""))
A20: 019 | B20: 19_Inv02_E | C20: SIT API URL | D20: UAT API URL | E20: PROD API URL | F20: https://10.11.37.36:8080/etfAPIM/ | G20: https://10.11.66.149:8080/etfAPIM/ | H20: https://10.16.1.61:8080/etfAPIM/ | I20: =IF(ISERROR(F20), "缺SIT API URL", IF(F20=0, "缺SIT API URL", "")) | J20: =IF(ISERROR(G20), "缺UAT API URL", IF(G20=0, "缺UAT API URL", "")) | K20: =IF(ISERROR(H20), "缺PROD API URL", IF(H20=0, "缺PROD API URL", ""))
A21: 020 | B21: 20_Inv03_E | C21: SIT API URL | D21: UAT API URL | E21: PROD API URL | F21: https://10.11.37.36:8080/etfAPIM/ | G21: https://10.11.66.149:8080/etfAPIM/ | H21: https://10.16.1.61:8080/etfAPIM/ | I21: =IF(ISERROR(F21), "缺SIT API URL", IF(F21=0, "缺SIT API URL", "")) | J21: =IF(ISERROR(G21), "缺UAT API URL", IF(G21=0, "缺UAT API URL", "")) | K21: =IF(ISERROR(H21), "缺PROD API URL", IF(H21=0, "缺PROD API URL", ""))
A22: 021 | B22: 21_Inv04_E | C22: SIT API URL | D22: UAT API URL | E22: PROD API URL | F22: https://10.11.37.36:8080/etfAPIM/ | G22: https://10.11.66.149:8080/etfAPIM/ | H22: https://10.16.1.61:8080/etfAPIM/ | I22: =IF(ISERROR(F22), "缺SIT API URL", IF(F22=0, "缺SIT API URL", "")) | J22: =IF(ISERROR(G22), "缺UAT API URL", IF(G22=0, "缺UAT API URL", "")) | K22: =IF(ISERROR(H22), "缺PROD API URL", IF(H22=0, "缺PROD API URL", ""))
A23: 022 | B23: 22_Inv05_E | C23: SIT API URL | D23: UAT API URL | E23: PROD API URL | F23: https://10.11.37.36:8080/etfAPIM/ | G23: https://10.11.66.149:8080/etfAPIM/ | H23: https://10.16.1.61:8080/etfAPIM/ | I23: =IF(ISERROR(F23), "缺SIT API URL", IF(F23=0, "缺SIT API URL", "")) | J23: =IF(ISERROR(G23), "缺UAT API URL", IF(G23=0, "缺UAT API URL", "")) | K23: =IF(ISERROR(H23), "缺PROD API URL", IF(H23=0, "缺PROD API URL", ""))
A24: 023 | B24: 23_Inv06_E | C24: SIT API URL | D24: UAT API URL | E24: PROD API URL | F24: https://10.11.37.36:8080/etfAPIM/ | G24: https://10.11.66.149:8080/etfAPIM/ | H24: https://10.16.1.61:8080/etfAPIM/ | I24: =IF(ISERROR(F24), "缺SIT API URL", IF(F24=0, "缺SIT API URL", "")) | J24: =IF(ISERROR(G24), "缺UAT API URL", IF(G24=0, "缺UAT API URL", "")) | K24: =IF(ISERROR(H24), "缺PROD API URL", IF(H24=0, "缺PROD API URL", ""))
A25: 024 | B25: 24_Inv07_E | C25: SIT API URL | D25: UAT API URL | E25: PROD API URL | F25: https://10.11.37.36:8080/etfAPIM/ | G25: https://10.11.66.149:8080/etfAPIM/ | H25: https://10.16.1.61:8080/etfAPIM/ | I25: =IF(ISERROR(F25), "缺SIT API URL", IF(F25=0, "缺SIT API URL", "")) | J25: =IF(ISERROR(G25), "缺UAT API URL", IF(G25=0, "缺UAT API URL", "")) | K25: =IF(ISERROR(H25), "缺PROD API URL", IF(H25=0, "缺PROD API URL", ""))
A26: 025 | B26: 25_Inv08_E | C26: SIT API URL | D26: UAT API URL | E26: PROD API URL | F26: https://10.11.37.36:8080/etfAPIM/ | G26: https://10.11.66.149:8080/etfAPIM/ | H26: https://10.16.1.61:8080/etfAPIM/ | I26: =IF(ISERROR(F26), "缺SIT API URL", IF(F26=0, "缺SIT API URL", "")) | J26: =IF(ISERROR(G26), "缺UAT API URL", IF(G26=0, "缺UAT API URL", "")) | K26: =IF(ISERROR(H26), "缺PROD API URL", IF(H26=0, "缺PROD API URL", ""))
A27: 026 | B27: 26_Inv09_E | C27: SIT API URL | D27: UAT API URL | E27: PROD API URL | F27: https://10.11.37.36:8080/etfAPIM/ | G27: https://10.11.66.149:8080/etfAPIM/ | H27: https://10.16.1.61:8080/etfAPIM/ | I27: =IF(ISERROR(F27), "缺SIT API URL", IF(F27=0, "缺SIT API URL", "")) | J27: =IF(ISERROR(G27), "缺UAT API URL", IF(G27=0, "缺UAT API URL", "")) | K27: =IF(ISERROR(H27), "缺PROD API URL", IF(H27=0, "缺PROD API URL", ""))
A28: 027 | B28: 27_Inv10_E | C28: SIT API URL | D28: UAT API URL | E28: PROD API URL | F28: https://10.11.37.36:8080/etfAPIM/ | G28: https://10.11.66.149:8080/etfAPIM/ | H28: https://10.16.1.61:8080/etfAPIM/ | I28: =IF(ISERROR(F28), "缺SIT API URL", IF(F28=0, "缺SIT API URL", "")) | J28: =IF(ISERROR(G28), "缺UAT API URL", IF(G28=0, "缺UAT API URL", "")) | K28: =IF(ISERROR(H28), "缺PROD API URL", IF(H28=0, "缺PROD API URL", ""))
A29: 028 | B29: 28_Inv11_E | C29: SIT API URL | D29: UAT API URL | E29: PROD API URL | F29: https://10.11.37.36:8080/etfAPIM/ | G29: https://10.11.66.149:8080/etfAPIM/ | H29: https://10.16.1.61:8080/etfAPIM/ | I29: =IF(ISERROR(F29), "缺SIT API URL", IF(F29=0, "缺SIT API URL", "")) | J29: =IF(ISERROR(G29), "缺UAT API URL", IF(G29=0, "缺UAT API URL", "")) | K29: =IF(ISERROR(H29), "缺PROD API URL", IF(H29=0, "缺PROD API URL", ""))
A30: 029 | B30: 29_Inv12_E | C30: SIT API URL | D30: UAT API URL | E30: PROD API URL | F30: https://10.11.37.36:8080/etfAPIM/ | G30: https://10.11.66.149:8080/etfAPIM/ | H30: https://10.16.1.61:8080/etfAPIM/ | I30: =IF(ISERROR(F30), "缺SIT API URL", IF(F30=0, "缺SIT API URL", "")) | J30: =IF(ISERROR(G30), "缺UAT API URL", IF(G30=0, "缺UAT API URL", "")) | K30: =IF(ISERROR(H30), "缺PROD API URL", IF(H30=0, "缺PROD API URL", ""))
... A251: 253 | B251: 253_C002 | C251: SIT API URL | D251: UAT API URL | E251: PROD API URL | F251: http://10.11.35.133/pb/Service/ApproveService.asmx?op=eBill_Webservice_yfp | G251: http://10.11.152.102/pb/Service/ApproveService.asmx?op=eBill_Webservice_yfp | H251: http://10.16.1.10/pb/Service/ApproveService.asmx?op=eBill_Webservice_yfp | I251: =IF(ISERROR(F251), "缺SIT API URL", IF(F251=0, "缺SIT API URL", "")) | J251: =IF(ISERROR(G251), "缺UAT API URL", IF(G251=0, "缺UAT API URL", "")) | K251: =IF(ISERROR(H251), "缺PROD API URL", IF(H251=0, "缺PROD API URL", ""))
A252: 254 | B252: 254_C003 | C252: SIT API URL | D252: UAT API URL | E252: PROD API URL | G252: http://10.11.148.3/eBill_Webservice/service1.asmx?op=eBill_Webservice | H252: http://10.12.1.45/eBill_Webservice/service1.asmx?op=eBill_Webservice | I252: =IF(ISERROR(F252), "缺SIT API URL", IF(F252=0, "缺SIT API URL", "")) -> 缺SIT API URL | J252: =IF(ISERROR(G252), "缺UAT API URL", IF(G252=0, "缺UAT API URL", "")) | K252: =IF(ISERROR(H252), "缺PROD API URL", IF(H252=0, "缺PROD API URL", ""))
A253: 255 | B253: 255_C004 | C253: SIT API URL | D253: UAT API URL | E253: PROD API URL | G253: https://videocenter-uat.sinopac.com:8080/VCS/restful/generateApiToken | H253: https://videocenter.sinopac.com:8080/VCS/restful/generateApiToken | I253: =IF(ISERROR(F253), "缺SIT API URL", IF(F253=0, "缺SIT API URL", "")) -> 缺SIT API URL | J253: =IF(ISERROR(G253), "缺UAT API URL", IF(G253=0, "缺UAT API URL", "")) | K253: =IF(ISERROR(H253), "缺PROD API URL", IF(H253=0, "缺PROD API URL", ""))
A254: 256 | B254: 256_C005 | C254: SIT API URL | D254: UAT API URL | E254: PROD API URL | G254: https://videocenter-uat.sinopac.com:8080/VCS/restful/promptCallIn | H254: https://videocenter.sinopac.com:8080/VCS/restful/promptCallIn | I254: =IF(ISERROR(F254), "缺SIT API URL", IF(F254=0, "缺SIT API URL", "")) -> 缺SIT API URL | J254: =IF(ISERROR(G254), "缺UAT API URL", IF(G254=0, "缺UAT API URL", "")) | K254: =IF(ISERROR(H254), "缺PROD API URL", IF(H254=0, "缺PROD API URL", ""))
A255: 257 | B255: 257_C006 | C255: SIT API URL | D255: UAT API URL | E255: PROD API URL | G255: https://videocenter-uat.sinopac.com:8080/VCS/restful/custWaiting | H255: https://videocenter.sinopac.com:8080/VCS/restful/custWaiting | I255: =IF(ISERROR(F255), "缺SIT API URL", IF(F255=0, "缺SIT API URL", "")) -> 缺SIT API URL | J255: =IF(ISERROR(G255), "缺UAT API URL", IF(G255=0, "缺UAT API URL", "")) | K255: =IF(ISERROR(H255), "缺PROD API URL", IF(H255=0, "缺PROD API URL", ""))
A256: 258 | B256: 258_C007 | C256: SIT API URL | D256: UAT API URL | E256: PROD API URL | G256: https://videocenter-uat.sinopac.com:8080/VCS/restful/custCancelCall | H256: https://videocenter.sinopac.com:8080/VCS/restful/custCancelCall | I256: =IF(ISERROR(F256), "缺SIT API URL", IF(F256=0, "缺SIT API URL", "")) -> 缺SIT API URL | J256: =IF(ISERROR(G256), "缺UAT API URL", IF(G256=0, "缺UAT API URL", "")) | K256: =IF(ISERROR(H256), "缺PROD API URL", IF(H256=0, "缺PROD API URL", ""))
A257: 259 | B257: 259_C008 | C257: SIT API URL | D257: UAT API URL | E257: PROD API URL | G257: https://videocenter-uat.sinopac.com:8080/VCS/restful/reportAgentDisconnected | H257: https://videocenter.sinopac.com:8080/VCS/restful/reportAgentDisconnected | I257: =IF(ISERROR(F257), "缺SIT API URL", IF(F257=0, "缺SIT API URL", "")) -> 缺SIT API URL | J257: =IF(ISERROR(G257), "缺UAT API URL", IF(G257=0, "缺UAT API URL", "")) | K257: =IF(ISERROR(H257), "缺PROD API URL", IF(H257=0, "缺PROD API URL", ""))
A258: 260 | B258: 260_C009 | C258: SIT API URL | D258: UAT API URL | E258: PROD API URL | G258: https://videocenter-uat.sinopac.com:8080/VCS/restful/vidyoLoginValidate | H258: https://videocenter.sinopac.com:8080/VCS/restful/vidyoLoginValidate | I258: =IF(ISERROR(F258), "缺SIT API URL", IF(F258=0, "缺SIT API URL", "")) -> 缺SIT API URL | J258: =IF(ISERROR(G258), "缺UAT API URL", IF(G258=0, "缺UAT API URL", "")) | K258: =IF(ISERROR(H258), "缺PROD API URL", IF(H258=0, "缺PROD API URL", ""))
A259: 261 | B259: 261_C010 | C259: SIT API URL | D259: UAT API URL | E259: PROD API URL | F259: http://10.11.36.37:808/AppService/WebServices/ws_UserStatusQuery.ashx | G259: http://10.11.42.80:808/AppService/WebServices/ws_UserStatusQuery.ashx | H259: http://10.15.1.55:808/AppService/WebServices/ws_UserStatusQuery.ashx | I259: =IF(ISERROR(F259), "缺SIT API URL", IF(F259=0, "缺SIT API URL", "")) | J259: =IF(ISERROR(G259), "缺UAT API URL", IF(G259=0, "缺UAT API URL", "")) | K259: =IF(ISERROR(H259), "缺PROD API URL", IF(H259=0, "缺PROD API URL", ""))
A260: 262 | B260: 262_C011 | C260: SIT API URL | D260: UAT API URL | E260: PROD API URL | F260: http://10.11.36.36/MemberPortal/Member/ProxyLogin.ashx | G260: http://10.11.42.235/MemberPortal/Member/ProxyLogin.ashx | H260: https://mma.sinopac.com/MemberPortal/Member/ProxyLogin.ashx | I260: =IF(ISERROR(F260), "缺SIT API URL", IF(F260=0, "缺SIT API URL", "")) | J260: =IF(ISERROR(G260), "缺UAT API URL", IF(G260=0, "缺UAT API URL", "")) | K260: =IF(ISERROR(H260), "缺PROD API URL", IF(H260=0, "缺PROD API URL", ""))
A261: 263 | B261: 263_C012 | C261: SIT API URL | D261: UAT API URL | E261: PROD API URL | F261: http://10.11.36.37:808/AppService/WebServices/ws_ApplyMMAUser.ashx | G261: http://10.11.42.80:808/AppService/WebServices/ws_ApplyMMAUser.ashx | H261: http://10.15.1.55:808/AppService/WebServices/ws_ApplyMMAUser.ashx | I261: =IF(ISERROR(F261), "缺SIT API URL", IF(F261=0, "缺SIT API URL", "")) | J261: =IF(ISERROR(G261), "缺UAT API URL", IF(G261=0, "缺UAT API URL", "")) | K261: =IF(ISERROR(H261), "缺PROD API URL", IF(H261=0, "缺PROD API URL", ""))
A262: 264 | B262: 264_C013 | C262: SIT API URL | D262: UAT API URL | E262: PROD API URL | F262: net.tcp://10.11.36.37:809/AppService/BranchService.svc | G262: net.tcp://10.11.42.80:809/AppService/BranchService.svc | H262: net.tcp://10.15.1.55:809/AppService/BranchService.svc | I262: =IF(ISERROR(F262), "缺SIT API URL", IF(F262=0, "缺SIT API URL", "")) | J262: =IF(ISERROR(G262), "缺UAT API URL", IF(G262=0, "缺UAT API URL", "")) | K262: =IF(ISERROR(H262), "缺PROD API URL", IF(H262=0, "缺PROD API URL", ""))
A263: 265 | B263: 265_C014 | C263: SIT API URL | D263: UAT API URL | E263: PROD API URL | F263: http://10.11.37.81/B2BWS/CIBB2BService?wsdl | G263: http://10.11.37.81/B2BWS/CIBB2BService?wsdl | H263: http://10.16.1.229/B2BWS/CIBB2BService | I263: =IF(ISERROR(F263), "缺SIT API URL", IF(F263=0, "缺SIT API URL", "")) | J263: =IF(ISERROR(G263), "缺UAT API URL", IF(G263=0, "缺UAT API URL", "")) | K263: =IF(ISERROR(H263), "缺PROD API URL", IF(H263=0, "缺PROD API URL", ""))
A264: 267 | B264: 267_CrossSaleCheck | C264: SIT API URL | D264: UAT API URL | E264: PROD API URL | F264: http://10.11.34.237/NCRM-WS/WmsService?wsdl | G264: http://10.11.42.113/NCRM-WS/WmsService?wsdl | H264: http://10.16.1.24/NCRM-WS/WmsService?wsdl | I264: =IF(ISERROR(F264), "缺SIT API URL", IF(F264=0, "缺SIT API URL", "")) | J264: =IF(ISERROR(G264), "缺UAT API URL", IF(G264=0, "缺UAT API URL", "")) | K264: =IF(ISERROR(H264), "缺PROD API URL", IF(H264=0, "缺PROD API URL", ""))
A265: 268 | B265: 268_CrossSaleUpdate | C265: SIT API URL | D265: UAT API URL | E265: PROD API URL | F265: http://10.11.34.237/NCRM-WS/WmsService?wsdl | G265: http://10.11.42.113/NCRM-WS/WmsService?wsdl | H265: http://10.16.1.24/NCRM-WS/WmsService?wsdl | I265: =IF(ISERROR(F265), "缺SIT API URL", IF(F265=0, "缺SIT API URL", "")) | J265: =IF(ISERROR(G265), "缺UAT API URL", IF(G265=0, "缺UAT API URL", "")) | K265: =IF(ISERROR(H265), "缺PROD API URL", IF(H265=0, "缺PROD API URL", ""))
A266: 269 | B266: 269_InvProfileCalculate | C266: SIT API URL | D266: UAT API URL | E266: PROD API URL | F266: http://10.11.34.237/NCRM-WS/WmsService?wsdl | G266: http://10.11.42.113/NCRM-WS/WmsService?wsdl | H266: http://10.16.1.24/NCRM-WS/WmsService?wsdl | I266: =IF(ISERROR(F266), "缺SIT API URL", IF(F266=0, "缺SIT API URL", "")) | J266: =IF(ISERROR(G266), "缺UAT API URL", IF(G266=0, "缺UAT API URL", "")) | K266: =IF(ISERROR(H266), "缺PROD API URL", IF(H266=0, "缺PROD API URL", ""))
A267: 270 | B267: 270_InsCusInvQuestionnaire | C267: SIT API URL | D267: UAT API URL | E267: PROD API URL | F267: http://10.11.34.237/NCRM-WS/WmsService?wsdl | G267: http://10.11.42.113/NCRM-WS/WmsService?wsdl | H267: http://10.16.1.24/NCRM-WS/WmsService?wsdl | I267: =IF(ISERROR(F267), "缺SIT API URL", IF(F267=0, "缺SIT API URL", "")) | J267: =IF(ISERROR(G267), "缺UAT API URL", IF(G267=0, "缺UAT API URL", "")) | K267: =IF(ISERROR(H267), "缺PROD API URL", IF(H267=0, "缺PROD API URL", ""))
A268: 271 | B268: 271_GetCusFinanceStatus | C268: SIT API URL | D268: UAT API URL | E268: PROD API URL | F268: http://10.11.34.237/NCRM-WS/WmsService?wsdl | G268: http://10.11.42.113/NCRM-WS/WmsService?wsdl | H268: http://10.16.1.24/NCRM-WS/WmsService?wsdl | I268: =IF(ISERROR(F268), "缺SIT API URL", IF(F268=0, "缺SIT API URL", "")) | J268: =IF(ISERROR(G268), "缺UAT API URL", IF(G268=0, "缺UAT API URL", "")) | K268: =IF(ISERROR(H268), "缺PROD API URL", IF(H268=0, "缺PROD API URL", ""))
A269: 272 | B269: 272_GetCusKYC | C269: SIT API URL | D269: UAT API URL | E269: PROD API URL | F269: http://10.11.34.237/NCRM-WS/WmsService?wsdl | G269: http://10.11.42.113/NCRM-WS/WmsService?wsdl | H269: http://10.16.1.24/NCRM-WS/WmsService?wsdl | I269: =IF(ISERROR(F269), "缺SIT API URL", IF(F269=0, "缺SIT API URL", "")) | J269: =IF(ISERROR(G269), "缺UAT API URL", IF(G269=0, "缺UAT API URL", "")) | K269: =IF(ISERROR(H269), "缺PROD API URL", IF(H269=0, "缺PROD API URL", ""))
A270: 273 | B270: 273_LoginValidate | C270: SIT API URL | D270: UAT API URL | E270: PROD API URL | F270: http://10.11.37.16/IDPortal/ | G270: http://10.11.42.84/IDPortal/ | H270: http://10.15.1.182/IDPortal/ | I270: =IF(ISERROR(F270), "缺SIT API URL", IF(F270=0, "缺SIT API URL", "")) | J270: =IF(ISERROR(G270), "缺UAT API URL", IF(G270=0, "缺UAT API URL", "")) | K270: =IF(ISERROR(H270), "缺PROD API URL", IF(H270=0, "缺PROD API URL", ""))
... A302: 305 | B302: 305_Inv010_T | C302: SIT API URL | D302: UAT API URL | E302: PROD API URL | F302: http://10.11.140.110/[交易類別]/[API名稱] | G302: http://10.11.152.110/[交易類別]/[API名稱] | H302: 申請中 | I302: =IF(ISERROR(F302), "缺SIT API URL", IF(F302=0, "缺SIT API URL", "")) | J302: =IF(ISERROR(G302), "缺UAT API URL", IF(G302=0, "缺UAT API URL", "")) | K302: =IF(ISERROR(H302), "缺PROD API URL", IF(H302=0, "缺PROD API URL", ""))
A303: 306 | B303: 306_TPSPS_GetCustomerData | C303: SIT API URL | D303: UAT API URL | E303: PROD API URL | F303: http://10.11.36.35:888/TMUAPIService/TPSPS_GetCustomerData?xmlData=<?xml version="1.0" encoding="UTF-8" ?><InfoTPSPS_GetCustomerDataIn><MsgID/><ChlName/><ChlEJNo/><ChlSendTime/><CustomerID>A1328080040</CustomerID><ChlIP/></InfoTPSPS_GetCustomerDataIn> | I303: =IF(ISERROR(F303), "缺SIT API URL", IF(F303=0, "缺SIT API URL", "")) | J303: =IF(ISERROR(G303), "缺UAT API URL", IF(G303=0, "缺UAT API URL", "")) -> 缺UAT API URL | K303: =IF(ISERROR(H303), "缺PROD API URL", IF(H303=0, "缺PROD API URL", "")) -> 缺PROD API URL
A304: 307 | B304: 307_TPSPS_GetNAVData | C304: SIT API URL | D304: UAT API URL | E304: PROD API URL | F304: http://10.11.36.35:888/TMUAPIService/TPSPS_GetNAVData?xmlData=<?xml version="1.0" encoding="UTF-8" ?><InfoTPSPS_GetNAVDataIn><MsgID/><ChlName/><ChlEJNo/><ChlSendTime></ChlSendTime><ChlIP/></InfoTPSPS_GetNAVDataIn> | I304: =IF(ISERROR(F304), "缺SIT API URL", IF(F304=0, "缺SIT API URL", "")) | J304: =IF(ISERROR(G304), "缺UAT API URL", IF(G304=0, "缺UAT API URL", "")) -> 缺UAT API URL | K304: =IF(ISERROR(H304), "缺PROD API URL", IF(H304=0, "缺PROD API URL", "")) -> 缺PROD API URL
A305: 308 | B305: 308_HKSPS_GetCustomerData | C305: SIT API URL | D305: UAT API URL | E305: PROD API URL | F305: http://10.11.36.35:888/TMUAPIService/HKSPS_GetCustomerData?xmlData=<?xml version="1.0" encoding="UTF-8" ?><InfoHKSPS_GetCustomerDataIn><MsgID/><ChlName/><ChlEJNo/><ChlSendTime/><CustomerID>Z4999537480TW</CustomerID><ChlIP/></InfoHKSPS_GetCustomerDataIn> | I305: =IF(ISERROR(F305), "缺SIT API URL", IF(F305=0, "缺SIT API URL", "")) | J305: =IF(ISERROR(G305), "缺UAT API URL", IF(G305=0, "缺UAT API URL", "")) -> 缺UAT API URL | K305: =IF(ISERROR(H305), "缺PROD API URL", IF(H305=0, "缺PROD API URL", "")) -> 缺PROD API URL
A306: 309 | B306: 309_HKSPS_GetNAVData | C306: SIT API URL | D306: UAT API URL | E306: PROD API URL | F306: http://10.11.36.35:888/TMUAPIService/HKSPS_GetNAVData?xmlData=<?xml version="1.0" encoding="UTF-8" ?><InfoHKSPS_GetNAVDataIn><MsgID/><ChlName/><ChlEJNo/><ChlSendTime></ChlSendTime><ChlIP/></InfoHKSPS_GetNAVDataIn> | I306: =IF(ISERROR(F306), "缺SIT API URL", IF(F306=0, "缺SIT API URL", "")) | J306: =IF(ISERROR(G306), "缺UAT API URL", IF(G306=0, "缺UAT API URL", "")) -> 缺UAT API URL | K306: =IF(ISERROR(H306), "缺PROD API URL", IF(H306=0, "缺PROD API URL", "")) -> 缺PROD API URL
A307: 310 | B307: 310_MXRep_GetRPTotalAMT | C307: SIT API URL | D307: UAT API URL | E307: PROD API URL | F307: http://10.11.36.35:888/TMUAPIService/MXRep_GetRPTotalAMT?xmlData=<?xml version="1.0" encoding="UTF-8" ?><InfoMXRep_GetRPTotalAMTIn><MsgID/><ChlName/><ChlEJNo/><ChlSendTime/><CustomerID>P2517236280</CustomerID><ChlIP/></InfoMXRep_GetRPTotalAMTIn> | I307: =IF(ISERROR(F307), "缺SIT API URL", IF(F307=0, "缺SIT API URL", "")) | J307: =IF(ISERROR(G307), "缺UAT API URL", IF(G307=0, "缺UAT API URL", "")) -> 缺UAT API URL | K307: =IF(ISERROR(H307), "缺PROD API URL", IF(H307=0, "缺PROD API URL", "")) -> 缺PROD API URL
A308: 311 | B308: 311_MXRep_GetRPDetail | C308: SIT API URL | D308: UAT API URL | E308: PROD API URL | F308: http://10.11.36.35:888/TMUAPIService/MXRep_GetRPDetail?xmlData=<?xml version="1.0" encoding="UTF-8" ?><InfoMXRep_GetRPDetailIn><MsgID/><ChlName/><ChlEJNo/><ChlSendTime/><CustomerID>P2517236280</CustomerID><ChlIP/></InfoMXRep_GetRPDetailIn> | I308: =IF(ISERROR(F308), "缺SIT API URL", IF(F308=0, "缺SIT API URL", "")) | J308: =IF(ISERROR(G308), "缺UAT API URL", IF(G308=0, "缺UAT API URL", "")) -> 缺UAT API URL | K308: =IF(ISERROR(H308), "缺PROD API URL", IF(H308=0, "缺PROD API URL", "")) -> 缺PROD API URL
A309: 312 | B309: 312_MXRep_GetBondTx | C309: SIT API URL | D309: UAT API URL | E309: PROD API URL | F309: http://10.11.36.35:888/TMUAPIService/MXRep_GetBondTx?xmlData=<?xml version="1.0" encoding="UTF-8" ?><InfoMXRep_GetBondTxIn><MsgID/><ChlName/><ChlEJNo/><ChlSendTime/><CustomerID>VGBD26940</CustomerID><StartDate>2022/01/01</StartDate><EndDate>2024/01/01</EndDate><ChlIP/></InfoMXRep_GetBondTxIn> | I309: =IF(ISERROR(F309), "缺SIT API URL", IF(F309=0, "缺SIT API URL", "")) | J309: =IF(ISERROR(G309), "缺UAT API URL", IF(G309=0, "缺UAT API URL", "")) -> 缺UAT API URL | K309: =IF(ISERROR(H309), "缺PROD API URL", IF(H309=0, "缺PROD API URL", "")) -> 缺PROD API URL
A310: 313 | B310: 313_MXRep_GetRPTx | C310: SIT API URL | D310: UAT API URL | E310: PROD API URL | F310: http://10.11.36.35:888/TMUAPIService/MXRep_GetRPTx?xmlData=<?xml version="1.0" encoding="UTF-8" ?><InfoMXRep_GetRPTxIn><MsgID/><ChlName/><ChlEJNo/><ChlSendTime/><CustomerID>A1522014940</CustomerID><StartDate>2022/01/01</StartDate><EndDate>2024/01/01</EndDate><ChlIP/></InfoMXRep_GetRPTxIn> | I310: =IF(ISERROR(F310), "缺SIT API URL", IF(F310=0, "缺SIT API URL", "")) | J310: =IF(ISERROR(G310), "缺UAT API URL", IF(G310=0, "缺UAT API URL", "")) -> 缺UAT API URL | K310: =IF(ISERROR(H310), "缺PROD API URL", IF(H310=0, "缺PROD API URL", "")) -> 缺PROD API URL
A311: 314 | B311: 314_funDoAutoInvestment | C311: SIT API URL | D311: UAT API URL | E311: PROD API URL | F311: http://10.11.35.51:8024/GDWebService.asmx/funDoAutoInvestment | G311: http://10.11.66.136:8024/GDWebService.asmx/funDoAutoInvestment | H311: http://10.16.1.29:8024/GDWebService.asmx/funDoAutoInvestment | I311: =IF(ISERROR(F311), "缺SIT API URL", IF(F311=0, "缺SIT API URL", "")) | J311: =IF(ISERROR(G311), "缺UAT API URL", IF(G311=0, "缺UAT API URL", "")) | K311: =IF(ISERROR(H311), "缺PROD API URL", IF(H311=0, "缺PROD API URL", ""))
A312: 315 | B312: 315_funGetAutoInvestment | C312: SIT API URL | D312: UAT API URL | E312: PROD API URL | F312: http://10.11.35.51:8024/GDWebService.asmx/funGetAutoInvestment | G312: http://10.11.66.136:8024/GDWebService.asmx/funGetAutoInvestment | H312: http://10.16.1.29:8024/GDWebService.asmx/funGetAutoInvestment | I312: =IF(ISERROR(F312), "缺SIT API URL", IF(F312=0, "缺SIT API URL", "")) | J312: =IF(ISERROR(G312), "缺UAT API URL", IF(G312=0, "缺UAT API URL", "")) | K312: =IF(ISERROR(H312), "缺PROD API URL", IF(H312=0, "缺PROD API URL", ""))
A313: 316 | B313: 316_GetGoldPrice | C313: SIT API URL | D313: UAT API URL | E313: PROD API URL | F313: http://10.11.22.126:886/ETSRateService.asm/GetGoldPrice | G313: http://10.11.66.160:886/ETSRateService.asm/GetGoldPrice | H313: http://10.16.1.11:886/ETSRateService.asm/GetGoldPrice | I313: =IF(ISERROR(F313), "缺SIT API URL", IF(F313=0, "缺SIT API URL", "")) | J313: =IF(ISERROR(G313), "缺UAT API URL", IF(G313=0, "缺UAT API URL", "")) | K313: =IF(ISERROR(H313), "缺PROD API URL", IF(H313=0, "缺PROD API URL", ""))
A314: 317 | B314: 317_GetGoldPriceHistory | C314: SIT API URL | D314: UAT API URL | E314: PROD API URL | F314: http://10.11.22.126:886/ETSRateService.asm/GetGoldPriceHistory | G314: http://10.11.66.160:886/ETSRateService.asm/GetGoldPriceHistory | H314: http://10.16.1.11:886/ETSRateService.asm/GetGoldPriceHistory | I314: =IF(ISERROR(F314), "缺SIT API URL", IF(F314=0, "缺SIT API URL", "")) | J314: =IF(ISERROR(G314), "缺UAT API URL", IF(G314=0, "缺UAT API URL", "")) | K314: =IF(ISERROR(H314), "缺PROD API URL", IF(H314=0, "缺PROD API URL", ""))
A315: 318 | B315: 318_GetCusRiskMsg | C315: SIT API URL | D315: UAT API URL | E315: PROD API URL | F315: http://10.11.34.237/NCRM-WS/WmsService?wsdl | G315: http://10.11.42.113/NCRM-WS/WmsService?wsdl | H315: http://10.16.1.24/NCRM-WS/WmsService?wsdl | I315: =IF(ISERROR(F315), "缺SIT API URL", IF(F315=0, "缺SIT API URL", "")) | J315: =IF(ISERROR(G315), "缺UAT API URL", IF(G315=0, "缺UAT API URL", "")) | K315: =IF(ISERROR(H315), "缺PROD API URL", IF(H315=0, "缺PROD API URL", ""))
A316: 319 | B316: 319_GetKYCQuestion | C316: SIT API URL | D316: UAT API URL | E316: PROD API URL | F316: http://10.11.34.237/NCRM-WS/WmsService?wsdl | G316: http://10.11.42.113/NCRM-WS/WmsService?wsdl | H316: http://10.16.1.24/NCRM-WS/WmsService?wsdl | I316: =IF(ISERROR(F316), "缺SIT API URL", IF(F316=0, "缺SIT API URL", "")) | J316: =IF(ISERROR(G316), "缺UAT API URL", IF(G316=0, "缺UAT API URL", "")) | K316: =IF(ISERROR(H316), "缺PROD API URL", IF(H316=0, "缺PROD API URL", ""))
A317: 320 | B317: 320_QueTest | C317: SIT API URL | D317: UAT API URL | E317: PROD API URL | F317: http://10.11.34.237/NCRM-WS/WmsService?wsdl | G317: http://10.11.42.113/NCRM-WS/WmsService?wsdl | H317: http://10.16.1.24/NCRM-WS/WmsService?wsdl | I317: =IF(ISERROR(F317), "缺SIT API URL", IF(F317=0, "缺SIT API URL", "")) | J317: =IF(ISERROR(G317), "缺UAT API URL", IF(G317=0, "缺UAT API URL", "")) | K317: =IF(ISERROR(H317), "缺PROD API URL", IF(H317=0, "缺PROD API URL", ""))
A318: 321 | B318: 321_QueTestConfirm | C318: SIT API URL | D318: UAT API URL | E318: PROD API URL | F318: http://10.11.34.237/NCRM-WS/WmsService?wsdl | G318: http://10.11.42.113/NCRM-WS/WmsService?wsdl | H318: http://10.16.1.24/NCRM-WS/WmsService?wsdl | I318: =IF(ISERROR(F318), "缺SIT API URL", IF(F318=0, "缺SIT API URL", "")) | J318: =IF(ISERROR(G318), "缺UAT API URL", IF(G318=0, "缺UAT API URL", "")) | K318: =IF(ISERROR(H318), "缺PROD API URL", IF(H318=0, "缺PROD API URL", ""))
A319: 322 | B319: 322_GetRecommPdf | C319: SIT API URL | D319: UAT API URL | E319: PROD API URL | F319: http://10.11.34.237/NCRM-WS/WmsService?wsdl | G319: http://10.11.42.113/NCRM-WS/WmsService?wsdl | H319: http://10.16.1.24/NCRM-WS/WmsService?wsdl | I319: =IF(ISERROR(F319), "缺SIT API URL", IF(F319=0, "缺SIT API URL", "")) | J319: =IF(ISERROR(G319), "缺UAT API URL", IF(G319=0, "缺UAT API URL", "")) | K319: =IF(ISERROR(H319), "缺PROD API URL", IF(H319=0, "缺PROD API URL", ""))
A320: 323 | B320: 323_GetFundRankings | C320: SIT API URL | D320: UAT API URL | E320: PROD API URL | F320: http://10.11.34.237/NCRM-WS/WmsService?wsdl | G320: http://10.11.42.113/NCRM-WS/WmsService?wsdl | H320: http://10.16.1.24/NCRM-WS/WmsService?wsdl | I320: =IF(ISERROR(F320), "缺SIT API URL", IF(F320=0, "缺SIT API URL", "")) | J320: =IF(ISERROR(G320), "缺UAT API URL", IF(G320=0, "缺UAT API URL", "")) | K320: =IF(ISERROR(H320), "缺PROD API URL", IF(H320=0, "缺PROD API URL", ""))
A321: 324 | B321: 324_GetCusGolds | C321: SIT API URL | D321: UAT API URL | E321: PROD API URL | F321: http://10.11.34.237/NCRM-WS/WmsService?wsdl | G321: http://10.11.42.113/NCRM-WS/WmsService?wsdl | H321: http://10.16.1.24/NCRM-WS/WmsService?wsdl | I321: =IF(ISERROR(F321), "缺SIT API URL", IF(F321=0, "缺SIT API URL", "")) | J321: =IF(ISERROR(G321), "缺UAT API URL", IF(G321=0, "缺UAT API URL", "")) | K321: =IF(ISERROR(H321), "缺PROD API URL", IF(H321=0, "缺PROD API URL", ""))
A322: 325 | B322: 325_Inv110_F | C322: SIT API URL | D322: UAT API URL | E322: PROD API URL | F322: http://10.11.34.63:8085/iFundWebService/iFundWebService.asmx | G322: http://10.11.42.20:8081/iFundWebService/iFundWebService.asmx | H322: http://10.16.1.20:8085/iFundWebService/iFundWebService.asmx | I322: =IF(ISERROR(F322), "缺SIT API URL", IF(F322=0, "缺SIT API URL", "")) | J322: =IF(ISERROR(G322), "缺UAT API URL", IF(G322=0, "缺UAT API URL", "")) | K322: =IF(ISERROR(H322), "缺PROD API URL", IF(H322=0, "缺PROD API URL", ""))
... A345: 348 | B345: 348_LINEBinding | C345: SIT API URL | D345: UAT API URL | E345: PROD API URL | F345: http://10.11.136.8/wise/1/checkbinding | G345: http://10.11.148.8/wise/1/checkbinding | H345: http://110.16.1.129/wise/1/checkbinding | I345: =IF(ISERROR(F345), "缺SIT API URL", IF(F345=0, "缺SIT API URL", "")) | J345: =IF(ISERROR(G345), "缺UAT API URL", IF(G345=0, "缺UAT API URL", "")) | K345: =IF(ISERROR(H345), "缺PROD API URL", IF(H345=0, "缺PROD API URL", ""))
A346: 349 | B346: 349_MMA_OnlineCase1 | C346: SIT API URL | D346: UAT API URL | E346: PROD API URL | I346: =IF(ISERROR(F346), "缺SIT API URL", IF(F346=0, "缺SIT API URL", "")) -> 缺SIT API URL | J346: =IF(ISERROR(G346), "缺UAT API URL", IF(G346=0, "缺UAT API URL", "")) -> 缺UAT API URL | K346: =IF(ISERROR(H346), "缺PROD API URL", IF(H346=0, "缺PROD API URL", "")) -> 缺PROD API URL
A347: 350 | B347: 350_CHKP2PMAC | C347: SIT API URL | D347: UAT API URL | E347: PROD API URL | F347: http://10.11.62.91:8733/ENCGWS/ENCService.svc | G347: http://10.11.63.105:8733/ENCGWS/ENCService.svc | H347: http://10.19.1.130:8733/ENCGWS/ENCService.svc | I347: =IF(ISERROR(F347), "缺SIT API URL", IF(F347=0, "缺SIT API URL", "")) | J347: =IF(ISERROR(G347), "缺UAT API URL", IF(G347=0, "缺UAT API URL", "")) | K347: =IF(ISERROR(H347), "缺PROD API URL", IF(H347=0, "缺PROD API URL", ""))
A348: 351 | B348: 351_MAKP2PMAC | C348: SIT API URL | D348: UAT API URL | E348: PROD API URL | F348: http://10.11.62.91:8733/ENCGWS/ENCService.svc | G348: http://10.11.63.105:8733/ENCGWS/ENCService.svc | H348: http://10.19.1.130:8733/ENCGWS/ENCService.svc | I348: =IF(ISERROR(F348), "缺SIT API URL", IF(F348=0, "缺SIT API URL", "")) | J348: =IF(ISERROR(G348), "缺UAT API URL", IF(G348=0, "缺UAT API URL", "")) | K348: =IF(ISERROR(H348), "缺PROD API URL", IF(H348=0, "缺PROD API URL", ""))
A349: 352 | B349: 352_GetLastStatementInfo | C349: SIT API URL | D349: UAT API URL | E349: PROD API URL | F349: http://10.11.140.161/api/Account/GetLastStatementInfo | I349: =IF(ISERROR(F349), "缺SIT API URL", IF(F349=0, "缺SIT API URL", "")) | J349: =IF(ISERROR(G349), "缺UAT API URL", IF(G349=0, "缺UAT API URL", "")) -> 缺UAT API URL | K349: =IF(ISERROR(H349), "缺PROD API URL", IF(H349=0, "缺PROD API URL", "")) -> 缺PROD API URL
A350: 353 | B350: 353_GetStatementBarCode | C350: SIT API URL | D350: UAT API URL | E350: PROD API URL | F350: http://10.11.140.161/api/Account/GetStatementBarCode | I350: =IF(ISERROR(F350), "缺SIT API URL", IF(F350=0, "缺SIT API URL", "")) | J350: =IF(ISERROR(G350), "缺UAT API URL", IF(G350=0, "缺UAT API URL", "")) -> 缺UAT API URL | K350: =IF(ISERROR(H350), "缺PROD API URL", IF(H350=0, "缺PROD API URL", "")) -> 缺PROD API URL
A351: 354 | B351: 354_GetOutstandingBalance | C351: SIT API URL | D351: UAT API URL | E351: PROD API URL | F351: http://10.11.140.161/api/Account/GetOutstandingBalance | I351: =IF(ISERROR(F351), "缺SIT API URL", IF(F351=0, "缺SIT API URL", "")) | J351: =IF(ISERROR(G351), "缺UAT API URL", IF(G351=0, "缺UAT API URL", "")) -> 缺UAT API URL | K351: =IF(ISERROR(H351), "缺PROD API URL", IF(H351=0, "缺PROD API URL", "")) -> 缺PROD API URL
A352: 355 | B352: 355_GetStatementBalance | C352: SIT API URL | D352: UAT API URL | E352: PROD API URL | F352: /api/Account/GetStatementBalance | I352: =IF(ISERROR(F352), "缺SIT API URL", IF(F352=0, "缺SIT API URL", "")) | J352: =IF(ISERROR(G352), "缺UAT API URL", IF(G352=0, "缺UAT API URL", "")) -> 缺UAT API URL | K352: =IF(ISERROR(H352), "缺PROD API URL", IF(H352=0, "缺PROD API URL", "")) -> 缺PROD API URL
A353: 356 | B353: 356_GetFeaturedCards | C353: SIT API URL | D353: UAT API URL | E353: PROD API URL | F353: http://10.11.140.161/api/ApplyCard/GetFeaturedCards | I353: =IF(ISERROR(F353), "缺SIT API URL", IF(F353=0, "缺SIT API URL", "")) | J353: =IF(ISERROR(G353), "缺UAT API URL", IF(G353=0, "缺UAT API URL", "")) -> 缺UAT API URL | K353: =IF(ISERROR(H353), "缺PROD API URL", IF(H353=0, "缺PROD API URL", "")) -> 缺PROD API URL
A354: 357 | B354: 357_DisplayCardState | C354: SIT API URL | D354: UAT API URL | E354: PROD API URL | F354: http://10.11.140.161/api/DisplayCard/DisplayCardState | I354: =IF(ISERROR(F354), "缺SIT API URL", IF(F354=0, "缺SIT API URL", "")) | J354: =IF(ISERROR(G354), "缺UAT API URL", IF(G354=0, "缺UAT API URL", "")) -> 缺UAT API URL | K354: =IF(ISERROR(H354), "缺PROD API URL", IF(H354=0, "缺PROD API URL", "")) -> 缺PROD API URL
A355: 358 | B355: 358_DisplayCardActivate | C355: SIT API URL | D355: UAT API URL | E355: PROD API URL | F355: http://10.11.140.161/api/DisplayCard/DisplayCardActivate | I355: =IF(ISERROR(F355), "缺SIT API URL", IF(F355=0, "缺SIT API URL", "")) | J355: =IF(ISERROR(G355), "缺UAT API URL", IF(G355=0, "缺UAT API URL", "")) -> 缺UAT API URL | K355: =IF(ISERROR(H355), "缺PROD API URL", IF(H355=0, "缺PROD API URL", "")) -> 缺PROD API URL
A356: 359 | B356: 359_DisplayCardAuthenticate | C356: SIT API URL | D356: UAT API URL | E356: PROD API URL | F356: http://10.11.140.161/api/DisplayCard/DisplayCardAuthenticate | I356: =IF(ISERROR(F356), "缺SIT API URL", IF(F356=0, "缺SIT API URL", "")) | J356: =IF(ISERROR(G356), "缺UAT API URL", IF(G356=0, "缺UAT API URL", "")) -> 缺UAT API URL | K356: =IF(ISERROR(H356), "缺PROD API URL", IF(H356=0, "缺PROD API URL", "")) -> 缺PROD API URL
A357: 360 | B357: 360_CheckIfHoldValidCard | C357: SIT API URL | D357: UAT API URL | E357: PROD API URL | F357: http://10.11.140.161/api/Member/CheckIfHoldValidCard | I357: =IF(ISERROR(F357), "缺SIT API URL", IF(F357=0, "缺SIT API URL", "")) | J357: =IF(ISERROR(G357), "缺UAT API URL", IF(G357=0, "缺UAT API URL", "")) -> 缺UAT API URL | K357: =IF(ISERROR(H357), "缺PROD API URL", IF(H357=0, "缺PROD API URL", "")) -> 缺PROD API URL
A358: 361 | B358: 361_GetMyCards | C358: SIT API URL | D358: UAT API URL | E358: PROD API URL | F358: http://10.11.140.161/api/Member/GetMyCards | I358: =IF(ISERROR(F358), "缺SIT API URL", IF(F358=0, "缺SIT API URL", "")) | J358: =IF(ISERROR(G358), "缺UAT API URL", IF(G358=0, "缺UAT API URL", "")) -> 缺UAT API URL | K358: =IF(ISERROR(H358), "缺PROD API URL", IF(H358=0, "缺PROD API URL", "")) -> 缺PROD API URL
A359: 362 | B359: 362_CheckCardNo | C359: SIT API URL | D359: UAT API URL | E359: PROD API URL | F359: http://10.11.140.161/api/Member/CheckCardNo | I359: =IF(ISERROR(F359), "缺SIT API URL", IF(F359=0, "缺SIT API URL", "")) | J359: =IF(ISERROR(G359), "缺UAT API URL", IF(G359=0, "缺UAT API URL", "")) -> 缺UAT API URL | K359: =IF(ISERROR(H359), "缺PROD API URL", IF(H359=0, "缺PROD API URL", "")) -> 缺PROD API URL
A360: 363 | B360: 363_GetMemberInfo | C360: SIT API URL | D360: UAT API URL | E360: PROD API URL | F360: http://10.11.140.161/api/Member/GetMemberInfo | I360: =IF(ISERROR(F360), "缺SIT API URL", IF(F360=0, "缺SIT API URL", "")) | J360: =IF(ISERROR(G360), "缺UAT API URL", IF(G360=0, "缺UAT API URL", "")) -> 缺UAT API URL | K360: =IF(ISERROR(H360), "缺PROD API URL", IF(H360=0, "缺PROD API URL", "")) -> 缺PROD API URL
... A366: 369 | B366: 369_queryRealTimePrtLosSum | C366: SIT API URL | D366: UAT API URL | E366: PROD API URL | F366: http://servicerd.sinotrade.com.tw/divo/api/v1/dawho/queryRealTimePrtLosSum | I366: =IF(ISERROR(F366), "缺SIT API URL", IF(F366=0, "缺SIT API URL", "")) | J366: =IF(ISERROR(G366), "缺UAT API URL", IF(G366=0, "缺UAT API URL", "")) -> 缺UAT API URL | K366: =IF(ISERROR(H366), "缺PROD API URL", IF(H366=0, "缺PROD API URL", "")) -> 缺PROD API URL
A367: 370 | B367: 370_Inv38_E | C367: SIT API URL | D367: UAT API URL | E367: PROD API URL | F367: https://mmafundrwdtest.moneydj.com/GetForeignStock/ShareSharesData.aspx | G367: https://mmafundrwdtest.moneydj.com/GetForeignStock/ShareSharesData.aspx | H367: https://mmafund.moneydj.com/GetForeignStock/ShareSharesData.aspx | I367: =IF(ISERROR(F367), "缺SIT API URL", IF(F367=0, "缺SIT API URL", "")) | J367: =IF(ISERROR(G367), "缺UAT API URL", IF(G367=0, "缺UAT API URL", "")) | K367: =IF(ISERROR(H367), "缺PROD API URL", IF(H367=0, "缺PROD API URL", ""))
A368: 371 | B368: 371_Inv39_E | C368: SIT API URL | D368: UAT API URL | E368: PROD API URL | F368: https://mmafundrwdtest.moneydj.com/GetForeignStock/ShareSharesData.aspx | G368: https://mmafundrwdtest.moneydj.com/GetForeignStock/ShareSharesData.aspx | H368: https://mmafund.moneydj.com/GetForeignStock/ShareSharesData.aspx | I368: =IF(ISERROR(F368), "缺SIT API URL", IF(F368=0, "缺SIT API URL", "")) | J368: =IF(ISERROR(G368), "缺UAT API URL", IF(G368=0, "缺UAT API URL", "")) | K368: =IF(ISERROR(H368), "缺PROD API URL", IF(H368=0, "缺PROD API URL", ""))
A369: 372 | B369: 372_Inv40_E | C369: SIT API URL | D369: UAT API URL | E369: PROD API URL | F369: https://mmafundrwdtest.moneydj.com/GetForeignStock/ShareSharesData.aspx | G369: https://mmafundrwdtest.moneydj.com/GetForeignStock/ShareSharesData.aspx | H369: https://mmafund.moneydj.com/GetForeignStock/ShareSharesData.aspx | I369: =IF(ISERROR(F369), "缺SIT API URL", IF(F369=0, "缺SIT API URL", "")) | J369: =IF(ISERROR(G369), "缺UAT API URL", IF(G369=0, "缺UAT API URL", "")) | K369: =IF(ISERROR(H369), "缺PROD API URL", IF(H369=0, "缺PROD API URL", ""))
A370: 373 | B370: 373_Inv41_E | C370: SIT API URL | D370: UAT API URL | E370: PROD API URL | F370: https://10.11.37.36:8080/etfAPIM/etf/qry/q060 | G370: https://10.11.66.149:8080/etfAPIM/etf/qry/q060 | H370: https://10.16.1.61:8080/etfAPIM/etf/qry/q060 | I370: =IF(ISERROR(F370), "缺SIT API URL", IF(F370=0, "缺SIT API URL", "")) | J370: =IF(ISERROR(G370), "缺UAT API URL", IF(G370=0, "缺UAT API URL", "")) | K370: =IF(ISERROR(H370), "缺PROD API URL", IF(H370=0, "缺PROD API URL", ""))
A371: 374 | B371: 374_Inv01_O | C371: SIT API URL | D371: UAT API URL | E371: PROD API URL | F371: https://10.11.37.36:8080/etfAPIM/ | G371: https://10.11.66.149:8080/etfAPIM/ | H371: https://10.16.1.61:8080/etfAPIM/ | I371: =IF(ISERROR(F371), "缺SIT API URL", IF(F371=0, "缺SIT API URL", "")) | J371: =IF(ISERROR(G371), "缺UAT API URL", IF(G371=0, "缺UAT API URL", "")) | K371: =IF(ISERROR(H371), "缺PROD API URL", IF(H371=0, "缺PROD API URL", ""))
A372: 375 | B372: 375_Inv02_O | C372: SIT API URL | D372: UAT API URL | E372: PROD API URL | F372: https://10.11.37.36:8080/etfAPIM/ | G372: https://10.11.66.149:8080/etfAPIM/ | H372: https://10.16.1.61:8080/etfAPIM/ | I372: =IF(ISERROR(F372), "缺SIT API URL", IF(F372=0, "缺SIT API URL", "")) | J372: =IF(ISERROR(G372), "缺UAT API URL", IF(G372=0, "缺UAT API URL", "")) | K372: =IF(ISERROR(H372), "缺PROD API URL", IF(H372=0, "缺PROD API URL", ""))
A373: 376 | B373: 376_Inv03_O | C373: SIT API URL | D373: UAT API URL | E373: PROD API URL | F373: https://10.11.37.36:8080/etfAPIM/ | G373: https://10.11.66.149:8080/etfAPIM/ | H373: https://10.16.1.61:8080/etfAPIM/ | I373: =IF(ISERROR(F373), "缺SIT API URL", IF(F373=0, "缺SIT API URL", "")) | J373: =IF(ISERROR(G373), "缺UAT API URL", IF(G373=0, "缺UAT API URL", "")) | K373: =IF(ISERROR(H373), "缺PROD API URL", IF(H373=0, "缺PROD API URL", ""))
A374: 377 | B374: 377_Inv04_O | C374: SIT API URL | D374: UAT API URL | E374: PROD API URL | F374: https://10.11.37.36:8080/etfAPIM/ | G374: https://10.11.66.149:8080/etfAPIM/ | H374: https://10.16.1.61:8080/etfAPIM/ | I374: =IF(ISERROR(F374), "缺SIT API URL", IF(F374=0, "缺SIT API URL", "")) | J374: =IF(ISERROR(G374), "缺UAT API URL", IF(G374=0, "缺UAT API URL", "")) | K374: =IF(ISERROR(H374), "缺PROD API URL", IF(H374=0, "缺PROD API URL", ""))
A375: 378 | B375: 378_Inv05_O | C375: SIT API URL | D375: UAT API URL | E375: PROD API URL | F375: https://10.11.37.36:8080/etfAPIM/ | G375: https://10.11.66.149:8080/etfAPIM/ | H375: https://10.16.1.61:8080/etfAPIM/ | I375: =IF(ISERROR(F375), "缺SIT API URL", IF(F375=0, "缺SIT API URL", "")) | J375: =IF(ISERROR(G375), "缺UAT API URL", IF(G375=0, "缺UAT API URL", "")) | K375: =IF(ISERROR(H375), "缺PROD API URL", IF(H375=0, "缺PROD API URL", ""))
A376: 379 | B376: 379_Inv06_O | C376: SIT API URL | D376: UAT API URL | E376: PROD API URL | F376: https://10.11.37.36:8080/etfAPIM/ | G376: https://10.11.66.149:8080/etfAPIM/ | H376: https://10.16.1.61:8080/etfAPIM/ | I376: =IF(ISERROR(F376), "缺SIT API URL", IF(F376=0, "缺SIT API URL", "")) | J376: =IF(ISERROR(G376), "缺UAT API URL", IF(G376=0, "缺UAT API URL", "")) | K376: =IF(ISERROR(H376), "缺PROD API URL", IF(H376=0, "缺PROD API URL", ""))
A377: 380 | B377: 380_Inv07_O | C377: SIT API URL | D377: UAT API URL | E377: PROD API URL | F377: https://10.11.37.36:8080/etfAPIM/ | G377: https://10.11.66.149:8080/etfAPIM/ | H377: https://10.16.1.61:8080/etfAPIM/ | I377: =IF(ISERROR(F377), "缺SIT API URL", IF(F377=0, "缺SIT API URL", "")) | J377: =IF(ISERROR(G377), "缺UAT API URL", IF(G377=0, "缺UAT API URL", "")) | K377: =IF(ISERROR(H377), "缺PROD API URL", IF(H377=0, "缺PROD API URL", ""))
A378: 381 | B378: 381_Inv08_O | C378: SIT API URL | D378: UAT API URL | E378: PROD API URL | F378: https://10.11.37.36:8080/etfAPIM/ | G378: https://10.11.66.149:8080/etfAPIM/ | H378: https://10.16.1.61:8080/etfAPIM/ | I378: =IF(ISERROR(F378), "缺SIT API URL", IF(F378=0, "缺SIT API URL", "")) | J378: =IF(ISERROR(G378), "缺UAT API URL", IF(G378=0, "缺UAT API URL", "")) | K378: =IF(ISERROR(H378), "缺PROD API URL", IF(H378=0, "缺PROD API URL", ""))
...

Sheet 0714更新
A1: No | B1: Dept 部別 | C1: Team 科別 | D1: SysCode 應用系統代碼 | E1: SysName 中文應用系統名稱 | F1: Sys English Name | G1: API Code API代碼
A2: 55 | B2: 商品應用部 | C2: 財富信託科 | D2: TWTXN00073 | E2: 智能理財系統 | F2: ibrain | G2: Inv001_A | H2: =_xlfn.CONCAT(A2,"_",G2) -> 55_Inv001_A | I2: Y | J2: Y
A3: 56 | B3: 商品應用部 | C3: 財富信託科 | D3: TWTXN00073 | E3: 智能理財系統 | F3: ibrain | G3: Inv002_A | H3: =_xlfn.CONCAT(A3,"_",G3) -> 56_Inv002_A | I3: Y | J3: Y
A4: 57 | B4: 商品應用部 | C4: 財富信託科 | D4: TWTXN00073 | E4: 智能理財系統 | F4: ibrain | G4: Inv003_A | H4: =_xlfn.CONCAT(A4,"_",G4) -> 57_Inv003_A | I4: Y | J4: Y
A5: 58 | B5: 商品應用部 | C5: 財富信託科 | D5: TWTXN00073 | E5: 智能理財系統 | F5: ibrain | G5: Inv004_A | H5: =_xlfn.CONCAT(A5,"_",G5) -> 58_Inv004_A | I5: Y | J5: Y
A6: 59 | B6: 商品應用部 | C6: 財富信託科 | D6: TWTXN00073 | E6: 智能理財系統 | F6: ibrain | G6: Inv005_A | H6: =_xlfn.CONCAT(A6,"_",G6) -> 59_Inv005_A | I6: Y | J6: Y
A7: 60 | B7: 商品應用部 | C7: 財富信託科 | D7: TWTXN00073 | E7: 智能理財系統 | F7: ibrain | G7: Inv006_A | H7: =_xlfn.CONCAT(A7,"_",G7) -> 60_Inv006_A | I7: Y | J7: Y
A8: 61 | B8: 商品應用部 | C8: 財富信託科 | D8: TWTXN00073 | E8: 智能理財系統 | F8: ibrain | G8: Inv007_A | H8: =_xlfn.CONCAT(A8,"_",G8) -> 61_Inv007_A | I8: Y | J8: Y
A9: 62 | B9: 商品應用部 | C9: 財富信託科 | D9: TWTXN00073 | E9: 智能理財系統 | F9: ibrain | G9: Inv008_A | H9: =_xlfn.CONCAT(A9,"_",G9) -> 62_Inv008_A | I9: Y | J9: Y
A10: 63 | B10: 商品應用部 | C10: 財富信託科 | D10: TWTXN00073 | E10: 智能理財系統 | F10: ibrain | G10: Inv009_A | H10: =_xlfn.CONCAT(A10,"_",G10) -> 63_Inv009_A | I10: Y | J10: Y
A11: 64 | B11: 商品應用部 | C11: 財富信託科 | D11: TWTXN00073 | E11: 智能理財系統 | F11: ibrain | G11: Inv010_A | H11: =_xlfn.CONCAT(A11,"_",G11) -> 64_Inv010_A | I11: Y | J11: Y
A12: 65 | B12: 商品應用部 | C12: 財富信託科 | D12: TWTXN00073 | E12: 智能理財系統 | F12: ibrain | G12: Inv011_A | H12: =_xlfn.CONCAT(A12,"_",G12) -> 65_Inv011_A | I12: Y | J12: Y
A13: 66 | B13: 商品應用部 | C13: 財富信託科 | D13: TWTXN00073 | E13: 智能理財系統 | F13: ibrain | G13: Inv012_A | H13: =_xlfn.CONCAT(A13,"_",G13) -> 66_Inv012_A | I13: Y | J13: Y
... A156: 209 | B156: 商品應用部 | C156: 財富信託科 | D156: BS09040 | E156: 財富交易OBU基金網銀系統 | F156: OBU | G156: Inv25_O | H156: =_xlfn.CONCAT(A156,"_",G156) -> 209_Inv25_O | I156: Y | J156: Y
A157: 267 | B157: 金融技術部 | C157: 資料庫應用科 | D157: BS09050 | E157: 新客戶關係暨財富管理系統 | F157: NCRM | G157: CheckCifEtfFg | H157: 267_CrossSaleCheck | I157: Y | J157: 267_CrossSaleCheck
A158: 268 | B158: 金融技術部 | C158: 資料庫應用科 | D158: BS09050 | E158: 新客戶關係暨財富管理系統 | F158: NCRM | G158: UpdateCifEtfFg | H158: 268_CrossSaleUpdate | I158: Y | J158: 268_CrossSaleUpdate
A159: 269 | B159: 金融技術部 | C159: 資料庫應用科 | D159: BS09050 | E159: 新客戶關係暨財富管理系統 | F159: NCRM | G159: RiskTest | H159: 269_InvProfileCalculate | I159: Y | J159: 269_InvProfileCalculate
A160: 270 | B160: 金融技術部 | C160: 資料庫應用科 | D160: BS09050 | E160: 新客戶關係暨財富管理系統 | F160: NCRM | G160: RiskTestConfirm | H160: 270_InsCusInvQuestionnaire | I160: Y | J160: 270_InsCusInvQuestionnaire
A161: 271 | B161: 金融技術部 | C161: 資料庫應用科 | D161: BS09050 | E161: 新客戶關係暨財富管理系統 | F161: NCRM | G161: GetD_Risk | H161: 271_GetCusFinanceStatus | I161: Y | J161: 271_GetCusFinanceStatus
A162: 272 | B162: 金融技術部 | C162: 資料庫應用科 | D162: BS09050 | E162: 新客戶關係暨財富管理系統 | F162: NCRM | G162: GetPdf | H162: 272_GetCusKYC | I162: Y | J162: 272_GetCusKYC
A163: 292 | B163: 商品應用部 | C163: 財富信託科 | D163: TWTXN00059 | E163: 財富交易網銀系統 | F163: iFund | G163: Inv104_F | H163: =_xlfn.CONCAT(A163,"_",G163) -> 292_Inv104_F | I163: Y | J163: Y
A164: 293 | B164: 商品應用部 | C164: 財富信託科 | D164: TWTXN00059 | E164: 財富交易網銀系統 | F164: iFund | G164: Inv105_F | H164: =_xlfn.CONCAT(A164,"_",G164) -> 293_Inv105_F | I164: Y | J164: Y
A165: 298 | B165: 商品應用部 | C165: 財富信託科 | D165: TWTXN00092 | E165: 信託後台API服務 | F165: iTrust | G165: Inv003_T | H165: =_xlfn.CONCAT(A165,"_",G165) -> 298_Inv003_T | I165: Y | J165: Y
A166: 299 | B166: 商品應用部 | C166: 財富信託科 | D166: TWTXN00092 | E166: 信託後台API服務 | F166: iTrust | G166: Inv004_T | H166: =_xlfn.CONCAT(A166,"_",G166) -> 299_Inv004_T | I166: Y | J166: Y
A167: 300 | B167: 商品應用部 | C167: 財富信託科 | D167: TWTXN00092 | E167: 信託後台API服務 | F167: iTrust | G167: Inv005_T | H167: =_xlfn.CONCAT(A167,"_",G167) -> 300_Inv005_T | I167: Y | J167: Y
A168: 301 | B168: 商品應用部 | C168: 財富信託科 | D168: TWTXN00092 | E168: 信託後台API服務 | F168: iTrust | G168: Inv006_T | H168: =_xlfn.CONCAT(A168,"_",G168) -> 301_Inv006_T | I168: Y | J168: Y
A169: 302 | B169: 商品應用部 | C169: 財富信託科 | D169: TWTXN00092 | E169: 信託後台API服務 | F169: iTrust | G169: Inv007_T | H169: =_xlfn.CONCAT(A169,"_",G169) -> 302_Inv007_T | I169: Y | J169: Y
A170: 303 | B170: 商品應用部 | C170: 財富信託科 | D170: TWTXN00092 | E170: 信託後台API服務 | F170: iTrust | G170: Inv008_T | H170: =_xlfn.CONCAT(A170,"_",G170) -> 303_Inv008_T | I170: Y | J170: Y
A171: 304 | B171: 商品應用部 | C171: 財富信託科 | D171: TWTXN00092 | E171: 信託後台API服務 | F171: iTrust | G171: Inv009_T | H171: =_xlfn.CONCAT(A171,"_",G171) -> 304_Inv009_T | I171: Y | J171: Y
A172: 305 | B172: 商品應用部 | C172: 財富信託科 | D172: TWTXN00092 | E172: 信託後台API服務 | F172: iTrust | G172: Inv010_T | H172: =_xlfn.CONCAT(A172,"_",G172) -> 305_Inv010_T | I172: Y | J172: Y
A173: 318 | B173: 金融技術部 | C173: 資料庫應用科 | D173: BS09050 | E173: 新客戶關係暨財富管理系統 | F173: NCRM | G173: GetCusRiskMsg | H173: =_xlfn.CONCAT(A173,"_",G173) -> 318_GetCusRiskMsg | I173: Y | J173: Y
A174: 319 | B174: 金融技術部 | C174: 資料庫應用科 | D174: BS09050 | E174: 新客戶關係暨財富管理系統 | F174: NCRM | G174: GetKYCQuestion | H174: =_xlfn.CONCAT(A174,"_",G174) -> 319_GetKYCQuestion | I174: Y | J174: Y
... A231: 424 | B231: 商品應用部 | C231: 財富信託科 | D231: TWTXN00073 | E231: 智能理財系統 | F231: ibrain | G231: Inv058_A | H231: =_xlfn.CONCAT(A231,"_",G231) -> 424_Inv058_A | I231: Y | J231: 424_Inv_058_A

Sheet 0721更新
D1: sheetname
A2: NCRM | B2: GetCusRiskMsg | C2: funGetCusRiskMsg | D2: =VLOOKUP(B2,'0714更新'!G:H,2,FALSE) -> 318_GetCusRiskMsg
A3: NCRM | B3: GetKYCQuestion | C3: funGetKYCQuestion | D3: =VLOOKUP(B3,'0714更新'!G:H,2,FALSE) -> 319_GetKYCQuestion
A4: NCRM | B4: QueTest | C4: funQueTest | D4: =VLOOKUP(B4,'0714更新'!G:H,2,FALSE) -> 320_QueTest
A5: NCRM | B5: QueTestConfirm | C5: funQueTestConfirm | D5: =VLOOKUP(B5,'0714更新'!G:H,2,FALSE) -> 321_QueTestConfirm
A6: NCRM | B6: GetRecommPdf | C6: funGetRecommPdf | D6: =VLOOKUP(B6,'0714更新'!G:H,2,FALSE) -> 322_GetRecommPdf
A7: NCRM | B7: GetFundRankings | C7: funGetFundRankings | D7: =VLOOKUP(B7,'0714更新'!G:H,2,FALSE) -> 323_GetFundRankings
A8: NCRM | B8: GetCusGolds | C8: funGetCusGolds | D8: =VLOOKUP(B8,'0714更新'!G:H,2,FALSE) -> 324_GetCusGolds
A9: OBU | B9: Inv11_O | C9: Qry040O | D9: =VLOOKUP(B9,'0714更新'!G:H,2,FALSE) -> 384_Inv11_O
A10: OBU | B10: Inv21_O | C10: Qry010O | D10: =VLOOKUP(B10,'0714更新'!G:H,2,FALSE) -> 394_Inv21_O
A11: OBU | B11: Inv13_O | C11: Tx045O | D11: =VLOOKUP(B11,'0714更新'!G:H,2,FALSE) -> 386_Inv13_O
A12: iFund | B12: Inv001_F | C12: funGetAllCertificate | D12: =VLOOKUP(B12,'0714更新'!G:H,2,FALSE) -> 104_Inv001_F
A13: iFund | B13: Inv069_F | C13: funconfirmSwitchRecord | D13: =VLOOKUP(B13,'0714更新'!G:H,2,FALSE) -> 172_Inv069_F
... A32: iTrust | B32: Inv010_T | C32: funGetSompanystockSum | D32: =VLOOKUP(B32,'0714更新'!G:H,2,FALSE) -> 305_Inv010_T

Sheet 0728更新
D1: sheetname
A2: iFund | B2: Inv072_F | C2: funCreateAirGeneralRecord | D2: =VLOOKUP(B2,'0714更新'!G:H,2,FALSE) -> 175_Inv072_F
A3: iFund | B3: Inv074_F | C3: funCreateAirAutoRecord | D3: =VLOOKUP(B3,'0714更新'!G:H,2,FALSE) -> 177_Inv074_F
A4: iFund | B4: Inv076_F | C4: funCreateAirRedemRecord | D4: =VLOOKUP(B4,'0714更新'!G:H,2,FALSE) -> 179_Inv076_F
A5: iFund | B5: Inv078_F | C5: funCreateAirSwitchRecord | D5: =VLOOKUP(B5,'0714更新'!G:H,2,FALSE) -> 181_Inv078_F
A6: iFund | B6: Inv080_F | C6: funJCreateAirEIMSubsRecord | D6: =VLOOKUP(B6,'0714更新'!G:H,2,FALSE) -> 183_Inv080_F
A7: iFund | B7: Inv082_F | C7: funJ_CreateAirBondRedemRecord | D7: =VLOOKUP(B7,'0714更新'!G:H,2,FALSE) -> 185_Inv082_F
A8: iFund | B8: Inv085_F | C8: funJ_CreateBondSubsRecord | D8: =VLOOKUP(B8,'0714更新'!G:H,2,FALSE) -> 188_Inv085_F
A9: iFund | B9: Inv087_F | C9: funJ_CreateBondRedemRecord | D9: =VLOOKUP(B9,'0714更新'!G:H,2,FALSE) -> 190_Inv087_F
A10: iFund | B10: Inv102_F | C10: funJ_ConfirmAirBondSubsRecord | D10: =VLOOKUP(B10,'0714更新'!G:H,2,FALSE) -> 191_Inv102_F
A11: iFund | B11: Inv103_F | C11: funJ_CreateAirBondSubsRecord | D11: =VLOOKUP(B11,'0714更新'!G:H,2,FALSE) -> 192_Inv103_F
A12: iFund | B12: Inv104_F | C12: funConfirmAirGainLoss | D12: =VLOOKUP(B12,'0714更新'!G:H,2,FALSE) -> 292_Inv104_F
A13: iFund | B13: Inv105_F | C13: funCreateAirGainLoss | D13: =VLOOKUP(B13,'0714更新'!G:H,2,FALSE) -> 293_Inv105_F
... A19: ibrain | B19: Inv028_A | C19: 確認資產再平衡交易 | D19: =VLOOKUP(B19,'0714更新'!G:H,2,FALSE) -> 82_Inv028_A

Sheet Summary
B2: TW IB/MB API List
B3: ='API Index'!B2 -> Version: | C3: ='API Index'!C2 -> 45471 | E3: No | F3: (多重項目)
I4: No | J4: (全部)
B5: Dept/Team/System | C5: 計數 - No | E5: 部/科/System | F5: 計數 - API Code API代碼
B6: 商品應用部 | C6: 210 | E6: 營運應用部 | F6: 1 | H6: 已回覆 | I6: 計數 - No | J6: Customer Transaction related | N6: Interface Contact Window
B7: 金融市場科 | C7: 6 | E7: 徵審應用科 | F7: 1 | H7: 45002 | I7: Dept/Team | J7: Callee | K7: Caller | L7: SSO | M7: 總計 | N7: Main Owner | O7: Proxy
B8: ETS | C8: 4 | E8: LoanApply | F8: 1 | I8: 金融技術部 | J8: 28 | M8: 28
B9: FOREX | C9: 2 | E9: 數位應用部 | F9: 19 | H9: v | I9: 架構應用科 | J9: 8 | M9: 8 | N9: 梁志偉 | O9: 林威佑
B10: 信用支付科 | C10: 11 | E10: 自助交易科 | F10: 5 | H10: v | I10: 資料庫應用科 | J10: 20 | M10: 20 | N10: 黃智剛 | O10: 林琬婷
B11: EWEB | C11: 11 | E11: FEP | F11: 5 | I11: 數位應用部 | J11: 81 | K11: 30 | L11: 2 | M11: 113
B12: 財富信託科 | C12: 193 | E12: 行動應用科 | F12: 1 | H12: v | I12: TST | K12: 13 | M12: 13 | N12: 梁志偉 | O12: 謝佩錡
B13: ETF | C13: 37 | E13: iBranch | F13: 1 | H13: v | I13: 企網平台科 | J13: 5 | K13: 6 | L13: 1 | M13: 12 | N13: 郭思廷 | O13: 吳文瑞
B14: ibrain | C14: 49 | E14: 數支應用科 | F14: 13 | H14: v | I14: 自助交易科 | J14: 24 | M14: 24 | N14: 楊勝富 | O14: 邱子芸
B15: iFund | C15: 101 | E15: PayBill | F15: 11 | H15: v | I15: 行動應用科 | J15: 5 | M15: 5 | N15: 喻璽 | O15: 吳育慶
B16: iTrust | C16: 4 | E16: BSPSearch | F16: 2 | H16: v | I16: 個網平台科 | J16: 4 | M16: 4 | N16: 賴怡婷 | O16: 林素娟
B17: OBU | C17: 1 | E17: 商品應用部 | F17: 89 | H17: v | I17: 通路應用科 | J17: 21 | K17: 5 | M17: 26 | N17: 黃國堂 | O17: 林彥良
B18: INS | C18: 1 | E18: 金融市場科 | F18: 12 | I18: 數支應用科 | J18: 22 | K18: 6 | L18: 1 | M18: 29 | N18: 汪冠宏 | O18: 翁岳駿
B19: 金融技術部 | C19: 8 | E19: TPSPS | F19: 2 | H19: v | I19: 永豐金證券 -系統開發一部 | J19: 5 | M19: 5
B20: 架構應用科 | C20: 2 | E20: HKSPS | F20: 2 | I20: 電子交易科 | J20: 5 | M20: 5 | N20: 卓崇聖 | O20: 喻璽
B21: TWIDPortal | C21: 2 | E21: MXREP | F21: 4 | H21: v | I21: 核心應用部 | J21: 4 | M21: 4
B22: 資料庫應用科 | C22: 6 | E22: Gold Business Systematic Investment Plan System | F22: 4 | H22: v | I22: 放款外匯科 | J22: 3 | M22: 3 | N22: 陳東隆 | O22: 施宗佑
B23: NCRM | C23: 6 | E23: 信用支付科 | F23: 13 | I23: 核心規劃科 | J23: 1 | M23: 1 | N23: 游鯉菁 | O23: 陳睿緯
B24: 核心應用部 | C24: 3 | E24: EWEB | F24: 13 | H24: v | I24: 商品應用部 | J24: 339 | M24: 339
B25: 放款外匯科 | C25: 3 | E25: 財富信託科 | F25: 64 | H25: v | I25: 金融市場科 | J25: 19 | M25: 19 | N25: 陶惟傑 | O25: 許南妮
B26: VISA DIRECT | C26: 3 | E26: ETF | F26: 4 | H26: v | I26: 信用支付科 | J26: 36 | M26: 36 | N26: 邵方明 | O26: 吳紫瑜
B27: 數位應用部 | C27: 53 | E27: ibrain | F27: 4 | I27: 財富信託科 | J27: 284 | M27: 284 | N27: 謝佩錡 | O27: 黃嘉皇
B28: 企網平台科 | C28: 11 | E28: iFund | F28: 20 | H28: v | I28: 營運應用部 | J28: 7 | M28: 7
B29: EAINET | C29: 1 | E29: iTrust | F29: 8 | H29: v | I29: 平台應用科 | J29: 1 | M29: 1 | N29: 蔡秋汶 | O29: 翁淑婉
B30: EVENTSITE | C30: 4 | E30: OBU | F30: 24 | H30: v | I30: 徵審應用科 | J30: 3 | M30: 3 | N30: 曾宏善 | O30: 廖萍志
B31: MMAB2B | C31: 6 | E31: INSAG | F31: 4 | I31: 營運發展科 | J31: 3 | M31: 3 | N31: 魏品軒 | O31: 賴佳慧
B32: 自助交易科 | C32: 16 | E32: 核心應用部 | F32: 1 | I32: 總計 | J32: 464 | K32: 30 | L32: 2 | M32: 496
B33: FEP | C33: 8 | E33: 核心規劃科 | F33: 1
B34: SMTP | C34: 8 | E34: ACCT_NTFY | F34: 1
B35: 個網平台科 | C35: 4 | E35: 金融技術部 | F35: 8
B36: AuthCenter | C36: 1 | E36: 架構應用科 | F36: 1
B37: FundInfo | C37: 3 | E37: LINE BC | F37: 1
B38: 通路應用科 | C38: 15 | E38: 資料庫應用科 | F38: 7
B39: BILLHUNTER | C39: 1 | E39: NCRM | F39: 7
B40: Branch | C40: 3 | E40: 永豐金證券 -系統開發一部 | F40: 5
B41: CSS | C41: 2 | E41: 電子交易科 | F41: 5
B42: FCMVIDEO | C42: 6 | E42: sinotrade | F42: 5
B43: PDF | C43: 1 | E43: 總計 | F43: 123
B44: SmartBot | C44: 2
B45: 數支應用科 | C45: 7
B46: O2O | C46: 2
B47: PayBill | C47: 3
B48: WebATM | C48: 1
B49: Trust Web | C49: 1
B50: 營運應用部 | C50: 6
B51: 平台應用科 | C51: 1
B52: EDM | C52: 1
B53: 徵審應用科 | C53: 2
B54: LoanApply | C54: 2
B55: 營運發展科 | C55: 3
... B58: 總計 | C58: 280

Sheet Callee Progress
B1: ='API Index'!B2 -> Version: | C1: ='API Index'!C2 -> 45471
B2: Alive 維運中 | C2: (多重項目)
C4: Type
C5: 計數 - No | D5: DEV/UT Rate | E5: 計數 - No 的加總 | F5: DEV/UT Rate 的加總 | I5: Interface Contact Window
B6: Dept部/Section科 | C6: Callee | D6: Callee | I6: Main Owner | J6: Proxy
B7: 核心應用部 | C7: 4 | D7: 1 | E7: 4 | F7: 1
B8: 放款外匯科 | C8: 3 | D8: 1 | E8: 3 | F8: 1
B9: 核心規劃科 | C9: 1 | D9: 1 | E9: 1 | F9: 1
B10: 商品應用部 | C10: 331 | D10: 1 | E10: 331 | F10: 1
B11: 金融市場科 | C11: 17 | D11: 1 | E11: 17 | F11: 1
B12: 信用支付科 | C12: 36 | D12: 1 | E12: 36 | F12: 1
B13: 財富信託科 | C13: 278 | D13: 1 | E13: 278 | F13: 1
B14: 金融技術部 | C14: 28 | D14: 1 | E14: 28 | F14: 1
B15: 架構應用科 | C15: 8 | D15: 1 | E15: 8 | F15: 1
B16: 資料庫應用科 | C16: 20 | D16: 1 | E16: 20 | F16: 1
B17: 數位應用部 | C17: 70 | D17: 1 | E17: 70 | F17: 1
B18: 企網平台科 | C18: 2 | D18: 1 | E18: 2 | F18: 1
... B30: 總計 | C30: 445 | D30: 1 | E30: 445 | F30: 1

Sheet 工作表4
A1: API collection | B1: (多重項目)
A3: 列標籤 | B3: 計數 - API Code API代碼
A4: 總計

Sheet Caller API
B1: ='Callee Progress'!B1 -> Version: | C1: ='Callee Progress'!C1 -> 45471
B5: Caller API 開發單測進度 : | E5: =AVERAGE(H8:H30) -> 1 | I5: YYYY/MM/DD
I6: 開發單測完成日
B7: Dept 部別 | C7: Team 科別 | D7: Type | E7: SysName / DB AccountName | F7: SysOwner | G7: Phase | H7: Dev完成率 | I7: Dev/UT Date | J7: Caller/Callee | K7: Expose API Name | L7: Remark 備註 | M7: API No. | N7: API Code API代碼 | O7: API Section API中英文名稱 | P7: Description API中文說明
A8: 1 | B8: 金融技術部 | C8: 架構應用科 | D8: 即時交易推播 | E8: 身分認證中心 | F8: 梁志偉 | G8: P1 | H8: 1 | I8: 45382 | J8: Caller | K8: PushNotification | L8: 系統呼叫網行銀 | X8: DeepLink
A9: 2 | B9: 數位應用部 | C9: 自助交易科 | D9: 即時交易推播 | E9: FEP跨行前置系統 | F9: 謝汰嵻 | G9: P1 | H9: 1 | I9: 45289 | J9: Caller | K9: PushNotification | L9: 系統呼叫網行銀 | M9: 227 | N9: NWC | O9: 關閉無卡提款(推播部分) | P9: 關閉無卡提款(推播部分)_狀態更新 | X9: SSOAuthentication
A10: 3 | B10: 數位應用部 | C10: 自助交易科 | D10: 即時交易推播 | E10: FEP無卡提款 | F10: 謝汰嵻 | G10: P1 | H10: 1 | I10: 45260 | J10: Caller | K10: CardlessWithdraw | L10: 系統呼叫網行銀 | M10: N/A | N10: ATM上的交易 | O10: 無卡提款 (ATM) | P10: 無卡提款(推播通知) | X10: getCustomerInfo
A11: 4 | B11: 金融技術部 | C11: 架構應用科 | D11: 即時交易推播 | E11: 開放API服務系統 | F11: 李騫政 | G11: P1 | H11: 1 | I11: 45382 | J11: Caller | K11: PushNotification | L11: 系統呼叫網行銀 | X11: CardlessWithdraw
A12: 5 | B12: 核心應用部 | C12: 核心規劃科 | D12: 即時交易推播 | E12: T24帳務訊息通知 | F12: 游鯉菁 | G12: P1 | H12: 1 | I12: 45322 | J12: Caller | K12: PushNotification | L12: 系統呼叫網行銀 | X12: SpecialRevolvingLoan
A13: 6 | B13: 商品應用部 | C13: 財富信託科 | D13: 即時交易推播 | E13: 美股/ETF | F13: 陳琦龍 | G13: P1 | H13: 1 | I13: 45351 | J13: Caller | K13: PushNotification | L13: 系統呼叫網行銀 | X13: PushNotification
A14: 7 | B14: 商品應用部 | C14: 財富信託科 | D14: 即時交易推播 | E14: 空地對接 | F14: 陳琦龍 | G14: P1 | H14: 1 | I14: 45351 | J14: Caller | K14: PushNotification | L14: 系統呼叫網行銀 | X14: ShoppingCartFundID
A15: 8 | B15: 金融技術部 | C15: 資料庫應用科 | D15: 批次交易推播 | E15: UnicaUser (DB) | F15: 楊雅慧 | G15: P1 | H15: 1 | I15: 45596 | J15: Caller | K15: PushNotification | L15: 系統呼叫網行銀 | X15: WatchList
A16: 9 | B16: 商品應用部 | C16: 財富信託科 | D16: 批次交易推播 | E16: ai_user (DB) | F16: 謝佩錡 | G16: P1 | H16: 1 | I16: 45351 | J16: Caller | K16: PushNotification | L16: 系統呼叫網行銀 | X16: sendVideoVerifyResult
A17: 10 | B17: 商品應用部 | C17: 財富信託科 | D17: 批次交易推播 | E17: ddsc (DB) | F17: 李佳欣 | G17: P1 | H17: 1 | I17: 45382 | J17: Caller | K17: PushNotification | L17: 系統呼叫網行銀
A18: 11 | B18: 證券系統開發一部 | C18: 電子交易科 | D18: 證券便利金 | E18: 大戶投APP | F18: 卓崇聖 | G18: P1 | H18: 1 | I18: 45443 | J18: Caller | K18: SpecialRevolvingLoan | L18: 系統呼叫網行銀
A19: 12 | B19: 數位應用部 | C19: 數支應用科 | D19: 即時交易推播 | E19: O2O金流服務系統 | F19: 賴長春 | G19: P1 | H19: 1 | I19: 45289 | J19: Caller | K19: PushNotification | L19: 系統呼叫網行銀 | M19: 439 | N19: PushNotification | O19: PushNotification | P19: funlink推播發送
A20: 13 | B20: 數位應用部 | C20: 個網平台科 | D20: 基金購物車 | E20: 基金資訊源(新理財資訊網) | F20: 林如瑩 | G20: P1 | H20: 1 | I20: 45322 | J20: Caller | K20: getShoppingCartFundID | L20: 系統呼叫網行銀 | M20: 476 | N20: getShoppingCartFundID | O20: getShoppingCartFundID | P20: getShoppingCartFundID
A21: 14 | B21: 數位應用部 | C21: 個網平台科 | D21: 基金購物車 | E21: 基金資訊源(新理財資訊網) | F21: 林如瑩 | G21: P1 | H21: 1 | I21: 45322 | J21: Caller | K21: updateShopingCartFundID | L21: 系統呼叫網行銀 | M21: 477 | N21: updateShopingCartFundID | O21: updateShopingCartFundID | P21: updateShopingCartFundID
A22: 15 | B22: 數位應用部 | C22: 個網平台科 | D22: 觀察清單 | E22: 基金資訊源(新理財資訊網) | F22: 林如瑩 | G22: P1 | H22: 1 | I22: 45322 | J22: Caller | K22: getWatchList | L22: 系統呼叫網行銀 | M22: 478 | N22: getWatchList | O22: getWatchList | P22: getWatchList
A23: 16 | B23: 數位應用部 | C23: 個網平台科 | D23: 觀察清單 | E23: 基金資訊源(新理財資訊網) | F23: 林如瑩 | G23: P1 | H23: 1 | I23: 45322 | J23: Caller | K23: saveWatchList | L23: 系統呼叫網行銀 | M23: 479 | N23: saveWatchList | O23: saveWatchList | P23: saveWatchList
A24: 17 | B24: 數位應用部 | C24: 通路應用科 | D24: 即時交易推播 | E24: 客服中心網路電話系統 | F24: 蔡騰輝 | G24: P1 | H24: 1 | I24: 45382 | J24: Caller | K24: PushNotification | L24: 系統呼叫網行銀
A25: 18 | B25: 數位應用部 | C25: 通路應用科 | D25: 視訊驗證結果 | E25: 客服中心網路電話系統 | F25: 蔡騰輝 | G25: P1 | H25: 1 | I25: 45289 | J25: Caller | K25: sendVideoVerifyResult | L25: 系統呼叫網行銀
A26: 19 | B26: 金融技術部 | C26: 資料庫應用科 | D26: 即時交易推播 | E26: 點數管理系統 | F26: 何欣蓓 | G26: P1 | H26: 1 | I26: 45473 | J26: Caller | K26: PushNotification | L26: 系統呼叫網行銀
A27: 20 | B27: 金融技術部 | C27: 資料庫應用科 | D27: 批次交易推播 | E27: 點數管理系統 | F27: 何欣蓓 | G27: P1 | H27: 1 | I27: 45443 | J27: Caller | K27: PushNotification | L27: 系統呼叫網行銀
A28: 21 | B28: 商品應用部 | C28: 信用支付科 | D28: 即時交易推播 | E28: 信用卡營運系統 | F28: 邵方明 | G28: P1 | H28: 1 | I28: 45322 | J28: Caller | K28: PushNotification | L28: 信用卡/簽帳金融卡即時消費通知
A29: 22 | B29: 商品應用部 | C29: 信用支付科 | D29: 即時交易推播 | E29: 信用卡營運系統 | F29: 邵方明 | G29: P1 | H29: 1 | I29: 45322 | J29: Caller | K29: PushNotification | L29: 信用卡帳單設定異動通知
A30: 23 | B30: 數位應用部 | C30: 數支應用科 | D30: 即時交易推播 | E30: 繳費網 | F30: 紀緯霖 | G30: P1 | H30: 1 | I30: 45289 | J30: Caller | K30: PushNotification | L30: 系統呼叫網行銀 | N30: RealTimePushNotification | O30: RealTimePushNotification | P30: 票交交易退款/取消推播發送
A31: 1 | B31: 金融技術部 | C31: 架構應用科 | D31: 網銀身分認證 | E31: APIM管理系統 | F31: 李騫政 | G31: P1 | H31: 1 | I31: 45382 | J31: Caller | K31: DeepLink | L31: 關聯系統
A32: 1 | B32: 數位應用部 | C32: 通路應用科 | D32: 網銀身分認證 | E32: 分行系統(Branch System) | F32: 林彥良 | G32: P2 | H32: 0 | J32: Caller | L32: 第一階段MMA還會在，所以分行系統呼叫的WCF不會變動，第二階段MMA也要換到新平台，所以提供給分行系統呼叫的WCF會調整成API的形式 | M32: 263 | N32: C012 | O32: 啟用網銀 Apply MMA | P32: 數位、雲端開戶啟用網銀
A33: 2 | B33: 數位應用部 | C33: 通路應用科 | D33: 網銀客戶查詢 | E33: 分行系統(Branch System) | F33: 林彥良 | G33: P2 | H33: 0 | J33: Caller | L33: 第一階段MMA還會在，所以分行系統呼叫的WCF不會變動，第二階段MMA也要換到新平台，所以提供給分行系統呼叫的WCF會調整成API的形式 | M33: 264 | N33: C013 | O33: MMA客戶狀態查詢、變更、新增 Inquery、Update、Add MMA Member Status | P33: MMA客戶狀態查詢、變更、新增 Inquery、Update、Add MMA Member Status
A34: 3 | B34: 數位應用部 | C34: 通路應用科 | D34: 網銀身分認證 | E34: 作業自動化中台 | F34: 魏金龍 | G34: P2 | H34: 0 | J34: Caller | L34: 第一階段MMA還會在，所以分行系統呼叫的WCF不會變動，第二階段MMA也要換到新平台，所以提供給分行系統呼叫的WCF會調整成API的形式 | M34: 418 | N34: C015 | O34: 啟用網銀 Apply MMA | P34: 數位、雲端開戶啟用網銀
A35: 4 | B35: 數位應用部 | C35: 數支應用科 | E35: 網路ATM3.0 | F35: 紀緯霖 | G35: P2 | H35: 0 | J35: Caller | M35: 425 | N35: IsSinoPacIP | O35: IsSinoPacIP | P35: 判斷是否以非行員身份在內部IP登入
A36: 5 | B36: 數位應用部 | C36: 數支應用科 | E36: 網路ATM3.0 | F36: 紀緯霖 | G36: P2 | H36: 0 | J36: Caller | M36: 426 | N36: TxnDetail | O36: TxnDetail | P36: 往來明細查詢
A37: 6 | B37: 數位應用部 | C37: 數支應用科 | E37: 豐收款 | F37: 張時達 | G37: P2 | H37: 0 | J37: Caller | M37: 427 | N37: MMALogin | O37: MMALogin | P37: MMA登入驗證
A38: 7 | B38: 數位應用部 | C38: 數支應用科 | E38: 豐收款 | F38: 田亦凡 | G38: P2 | H38: 0 | J38: Caller | M38: 428 | N38: IsMMA | O38: IsMMA | P38: 是否為MMA會員
A39: 8 | B39: 數位應用部 | C39: 數支應用科 | E39: 大咖App | F39: 張時達 | G39: P2 | H39: 0 | J39: Caller | M39: 429 | N39: G0102 | O39: G0102 | P39: ID 歸戶資料
C54: Phase 1 Infinity Exposed API Index List
B55: No | C55: Expose API Name | D55: Description | E55: Batch | F55: Start Date | G55: End Date | H55: Plan DeliveryDate | I55: Actual DeliveryDate
B56: 1 | C56: checkIP | D56: When the user logs in to MMA, we need to check if the user is in SinoPac IP, and if so, check if the login ID is of staff or not. If not, do not log the user in. | E56: Batch 2 | F56: 45170 | G56: 45189 | H56: 45191
B57: 2 | C57: SSO | D57: To enables users to securely authenticate with multiple applications and websites by using just one set of SSO token | E57: Batch 2 | F57: 45170 | G57: 45189 | H57: 45191
B58: 3 | C58: getCustomerInfo | D58: To get customer information if user has valid SSO Token | E58: Batch 2 | F58: 45170 | G58: 45189 | H58: 45191
B59: 4 | C59: Cardless Withdraw | D59: To Update the Cardless Withdraw status that the customer has already in ATM and withdraw money done. | E59: Batch 2 | F59: 45170 | G59: 45189 | H59: 45198
B60: 5 | C60: getShoppingCartFundID | D60: Retrieve New IB/MB Shopping Cart Fund IDs to Investment Site | E60: Batch 4 | F60: 45236 | G60: 45257 | H60: 45264
B61: 6 | C61: updateShopingCartFundID | D61: Update New IB/MB Shopping Cart Fund IDs from Investment Site | E61: Batch 4 | F61: 45236 | G61: 45257 | H61: 45264
B62: 7 | C62: saveWatchList | D62: Save User Watch List from Investment Site to New IB/MB DB | E62: Batch 4 | F62: 45236 | G62: 45257 | H62: 45264
B63: 8 | C63: getWatchList | D63: Retrieve User Watch List from New IB/MB to Investment Site | E63: Batch 4 | F63: 45236 | G63: 45257 | H63: 45264
B64: 9 | C64: CardlessWithDrawPushNotification | D64: To get Push notification and email for cardless withdrawal trigger from customer process at the ATM Side | E64: Batch 5 | F64: 45236 | G64: 45268 | H64: 45275
B65: 10 | C65: ApplySpecialRevolvingLoan | D65: Securities to apply special revolving loan | E65: Batch 5 | F65: 45236 | G65: 45268 | H65: 45275
B66: 11 | C66: WithdrawSpecialRevolvingLoan | D66: To withdraw securities and stock subscription | E66: Batch 5 | F66: 45236 | G66: 45268 | H66: 45275
B67: 12 | C67: PushNotification | D67: To get the real time push notifications for user actions | E67: Batch 5 | F67: 45236 | G67: 45268 | H67: 45275
B68: 13 | C68: sendVideoVerifyResult | D68: Share Video verification result to Video System | E68: Batch 5 | F68: 45236 | G68: 45268 | H68: 45275
B83: 網銀身分認證 | C83: 系統/帳號名稱 | E83: 經管單位/經管人員 | F83: 新網銀TST 窗口 | H83: 備註
B84: 行動網頁 | C84: funLink帳戶連結 | E84: 數支應用科/賴長春 | F84: 梁志偉
B85: 行銀 | C85: APIM管理系統 | E85: 架構應用科/李騫政 | F85: 梁志偉
B88: 即時交易推播 | C88: 系統/帳號名稱 | E88: 經管單位/經管人員 | F88: 新網銀TST 窗口 | H88: 備註
B89: API | C89: 跨行前置系統 | E89: 自助交易科/謝汰嵻 | F89: 吳育慶
C90: 叫號系統 | E90: 通路應用科/陳金龍 | F90: 吳育慶
C91: 身分認證中心 | E91: 架構應用科/梁志偉 | F91: 吳育慶
C92: 開放API服務系統 | E92: 架構應用科/李騫政 | F92: 吳育慶
C93: 空地對接 | E93: 財富信託科/陳琦龍 | F93: 吳育慶
C94: 核心系統 | E94: 核心規劃科/楊怡娟 | F94: 吳育慶
B97: 批次交易推播 | C97: 帳號名稱 | E97: 經管單位/經管人員 | F97: 新網銀TST 窗口 | H97: 備註
B98: 資料庫 | C98: UnicaUser | E98: 資料庫應用科/楊雅慧 | F98: 吳育慶
C99: ai_user | E99: 財富信託科/謝佩錡 | F99: 吳育慶
C100: ddsc | E100: 財富信託科/李佳欣 | F100: 吳育慶
C101: EAINETUser | E101: 企網平台科/徐睿宏 | F101: 吳育慶
B104: 證券便利金 | C104: 系統/帳號名稱 | E104: 經管單位/經管人員 | F104: 新網銀TST 窗口 | H104: 備註
B105: API | C105: 大戶投APP | E105: 永豐金證券 | F105: 卓崇聖
C106: 大戶投APP | E106: 永豐金證券 | F106: 卓崇聖
B109: 無卡提款狀態更新&推播發送 | C109: 系統/帳號名稱 | E109: 經管單位/經管人員 | F109: 新網銀TST 窗口 | H109: 備註
B110: API | C110: FEP | E110: 自助交易科/謝汰嵻 | F110: 吳育慶

Sheet API Index
B2: Version: | C2: 45471 | F2: API 目錄 Index | N2: 不得晚於2023/12/15
D3: Callee or Caller =行動銀行MB/個網銀MMA/大戶DAWHO | N3: YYYY/MM/DD
L4: 下架日 | N4: 開發單測完成日
B5: No | C5: Dept 部別 | D5: Team 科別 | E5: SysCode 應用系統代碼 | F5: SysName 中文應用系統名稱 | G5: Sys English Name | H5: API Code API代碼 | I5: API Name/Doc Section API中英文名稱 | J5: Description API中文說明 | K5: Alive 維運中 | L5: EndDate 預計下架日(YYYYMMDD) | M5: Dev完成率 | N5: Dev/UT Date | O5: Caller/Callee | P5: Remark 備註 | Q5: Request Content String | R5: Response Content String | S5: API collection | T5: URL待補 | U5: TST Dev% | V5: TST UT%
B6: 001 | C6: 商品應用部 | D6: 金融市場科 | E6: TWTXN00046 | F6: 敲價系統(Electronic Treasury Trading System) | G6: ETS | H6: RequestSpot | I6: 換匯取價 Request FX or GOLD Spot Rate | J6: 換匯取價 RequestSpotRate | K6: Y | M6: 1 | N6: 44927 | O6: Callee | Q6: http://10.11.22.126:886/ETSRateService.asmx/RequestSpot?intSource=8&strKBrNo=769&strRBrNo=006&strBuyCcy=EUR&strSellCcy=USD&decBuyAmt=0&decSellAmt=120000&strXmp=1&strNote=1&strBU=D&strCustId=87654321&strVerify=1001 | R6: <?xml version="1.0" encoding="utf-8" ?> <ReponseSpot> <ReturnRate> <SerialNo>2110007</SerialNo> <RetCode>1</RetCode> <RetMessage>254138556441300708785898874</RetMessage> <VerifyStr>1001</VerifyStr> <ValidSec>35</ValidSec> <TradeDate>2022/08/29 00:00:00</TradeDate> <ValueDate>2022/08/29 00:00:00</ValueDate> <KBrNo>769</KBrNo> <RBrNo>006</RBrNo> <SBrNo>006</SBrNo> <DealNo /> <BuyCcy>EUR</BuyCcy> <BuyAmount>117911.78000</BuyAmount> <SellCcy>USD</SellCcy> <SellAmount>120000.00000</SellAmount> <EmpFlag>1</EmpFlag> <NoteFlag>1</NoteFlag> <BUFlag>D</BUFlag> <TxSelect>1</TxSelect> <TxType>0</TxType> <TxPair>EUR/USD</TxPair> <MidlRate>1.02172</MidlRate> <MrktRate>1.02171</MrktRate> <CostRate>1.02021</CostRate> <ListRate>1.01771</ListRate> <DoneRate>1.01771</DoneRate> <OriginalAmount>120000.00000</OriginalAmount> <EquvUsdAmount>120000.00</EquvUsdAmount> <EquvBaseAmount>3614787.00</EquvBaseAmount> <SettleFlag>1</SettleFlag> <TxRemark /> <CustId>87654321</CustId> <CustName /> <CptyCode /> <AOCode /> <KinUserId /> <KinSUserId /> </ReturnRate> </ReponseSpot>
B7: 002 | C7: 商品應用部 | D7: 金融市場科 | E7: TWTXN00046 | F7: 敲價系統(Electronic Treasury Trading System) | G7: ETS | H7: RequestSpot2 | I7: 換匯取價-優利定存 RequestSpot2 | J7: 換匯取價-優利定存 RequestSpot2 | K7: Y | M7: 1 | N7: 44927 | O7: Callee | Q7: http://10.11.22.126:886/ETSRateService.asmx/RequestSpot2?intSource=8&strKBrNo=769&strRBrNo=006&strBuyCcy=EUR&strSellCcy=USD&decBuyAmt=0&decSellAmt=720000&strXmp=1&strNote=1&strBU=D&strCustId=87654321&strVerify=1002 | R7: <?xml version="1.0" encoding="utf-8" ?> <ReponseSpot> <ReturnRate> <SerialNo>2110012</SerialNo> <RetCode>1</RetCode> <RetMessage>254138556441900708785898874</RetMessage> <VerifyStr>1002</VerifyStr> <ValidSec>45</ValidSec> <TradeDate>2022/08/29 00:00:00</TradeDate> <ValueDate>2022/08/29 00:00:00</ValueDate> <KBrNo>769</KBrNo> <RBrNo>006</RBrNo> <SBrNo>006</SBrNo> <DealNo /> <BuyCcy>EUR</BuyCcy> <BuyAmount>707470.69000</BuyAmount> <SellCcy>USD</SellCcy> <SellAmount>720000.00000</SellAmount> <EmpFlag>1</EmpFlag> <NoteFlag>1</NoteFlag> <BUFlag>D</BUFlag> <TxSelect>1</TxSelect> <TxType>9</TxType> <TxPair>EUR/USD</TxPair> <MidlRate>1.02172</MidlRate> <MrktRate>1.02171</MrktRate> <CostRate>1.02021</CostRate> <ListRate>1.01771</ListRate> <DoneRate>1.01771</DoneRate> <OriginalAmount>720000.00000</OriginalAmount> <EquvUsdAmount>720000.00</EquvUsdAmount> <EquvBaseAmount>21688723.00</EquvBaseAmount> <SettleFlag>1</SettleFlag> <TxRemark /> <CustId>87654321</CustId> <CustName /> <CptyCode /> <AOCode /> <KinUserId /> <KinSUserId /> </ReturnRate> </ReponseSpot>
B8: 003 | C8: 商品應用部 | D8: 金融市場科 | E8: TWTXN00046 | F8: 敲價系統(Electronic Treasury Trading System) | G8: ETS | H8: InsertSpotDeal | I8: 換匯新增成交部位InsertSpotDeal | J8: 換匯新增成交部位InsertSpotDeal | K8: Y | M8: 1 | N8: 44927 | O8: Callee | Q8: http://10.11.22.126:886/ETSRateService.asmx/InsertSpotDeal?intSource=8&strDeal=<?xml version="1.0" encoding="utf-8" ?><ReponseSpot><ReturnRate><SerialNo>2110007</SerialNo><RetCode>1</RetCode><RetMessage>254138556441300708785898874</RetMessage><VerifyStr>1001</VerifyStr><ValidSec>35</ValidSec><TradeDate>2022/08/29</TradeDate><ValueDate>2022/08/29</ValueDate><KBrNo>769</KBrNo><RBrNo>006</RBrNo><SBrNo>006</SBrNo><DealNo /><BuyCcy>EUR</BuyCcy><BuyAmount>117911.78000</BuyAmount><SellCcy>USD</SellCcy><SellAmount>120000.00000</SellAmount><EmpFlag>1</EmpFlag><NoteFlag>1</NoteFlag><BUFlag>D</BUFlag><TxSelect>1</TxSelect><TxType>1</TxType><TxPair>EUR/USD</TxPair><MidlRate>1.02172</MidlRate><MrktRate>1.02171</MrktRate><CostRate>1.02021</CostRate><ListRate>1.01771</ListRate><DoneRate>1.01771</DoneRate><OriginalAmount>120000.00000</OriginalAmount><EquvUsdAmount>120000.00</EquvUsdAmount><EquvBaseAmount>3614787.00</EquvBaseAmount><SettleFlag>1</SettleFlag><TxRemark /><CustId>87654321</CustId><CustName /><CptyCode /><AOCode /><KinUserId>MMA</KinUserId><KinSUserId /></ReturnRate></ReponseSpot> | R8: <?xml version="1.0" encoding="utf-8" ?> <string xmlns="http://ETSWeb.bsp:886/">0829769001</string>
B9: 004 | C9: 商品應用部 | D9: 金融市場科 | E9: TWTXN00046 | F9: 敲價系統(Electronic Treasury Trading System) | G9: ETS | H9: GetReferRate | I9: 換匯參考試算GetReferRate | J9: 換匯參考試算GetReferRate | K9: Y | M9: 1 | N9: 44927 | O9: Callee | Q9: http://10.11.22.126:886//ETSRateService.asmx/GetReferRate?decOriAmt=10000&strFrCcy=USD&strToCcy=TWD | R9: <?xml version="1.0" encoding="utf-8" ?> <ETSSpotDeal> <RefRate> <RetCode>1</RetCode> <RetMessage>OK</RetMessage> <NoteFlag>N</NoteFlag> <CrossRate>29.90000</CrossRate> <OriginalAmount>10000</OriginalAmount> <CrossAmount>299000.00000</CrossAmount> <CrossPair>USD/TWD</CrossPair> <CrossCost>29.94000</CrossCost> <TxPair>USD/TWD</TxPair> <ListBuy>29.90000</ListBuy> <ListSell>30.11000</ListSell> </RefRate> <RefRate> <RetCode>1</RetCode> <RetMessage>OK</RetMessage> <NoteFlag>Y</NoteFlag> <CrossRate>29.70000</CrossRate> <OriginalAmount>10000</OriginalAmount> <CrossAmount>297000.00000</CrossAmount> <CrossPair>USD/TWD</CrossPair> <CrossCost>29.94000</CrossCost> <TxPair>USD/TWD</TxPair> <ListBuy>29.70000</ListBuy> <ListSell>30.31000</ListSell> </RefRate> </ETSSpotDeal>
B10: 005 | C10: 商品應用部 | D10: 金融市場科 | E10: TWTXN00065 | F10: 外幣留單撮合服務(Foreign Exchange Order Service) | G10: FOREX | H10: FUNINSERTFXORDER | I10: 新增留單紀錄(InsertFxOrder) | J10: 新增留單紀錄(InsertFxOrder) | K10: D | M10: 1 | N10: 44927 | O10: Callee | P10: 新網銀說未來不打算保留此功能 | Q10: http://10.11.35.51:8091/FxOrderWebservice.asmx/funFxOrderWS?xmlData= <?xml version="1.0" encoding="UTF-8"?> <GEPS> <RqHeader> <MsgID>FUNINSERTFXORDER</MsgID> <MsgType>G</MsgType> <ChlName>NETBANK</ChlName> <ChlEJNo>MMA-FUNINSERTFXORDER-0002107727917</ChlEJNo> <ChlSendTime>2021/03/12 11:44:16.799</ChlSendTime> <TxnID>V2700</TxnID> <BranchID>SPHNETBANK01</BranchID> <TermID>FXORDER@NETBANK</TermID> <UserID/> <SignID/> </RqHeader> <SvcRq> <Rq> <ExpireDate>20210326</ExpireDate> <KBrNo>769</KBrNo> <RBrNo/> <OriginalAmount>100000.00000</OriginalAmount> <BuyCcy>JPY</BuyCcy> <BuyAmount>100000</BuyAmount> <SellCcy>USD</SellCcy> <SellAmount>0</SellAmount> <BUFlag>D</BUFlag> <TxPair>USD/JPY</TxPair> <QuoteSide>O</QuoteSide> <OrderRate>105</OrderRate> <CustId>A1211114150</CustId> <CustEmail>test@test</CustEmail> <DbAcct>01400800016326</DbAcct> <CrAcct>01400800016326</CrAcct> <DbRemark/> <CrRemark/> </Rq> </SvcRq> </GEPS> | R10: <?xml version="1.0" encoding="utf-8"?> <GEPS> <RsHeader> <RsStat> <RsStatCode>SUCCESS</RsStatCode> <Desc>新增留單成功</Desc> </RsStat> <Overrides><Override /> </Overrides> <ChlEJNo>MMA-FUNINSERTFXORDER-0002107727917</ChlEJNo> <EJNo>MMA-FUNINSERTFXORDER-0002107727917</EJNo> <RqTime>2021/03/12 11:44:16.799</RqTime> <RsTime>2021/3/12 上午 11:44:17</RsTime> </RsHeader> <SvcRs> <Rs> <ErrMessage>succeed:OK</ErrMessage> <OrderNo>20210312114417544USDJPY</OrderNo> </Rs> </SvcRs> </GEPS>
B11: 006 | C11: 商品應用部 | D11: 金融市場科 | E11: TWTXN00065 | F11: 外幣留單撮合服務(Foreign Exchange Order Service) | G11: FOREX | H11: FUNDELETEFXORDER | I11: 刪除留單紀錄(DeleteFxOrder) | J11: 刪除留單紀錄(DeleteFxOrder) | K11: D | M11: 1 | N11: 44927 | O11: 金融市場科 | P11: 新網銀說未來不打算保留此功能 | Q11: http://10.11.35.51:8091/FxOrderWebservice.asmx/funFxOrderWS?xmlData= <?xml version="1.0" encoding="UTF-8"?> <GEPS> <RqHeader> <MsgID>FUNDELETEFXORDER</MsgID> <MsgType>G</MsgType> <ChlName>NETBANK</ChlName> <ChlEJNo>MMA-FUNDELETEFXORDER-0002107733389</ChlEJNo> <ChlSendTime>2021/03/12 11:46:06.801</ChlSendTime> <TxnID>V2700</TxnID> <BranchID>SPHNETBANK01</BranchID> <TermID>FXORDER@NETBANK</TermID> <UserID/> <SignID/> </RqHeader> <SvcRq> <Rq> <OrderNo>20210312114417544USDJPY</OrderNo> <CustId>A1211114150</CustId> </Rq> </SvcRq> </GEPS> | R11: <?xml version="1.0" encoding="utf-8"?> <GEPS> <RsHeader> <RsStat> <RsStatCode>SUCCESS</RsStatCode> <Desc>刪除留單成功</Desc> </RsStat> <Overrides><Override /> </Overrides> <ChlEJNo>MMA-FUNDELETEFXORDER-0002107733389</ChlEJNo> <EJNo>MMA-FUNDELETEFXORDER-0002107733389</EJNo> <RqTime>2021/03/12 11:46:06.801</RqTime> <RsTime>2021/3/12 上午 11:46:07</RsTime> </RsHeader> <SvcRs> <Rs> <ErrMessage>succeed:OK</ErrMessage> </Rs> </SvcRs> </GEPS>
B12: 007 | C12: 商品應用部 | D12: 信用支付科 | E12: TWWEB00023 | F12: 信用卡網站後台維護系統(Credit Card) | G12: EWEB | H12: MemberRegisterCheckCardInfo | I12: MemberRegisterCardCheck | J12: MMA會員註冊檢核 | K12: Y | M12: 1 | N12: 45001 | O12: Callee | P12: 程式無異動，故不需另行開發 | Q12: {"Content":{"ID":"A151041672","Birthday":"19010101"},"Header":{"ApplicationName":"MMA","UserID":"A151041672"}} | R12: {"Result":{"Success":true,"Mobile":"0928XXX612","Email":"","IsPaperStatement":true},"Header":{"SessionID":"ks34t01tjjmmlejjbyqnrf2j","ApplicationName":"MMA","ReferenceNo":"ad6a85fb-d903-46fe-b01d-d1b4c3c9b172","UserID":"A151041672","RequestTime":"2022-08-26T11:17:20.5599317+08:00","TxCode":"","RemoteAddr":"10.11.36.146","PageName":"","IsWriteLog":true,"SsaToken":"","ClientRefNo":null,"ClientTimestamp":null},"ResultCode":"00","ResultMessage":"","Error":null}
B13: 008 | C13: 商品應用部 | D13: 信用支付科 | E13: TWWEB00023 | F13: 信用卡網站後台維護系統(Credit Card) | G13: EWEB | H13: LatestTx | I13: LatestTx | J13: 最新消費資料 | K13: Y | M13: 1 | N13: 45001 | O13: Callee | P13: 程式無異動，故不需另行開發 | Q13: {"Content":{"ID":"A131XXXX82"},"Header":{"ApplicationName":"EWEB2","UserID":"A131XXXX82"}} | R13: { "Result": { "IsCompanyUser": false, "Items": [ { "CardFlag": "1", "CardNo": "4XX1", "IsMobileCard": false, "AuthDate": "2021/12/27", "AuthTime": "14:06:11", "Memo": "永豐ＴａＰａｙ驗證ＥＰＯＳ商店 ", "AuthAmt": 4001.0, "AuthAmtDesc": "4,001 ", "CountryCode": "TW", "AuthResult": "成功" }, { "CardFlag": "1", "CardNo": "4XX1", "IsMobileCard": false, "AuthDate": "2021/12/23", "AuthTime": "18:23:36", "Memo": "永豐ＴａＰａｙ驗證ＥＰＯＳ商店 ", "AuthAmt": 4001.0, "AuthAmtDesc": "4,001 ", "CountryCode": "TW", "AuthResult": "成功" } ] }, "Header": { "SessionID": "", "ApplicationName": "EWEB2", "ReferenceNo": "7fa756e2-d3e0-4691-854b-7ba4c9320c76", "UserID": "A131022582", "RequestTime": "2022-09-01T09:45:13.8539161+08:00", "TxCode": "", "RemoteAddr": "10.11.33.39", "PageName": "", "IsWriteLog": true, "SsaToken": "", "ClientRefNo": "7fa756e2-d3e0-4691-854b-7ba4c9320c76", "ClientTimestamp": "2022-09-01T09:45:13.8539161+08:00" }, "ResultCode": "00", "ResultMessage": "", "Error": null }
B14: 009 | C14: 商品應用部 | D14: 信用支付科 | E14: TWWEB00023 | F14: 信用卡網站後台維護系統(Credit Card) | G14: EWEB | H14: OutstandingDetail | I14: OutstandingDetail | J14: 消費明細查詢 (未結帳) | K14: Y | M14: 1 | N14: 45001 | O14: Callee | P14: 程式無異動，故不需另行開發 | Q14: {"Content":{"ID":"A131XXXX82","DateYYYYMMDD":"","IsExcludePaidUp":true},"Header":{"ApplicationName":"EWEB2","UserID":"A131XXXX82"}} | R14: { "Result": { "IsExcludePaidUp": true, "Detail": [ { "CurrencyCode": "000", "CurrencyName": "臺幣", "PID": "A131XXXX82 ", "CARD_TYPE": "3", "CardLast4": "4XX3", "TXDATE": "2020/04/17", "DEDATE": "2020/04/19", "TXCODE": "", "MEMO": "A- 屈臣氏Ｓ０２３３伊通店 ", "TXCUR": " ", "TXAMT": "", "AMT": "333", "PROD": "420", "EMBOSSING_TYPE": "001", "CardNoLast4": "4XX3", "CARDNAME": "升等商務御璽卡" } ], "SubTotal": [ { "CurrencyCode": "000", "CurrencyName": "臺幣", "Count": 19, "SubTotalAmt": "18,790" } ], "IsCompanyUser": false }, "Header": { "SessionID": "", "ApplicationName": "EWEB2", "ReferenceNo": "e82cd68a-bf8a-4699-97b5-acbfe267853c", "UserID": "A131022582", "RequestTime": "2022-09-01T09:51:05.9653362+08:00", "TxCode": "", "RemoteAddr": "10.11.140.10", "PageName": "", "IsWriteLog": true, "SsaToken": "", "ClientRefNo": null, "ClientTimestamp": null }, "ResultCode": "00", "ResultMessage": "", "Error": null }
B15: 010 | C15: 商品應用部 | D15: 信用支付科 | E15: TWWEB00023 | F15: 信用卡網站後台維護系統(Credit Card) | G15: EWEB | H15: RecentBill | I15: RecentBill | J15: 近期帳單查詢 | K15: Y | M15: 1 | N15: 45001 | O15: Callee | P15: 程式無異動，故不需另行開發 | Q15: {"Content":{"ID":"M151XXXX91","BillDateYYYYMM":"201704"},"Header":{"ApplicationName":"EWEB2","UserID":"A131XXXX82"}} | R15: { "Result": { "IsCompanyUser": false, "BillType": 0, "BaseData": { "ID": "M151147491", "CustName": "", "BillDate": "201706", "STMTDATE": "2017/06/06", "DUEDATE": "2017/06/21", "IsLineCR": false, "IntRate": "7.50%", "IntDate": "2017/09" }, "BillAmounts": [ { "CurrencyCode": "000", "CurrencyName": "臺幣", "PREVBAL": "120,659", "PREVPAYAMT": "0", "NEWADDAMT": "229,839", "FINCHARGE": "2,499", "LATECHARGE": "0", "CURRBAL": "352,997", "DUEAMT": "290,487", "DDAMT": "352,997", "DDBANK": "永豐銀行", "DDAcountNo": "3333333xxxx888", "ACT_LINE_CR": "N", "LastPaymentDate": "2015/10/10", "IntRate": 7.5, "IntDate": "201709", "LastPaymentAmt": "20,141", "TotalPaymentAmt": "29,650", "PaymentRecords": [ { "TXDATE": "2021/04/29", "DEDATE": "2021/04/29", "MEMO": "永豐自扣已入帳，謝謝！", "AMT": "-552" }, { "TXDATE": "2021/05/03", "DEDATE": "2021/05/03", "MEMO": "你的付款已入帳，謝謝！", "AMT": "29,098" } ] } ], "BillDeductMsgs": [ "您的預定扣款金額 臺幣 352,997 元將於 2017/06/21 透過 永豐銀行 帳號「3333333xxxx888」自動扣款，請於預定扣款日前一營業日存足帳戶餘額。如須申請帳單分期請於自動扣款日前5日完成申請。" ], "Reward": { "AddPoint": "1568", "AdjustPoint": "0", "ExchangePoint": "0", "TotalPoint": "5264", "ExpiringPoint": "0" }, "BillRecords": [ { "CurrencyCode": "000", "CurrencyName": "臺幣", "TXDATE": "2017/04/02", "DEDATE": "2017/06/01", "CardNo": "1806", "MEMO": " 6-XXXXX ", "AMT": "21", "TXAMT": "", "TXCUR": "", "CURDATE": "", "INST_RATE": "", "INST_AMT": "", "COUNTRY": " ", "TXCode": "3 " } ], "CashAdvanceInfo": { "CreditCardLimit": "2000000", "CreditAvailable": "0", "CashLimit": "0", "CashAvailable": "0", "AuthAmount": "0" }, "AsymmetricInstallmentInfo": [ { "TXDATE": "2021/03/05", "MEMO": "神腦蘋果手機60000(1624)", "AMT": "60,000", "INSAMT_MEMO": "第1-12期6成金額36,000、第13-24期4成金額24,000", "PAYAMT_MEMO": "第1-12期3,000、第13-24期2,000" } ] }, "Header": { "SessionID": "96c47e89-f50c-4406-b9bf-0eae6a308895", "ApplicationName": "EWEB2", "ReferenceNo": "ffc036ee-5f86-4826-b1e1-05ce7ffcc0e2", "UserID": "", "RequestTime": "2017-11-08T15:58:52.262743+08:00", "TxCode": "", "RemoteAddr": "10.11.33.40", "PageName": "", "IsWriteLog": true, "SsaToken": "", "ClientRefNo": "ffc036ee-5f86-4826-b1e1-05ce7ffcc0e2", "ClientTimestamp": "2017-11-08T15:58:52.262743+08:00" }, "ResultCode": "00", "ResultMessage": "", "Error": null }
B16: 011 | C16: 商品應用部 | D16: 信用支付科 | E16: TWBOS00017 | F16: 信用卡網站後台維護系統(Credit Card) | G16: EWEB | H16: OtpState | I16: OtpState | J16: OtpSvc - 查詢客戶DisplayCard狀態 | K16: Y | M16: 1 | N16: 45001 | O16: Callee | P16: 程式無異動，故不需另行開發 | Q16: Identity=A123123123 | R16: <OtpResponse xmlns:xsi="http://www.w3.org/2001/XMLSchema-instance" xmlns:xsd="http://www.w3.org/2001/XMLSchema" xmlns="http://tempuri.org/"> <Result>true</Result> <UserId>A123123123</UserId> <UserName>teete</UserName> <Code>0040</Code> <Message>登入MMA成功-DisplayCard OTP</Message> <TranSerial>49334</TranSerial> <CardNo>5243073229557395</CardNo> <OtpState>1</OtpState> <Issues>4</Issues> <ErrorCount>0</ErrorCount> </OtpResponse>
B17: 012 | C17: 商品應用部 | D17: 信用支付科 | E17: TWBOS00017 | F17: 信用卡網站後台維護系統(Credit Card) | G17: EWEB | H17: cardGetMain | I17: cardGetMain | J17: 查詢大戶信用卡資訊 | K17: Y | M17: 1 | N17: 45001 | O17: Callee | P17: 程式無異動，故不需另行開發 | Q17: CARD=552054XXXX133709; | R17: <CardGetMain><QueryResult>SUCCESS</QueryResult><PID></PID><CARD>552054XXXX133709</CARD><ErrLog></ErrLog><QueryData><CurrBal>29194</CurrBal><DueAmt>2940</DueAmt><DueDate>20220729</DueDate><StmtDate>20220703</StmtDate><LastPayTxdate>20080521</LastPayTxdate><LastPayAmt>3966</LastPayAmt><CreditLimit>000150000</CreditLimit><CreditAvailable>+000474738</CreditAvailable><Bonus>0</Bonus><IntRate>750</IntRate><EmpFlag>N</EmpFlag><VIPFlag>N</VIPFlag><WZFlag>N</WZFlag><EBILL>N</EBILL><DDAcct></DDAcct></QueryData></CardGetMain>
B18: 013 | C18: 商品應用部 | D18: 信用支付科 | E18: TWBOS00017 | F18: 信用卡網站後台維護系統(Credit Card) | G18: EWEB | H18: getDAWHORet | I18: getDAWHORet | J18: 大戶卡歷史回饋查詢 | K18: Y | M18: 1 | N18: 45001 | O18: Callee | P18: 程式無異動，故不需另行開發 | Q18: PID=A131418006;STMTMM=202207; | R18: <GetDAWHORet><STMTMM>202207</STMTMM><PID>A131418006</PID><QueryResult>SUCCESS</QueryResult><ErrLog></ErrLog><Returning>0</Returning></GetDAWHORet>
B19: 014 | C19: 商品應用部 | D19: 信用支付科 | E19: TWBOS00017 | F19: 信用卡網站後台維護系統(Credit Card) | G19: EWEB | H19: getDAWHOCardStatus | I19: getDAWHOCardStatus | J19: 大戶卡狀態查詢 | K19: Y | M19: 1 | N19: 45001 | O19: Callee | P19: 程式無異動，故不需另行開發 | Q19: PID=A111XXX967; | R19: <DAWHOCardStatus><PID>A111XXX967</PID><QueryResult>SUCCESS</QueryResult><ErrLog></ErrLog><DetailData><Detail TypeFace="212392" Status="4" /></DetailData></DAWHOCardStatus>
B20: 015 | C20: 商品應用部 | D20: 信用支付科 | E20: TWBOS00017 | F20: 信用卡網站後台維護系統(Credit Card) | G20: EWEB | H20: getDDFlag | I20: getDDFlag | J20: 大戶卡台幣帳戶自扣註記 | K20: Y | M20: 1 | N20: 45001 | O20: Callee | P20: 程式無異動，故不需另行開發 | Q20: PID=A111XXX967; | R20: <GetDDFlag><PID>A111316967</PID><QueryResult>SUCCESS</QueryResult><ErrLog></ErrLog><DDFlag>Y</DDFlag></GetDDFlag>
B21: 016 | C21: 商品應用部 | D21: 信用支付科 | E21: TWBOS00017 | F21: 信用卡網站後台維護系統(Credit Card) | G21: EWEB | H21: getBLHSHWithPaysum | I21: getBLHSHWithPaysum | J21: 大戶卡累積已繳金額查詢 | K21: Y | M21: 1 | N21: 45001 | O21: Callee | P21: 程式無異動，故不需另行開發 | Q21: PID=A131418006; | R21: <GetBLHSHWithPaysum><PID>A131418006 </PID><QueryResult>SUCCESS</QueryResult><ErrLog></ErrLog><STMTMM>202207</STMTMM><CURRBAL>29194.00</CURRBAL><DUEAMT>2940.00</DUEAMT><DUEDATE>20220729</DUEDATE><LPAYSUM>11541.00</LPAYSUM></GetBLHSHWithPaysum>
... B62: 057 | C62: 商品應用部 | D62: 財富信託科 | E62: TWTXN00073 | F62: 智能理財系統 | G62: ibrain | H62: Inv003_A | I62: 退休規劃_步驟一funGetRetirementStep1 | J62: 退休規劃_步驟一 | K62: Y | M62: 1 | N62: 45009 | O62: Callee | P62: 程式無異動，故不需另行開發 | Q62: {"RqHeader":{"MsgID":"MAPP","ChlName":"MAPP","ChlEJNo":"MMA-AI_GRS1-0000095798724","ChlSendTime":"2016-09-29T16:25:20","ChlIP":"127.0.0.1","Language":"TC","Version":"1.0","CustomerID":"A123456789","CustomerIDCheckcode":"1"},"SvcRq":{"Rq":{"Gender":"M","Age":"35","Salary":"60000","RetirementAge":"65"}}} | R62: {"RsHeader":{"RsStat":{"RsStatCode":"SUCCESS","Desc":"退休試算第一步成功回傳，"},"ChlEJNo":"MMA-AI_GRS1-0000095798724","RqTime":"2016-09-29T16:25:20","RsTime":"2016-09-29T16:35:20"},"SvcRs":{"RsCollect":{"Gender":"M","Age":"30","Salary":"50000","RetirementAge":"65","RetirementYear":"35","TargetDollar":"2000000","RetirementStAge":"38","RetirementEdAge":"65"}}}
B63: 058 | C63: 商品應用部 | D63: 財富信託科 | E63: TWTXN00073 | F63: 智能理財系統 | G63: ibrain | H63: Inv004_A | I63: 退休規劃_步驟二funGetRetirementStep2 | J63: 退休規劃_步驟二 | K63: Y | M63: 1 | N63: 44993 | O63: Callee | Q63: {"RqHeader":{"MsgID":"MAPP","ChlName":"MAPP","ChlEJNo":"MMA-AI_GRS2-0000095798724","ChlSendTime":"2016-09-29T16:25:20","ChlIP":"127.0.0.1","Language":"TC"},"SvcRq":{"Rq":{"Gender":"M","Age":"36","Salary":"60000","RetirementAge":"65","TargetDollar":"2000000","PFType":"01"}}} | R63: {"RsHeader":{"RsStat":{"RsStatCode":"SUCCESS","Desc":"退休試算第二步成功回傳，"},"ChlEJNo":"MMA-FUND_gBondCurSum-0000095798724","RqTime":"2016-09-29T16:25:20","RsTime":"2016-09-29T16:35:20"},"SvcRs":{"RsCollect1":{"Gender":"F","Age":"35","Salary":"60000","RetirementAge":"30","TargetDollar":"4000000","CalSeqNo":"201811290000001"},"RsCollect2":[{"InitialDollar":"500000","RSPDollar":"0","InitialSetting":"false"},{"InitialDollar":"400000","RSPDollar":"5000","InitialSetting":"false"},{"InitialDollar":"300000","RSPDollar":"6000","InitialSetting":"true"},{"InitialDollar":"200000","RSPDollar":"7000","InitialSetting":"false"},{"InitialDollar":"100000","RSPDollar":"8000","InitialSetting":"false"}]}}
B64: 059 | C64: 商品應用部 | D64: 財富信託科 | E64: TWTXN00073 | F64: 智能理財系統 | G64: ibrain | H64: Inv005_A | I64: 退休規劃 & 自訂計畫股債比funGetEquityExpo | J64: 退休規劃 & 自訂計畫股債比 | K64: Y | M64: 1 | N64: 45009 | O64: Callee | P64: 程式無異動，故不需另行開發 | Q64: {"RqHeader":{"MsgID":"","ChlName":"MAPP","ChlEJNo":"MMA-AI_GEE-0000095798724","ChlSendTime":"2016-09-29T16:25:20","ChlIP":"127.0.0.1","Language":"TC","Version":"1.0","CustomerID":"A123456789","CustomerIDCheckcode":"1"},"SvcRq":{"Rq":{"Gender":"M","Age":"35","Salary":"60000","InitialDollar":"500000","RSPDollar":"6000","RetirementAge":"65","TargetDollar":"30","PFType":"30","PFName":"準備xx基金","InvestYear":"0","Tko_EmpNo":"114832""ActNO":"00100412345678","IPigNo":"CEVT-P60-98-xx","IPigType":"01","IPigDESC":"準備離婚基金"}}} | R64: {"RsHeader":{"RsStat":{"RsStatCode":"SUCCESS","Desc":"股債比率回傳，"},"ChlEJNo":"MMA-AI_GEE-0000095798724","RqTime":"2016-09-29T16:25:20","RsTime":"2016-09-29T16:35:20"},"SvcRs":{"RsCollect":{"InitialStockRatio":"100"InitialBondRatio":"0","InitialDollar":"5000000","RSPDollar":"8000","CalSeqNo":"xxxxxxxxxx","InitialStockARatio":"30.00","InitialStockBRatio":"30.00","InitialStockCRatio":"0.00","InitialBondLRatio":"30.00","InitialBondMRatio":"10.00","InitialBondSRatio":"0.00”,"ActNO":"00100412345678","IPigNO":"CEVT-P60-98-xx","IPigType":"01","IPigDESC":"準備xx基金","InitialStockA":"VTI先鋒整體股市ETF","InitialStockB":"VEA先鋒富時已開發股市ETF","InitialStockC":"","InitialBondL":"SPTL：SPDR投資組合長期美國公債ETF","InitialBondM":"SCHR：SCHWAB美國中期公債ETF","InitialBondS":"SCHO：SCHWAB短期美國公債ETF”}}
B65: 060 | C65: 商品應用部 | D65: 財富信託科 | E65: TWTXN00073 | F65: 智能理財系統 | G65: ibrain | H65: Inv006_A | I65: 試算留存Email funAddEmail | J65: 試算留存Email | K65: Y | M65: 1 | N65: 45009 | O65: Callee | P65: 程式無異動，故不需另行開發 | Q65: {"RqHeader":{"MsgID":"","ChlName":"MAPP","ChlEJNo":"MMA-AI_AE-0000095798724","ChlSendTime":"2016-09-29T16:25:20","ChlIP":"127.0.0.1","Language":"TC","Version":"1.0","CustomerID":"A123456789","CustomerIDCheckcode":"1"},"SvcRq":{"Rq":{"Email":"jasontsai@sinopac.com","CalSeqNo":"2018112000000001"}}} | R65: {"RsHeader":{"RsStat":{"RsStatCode":"SUCCESS","Desc":"E-Mail留存成功"},"ChlEJNo":"MMA-AI_AE-0000095798724","RqTime":"2016-09-29T16:25:20","RsTime":"2016-09-29T16:35:20"},"SvcRs":{"RsCollect":{"Email":"JasonTsai"}}
B66: 061 | C66: 商品應用部 | D66: 財富信託科 | E66: TWTXN00073 | F66: 智能理財系統 | G66: ibrain | H66: Inv007_A | I66: Projection 表 funGetProjection | J66: Projection 表 | K66: Y | M66: 1 | N66: 45009 | O66: Callee | P66: 程式無異動，故不需另行開發 | Q66: {"RqHeader":{"MsgID":"","ChlName":"MAPP","ChlEJNo":"MMA-AI_GP-0000095798724","ChlSendTime":"2016-09-29T16:25:20","ChlIP":"127.0.0.1","Language":"TC","Version":"1.0","CustomerID":"A123456789","CustomerIDCheckcode":"1"},"SvcRq":{"Rq":{"InitialDollar":"500000","RSPDollar":"5000","TargetDollar":"2000000","InvestYear":"5"}}} | R66: {"RsHeader":{"RsStat":{"RsStatCode":"SUCCESS","Desc":"Projection回傳，"},"ChlEJNo":"MMA-AI_GP-0000095798724","RqTime":"2016-09-29T16:25:20","RsTime":"2016-09-29T16:35:20"},"SvcRs":{"RsCollect1":{"IRR":"10.82"},"RSCollect2":{"Situation1":[{"years":"2018","TargetDollar":"4500000","ActualDollar":"5000000","StockRatio":"60.00","BondRatio":"40.00"},{"years":"2019","TargetDollar":"4600000","ActualDollar":"5000000","StockRatio":"60.00","BondRatio":"40.00"},{"years":"2020","TargetDollar":"4700000","ActualDollar":"5000000","StockRatio":"60.00","BondRatio":"40.00"},{"years":"2021","TargetDollar":"4800000","ActualDollar":"5000000","StockRatio":"60.00","BondRatio":"40.00"},{"years":"2022","TargetDollar":"4900000","ActualDollar":"5000000","StockRatio":"60.00","BondRatio":"40.00"}],"Situation2":[{"years":"2018","TargetDollar":"5000000","ActualDollar":"5000000","StockRatio":"60.00","BondRatio":"40.00"},{"years":"2019","TargetDollar":"5100000","ActualDollar":"5000000","StockRatio":"60.00","BondRatio":"40.00"},{"years":"2020","TargetDollar":"5200000","ActualDollar":"5000000","StockRatio":"60.00","BondRatio":"40.00"},{"years":"2021","TargetDollar":"5300000","ActualDollar":"5000000","StockRatio":"60.00","BondRatio":"40.00"},{"years":"2022","TargetDollar":"5400000","ActualDollar":"5000000","StockRatio":"60.00","BondRatio":"40.00"}],"Situation3":[{"years":"2018","TargetDollar":"6000000","ActualDollar":"5000000","StockRatio":"60.00","BondRatio":"40.00"},{"years":"2019","TargetDollar":"7100000","ActualDollar":"5000000","StockRatio":"60.00","BondRatio":"40.00"},{"years":"2020","TargetDollar":"8200000","ActualDollar":"5000000","StockRatio":"60.00","BondRatio":"40.00"},{"years":"2021","TargetDollar":"9300000","ActualDollar":"5000000","StockRatio":"60.00","BondRatio":"40.00"},{"years":"2022","TargetDollar":"9400000","ActualDollar":"5000000","StockRatio":"60.00","BondRatio":"40.00"}]}}}
B67: 062 | C67: 商品應用部 | D67: 財富信託科 | E67: TWTXN00073 | F67: 智能理財系統 | G67: ibrain | H67: Inv008_A | I67: 自訂計畫_步驟一funGetMyPlanStep1 | J67: 自訂計畫_步驟一 | K67: Y | M67: 1 | N67: 45009 | O67: Callee | P67: 程式無異動，故不需另行開發 | Q67: {"RqHeader":{"MsgID":"","ChlName":"MAPP","ChlEJNo":"MMA-AI_GMS1-0000095798724","ChlSendTime":"2016-09-29T16:25:20","ChlIP":"127.0.0.1","Language":"TC","Version":"1.0","CustomerID":"A123456789","CustomerIDCheckcode":"1"},"SvcRq":{"Rq":{"Gender":"M","Age":"35","Salary":"60000","PFType":"02","PFName":"整修房子","ActNo":"00100412345678","IPigNO":"CEVT-P60-98-xx","IPigType":"01","IPigDESC":"準備離婚基金","InvestYear":"2","TargetDollar":"200000"}}} | R67: {"RsHeader":{"RsStat":{"RsStatCode":"SUCCESS","Desc":"自訂計畫第一步成功回傳，"},"ChlEJNo":"MMA-AI_GMS1-0000095798724","RqTime":"2016-09-29T16:25:20","RsTime":"2016-09-29T16:35:20"},"SvcRs":{"RsCollect":{"Gender":"M","Age":"30","Salary":"50000","InvestYear":"5","TargetDollar":"2000000","PFName":"我要修房子","ActNo":"00100412345678","IPigNO":"CEVT-P60-98-xx","IPigType":"01","IPigDESC":"準備離婚基金"}}
B68: 063 | C68: 商品應用部 | D68: 財富信託科 | E68: TWTXN00073 | F68: 智能理財系統 | G68: ibrain | H68: Inv009_A | I68: 自訂計畫_步驟二 funGetMyPlanStep2 | J68: 自訂計畫_步驟二 | K68: Y | M68: 1 | N68: 44993 | O68: Callee | Q68: {"RqHeader":{"MsgID":"","ChlName":"MAPP","ChlEJNo":"MMA-AI_GMS1-0000095798724","ChlSendTime":"2016-09-29T16:25:20","ChlIP":"127.0.0.1","Language":"TC","Version":"1.0","CustomerID":"A123456789","CustomerIDCheckcode":"1"},"SvcRq":{"Rq":{"Gender":"M","Age":"36","Salary":"60000","InvestYear":"5","TargetDollar":"2000000","PFType":"02","PFName":"整修房子","ActNo":"00100412345678","IPigNo":"CEVT-P60-98-xx","IPigType":"01","IPigDESC":"準備離婚基金"}}} | R68: {"RsHeader":{"RsStat":{"RsStatCode":"SUCCESS","Desc":"退休試算第二步成功回傳，"},"ChlEJNo":"MMA-AI_GMS2-0000095798724","RqTime":"2016-09-29T16:25:20","RsTime":"2016-09-29T16:35:20"},"SvcRs":{"RsCollect1":{"Gender":"F","Age":"35","Salary":"60000","InvestYear":"30","TargetDollar":"4000000","CalSeqNo":"201811290000001","自訂名稱":"整修房子","ActNO":"00100412345678","IPigNO":"CEVT-P60-98-xx","IPigType":"01","IPigDESC":"準備離婚基金"},"RsCollect2":[{"InitialDollar":"500000","RSPDollar":"0","InitialSetting":"false"},{"InitialDollar":"400000","RSPDollar":"5000","InitialSetting":"false"},{"InitialDollar":"300000","RSPDollar":"6000","InitialSetting":"true"},{"InitialDollar":"200000","RSPDollar":"7000","InitialSetting":"false"},{"InitialDollar":"100000","RSPDollar":"8000","InitialSetting":"false"}]}}
B69: 064 | C69: 商品應用部 | D69: 財富信託科 | E69: TWTXN00073 | F69: 智能理財系統 | G69: ibrain | H69: Inv010_A | I69: 歷史回測 funGetBackProjection | J69: 歷史回測 | K69: Y | M69: 1 | N69: 45009 | O69: Callee | P69: 程式無異動，故不需另行開發 | Q69: {"RqHeader":{"MsgID":"","ChlName":"MAPP","ChlEJNo":"MMA-AI_GBP-0000095798724","ChlSendTime":"2016-09-29T16:25:20","ChlIP":"127.0.0.1","Language":"TC","Version":"1.0","CustomerID":"A123456789","CustomerIDCheckcode":"1"},"SvcRq":{"Rq":{"TargetDollar":"2000000","InitialDollar":"500000","RSPDollar":"5000","InvestYear":"5","InvestStYear":"2000"}}} | R69: {"RsHeader":{"RsStat":{"RsStatCode":"SUCCESS","Desc":"BakProjection成功回傳，"},"ChlEJNo":"MMA-AI_GMS2-0000095798724","RqTime":"2016-09-29T16:25:20","RsTime":"2016-09-29T16:35:20"},"SvcRs":{"RsCollect1":{"InvestYear":"2","InvestStYear":"2015","InitialDollar":"2","RSPDollar":"2015","IRR":"10.82"},"RsCollect2":[{"Years":"2015","TargetDollar":"300000","TotalPV":"170000","TotalnvestDollar":"140000","StockRatio":"22.70","BondRatio":"77.30","EventName":""},{"Years":"2016","TargetDollar":"300000","TotalPV":"310000","TotalnvestDollar":"280000","StockRatio":"21.70","BondRatio":"78.30","EventName":"英國脫歐"},{"Years":"2017","TargetDollar":"300000","TotalPV":"380000","StockRatio":"20.70","BondRatio":"79.30","EventName":""}]}}
B70: 065 | C70: 商品應用部 | D70: 財富信託科 | E70: TWTXN00073 | F70: 智能理財系統 | G70: ibrain | H70: Inv011_A | I70: 歷史回測清單 funGetBackProjectionHistory | J70: 歷史回測清單 | K70: Y | M70: 1 | N70: 45009 | O70: Callee | P70: 程式無異動，故不需另行開發 | Q70: {"RqHeader":{"MsgID":"","ChlName":"MAPP","ChlEJNo":"MMA-AI_GBP-0000095798724","ChlSendTime":"2016-09-29T16:25:20","ChlIP":"127.0.0.1","Language":"TC","Version":"1.0","CustomerID":"A123456789","CustomerIDCheckcode":"1"},"SvcRq":{"Rq":{"SelectYear":""}}} | R70: {"RsHeader":{"RsStat":{"RsStatCode":"SUCCESS","Desc":"BackProjectionHistory成功回傳，"},"ChlEJNo":"MMA-AI_GMS2-0000095798724","RqTime":"2016-09-29T16:25:20","RsTime":"2016-09-29T16:35:20"},"SvcRs":{"RsCollect1":{"SelectYear":""},"RsCollect2":[{"Years":"1929","EventName":"經濟大蕭條"},{"Years":"1973","EventName":"石油危機"},{"Years":"1980","EventName":"拉美債務危機"},{"Years":"1987","EventName":"美國儲貸危機"},{"Years":"1997","EventName":"亞洲金融風暴"},{"Years":"2000","EventName":"網路泡沫破裂"},{"Years":"2008","EventName":"次級房貸風暴"},{"Years":"2010","EventName":"歐債危機"},{"Years":"2015","EventName":"油價暴跌"}]}}
B71: 066 | C71: 商品應用部 | D71: 財富信託科 | E71: TWTXN00073 | F71: 智能理財系統 | G71: ibrain | H71: Inv012_A | I71: 取得ETF投組試算資料 funGetEquityExpo | J71: 取得ETF投組試算資料 | K71: Y | M71: 1 | N71: 45009 | O71: Callee | P71: 程式無異動，故不需另行開發 | Q71: {"RqHeader":{"ChlName":"MAPP","ChlEJNo":"MMA-AI_gETFPFCal-0000095798724","ChlSendTime":"2016-09-29T16:25:20","CustomerID":"53948659","CustomerIDCheckcode":"0","ChlIP":"127.0.0.1","Language":""},"SvcRq":{"Rq":{"CalSeqNo":"2018113012345678","Tko_EmpNo":"100548""ActNo":"00100412345678","IPigNo":"CEVT-P60-98-xx","IPigType":"01","IPigDESC":"夢想"}}} | R71: {"RsHeader":{"RsStat":{"RsStatCode":"SUCCESS","Desc":"取得成功"},"ChlEJNo":"MMA-AI-ETF-GET-0000095798724","RqTime":"2016-09-29T16:25:20","RsTime":"2016-09-29T16:35:20"},"SvcRs":{"RsCollect1"：{"CalSeqNo":"2018122400000001","InitialEffectiveDate":"2018/12/24","MaturityDate":"2038/12/31","PFName":"退休規劃","Currency":"TWD","InitialDollar":"300000","RSPDollar":"5000","StockA_ID":"VTI","StockB_ID":"VEA","StockC_ID":"","BondL_ID":"VGLT","BondM_ID":"VGIT","BondS_ID":"VGSH","StockARisk":"4","StockBRisk":"4","StockCRisk":"","BondLRisk":"4","BondMRisk":"4","BondSRisk":"4","StockA_Name":"先鋒整體股市ETF","StockB_Name":"先鋒富時股市ETF","StockC_Name":"","BondL_Name":"先鋒長期政府公債","BondM_Name":"先鋒中期政府公債","BondS_Name":"先鋒短期政府公債","ActNo":"00100412345678","IPigNo":"CEVT-P60-98-xx","IPigType":"xxxxxxxxxxxxxx","IPigDESC":"夢想","CusType":"6","TargetDollar":"300000","InvestYear":"3"},"RsCollect2":[{"StockRatio":"55","BondRatio":"45","StockARatio":"34","StockBRatio":"21","StockCRatio":"0","BondLRatio":"28","BondMRatio":"10","BondSRatio":"7","PortfolioLevel":"4","IRR":"5.0","IRRTargetDollar":"310000"},{"StockRatio":"60","BondRatio":"40","StockARatio":"40","StockBRatio":"20","StockCRatio":"0","BondLRatio":"23","BondMRatio":"14","BondSRatio":"3","PortfolioLevel":"5","IRR":"5.2","IRRTargetDollar":"320000"},{"StockRatio":"70","BondRatio":"30","StockARatio":"45","StockBRatio":"25","StockCRatio":"0","BondLRatio":"17","BondMRatio":"8","BondSRatio":"5","PortfolioLevel":"6","IRR":"5.4","IRRTargetDollar":"330000"}]}}
B72: 067 | C72: 商品應用部 | D72: 財富信託科 | E72: TWTXN00073 | F72: 智能理財系統 | G72: ibrain | H72: Inv013_A | I72: 確認ETF投組申購交易 ETFPortfolioBuyConfirm | J72: 確認ETF投組申購交易 | K72: Y | M72: 1 | N72: 45009 | O72: Callee | P72: 程式無異動，故不需另行開發 | Q72: {"RqHeader":{"ChlName":"MAPP","ChlEJNo":"MMA-ETF-BUY-Confirm-0000095798724","ChlSendTime":"2016-09-29T16:25:20","CustomerID":"53948659","CustomerIDCheckcode":"0","ChlIP":"127.0.0.1","Language":""},"SvcRq":{"Rq":{"CalSeqNo":"2018122400000001","InitialEffectiveDate":"2018/12/24","MaturityDate":"2038/12/31","RSPDeduDate":"06","AccountNo":"01500312345678","TrustAccount":"01502012345678","ActNo":"00100412345678","IPigNo":"CEVT-P60-98-xx","IPigType":"xxxxxxxxxxxxxx","IPigDESC":"夢想","PortfolioLevel":"6"}}} | R72: {"RsHeader":{"RsStat":{"RsStatCode":"SUCCESS","Desc":"確認ETF投組申購交易成功"},"ChlEJNo":"MMA-ETF-BUY-Confirm-0000095798724","RqTime":"2016-09-29T16:25:20","RsTime":"2016-09-29T16:35:20"},"SvcRs":{"RsCollect":{"CalSeqNo":"2018122400000001","Stock_Ratio":"50","Bond_Ratio":"50","StockA_ID":"VTI","StockB_ID":"VEA","StockC_ID":"","BondL_ID":"VGLT","BondM_ID":"VGIT","BondS_ID":"VGSH","StockA_Name":"先鋒整體股市ETF","StockB_Name":"先鋒富時股市ETF","StockC_Name":"","BondL_Name":"先鋒長期政府公債","BondM_Name":"先鋒中期政府公債","BondS_Name":"先鋒短期政府公債","StockA_Ratio":"34","StockB_Ratio":"21","StockC_Ratio":"0","BondL_Ratio":"28","BondM_Ratio":"10","BondS_Ratio":"7","InitialEffectiveDate":"2018/12/24","MaturityDate":"20381231","PFName":"退休規劃","Currency":"TWD","InitialDollar":"300000","RSPDollar":"5000","RSPDeduDate":"06","AccountNo":"01500312345678","TrustAccount":"01502012345678","RR6Check":"N","ProductPI":"N","CustomerRiskLevel":"N","ProductYear":"N","InvestYear":"N""MailType":"2""Address":abs@sinopac.com,"StockARisk":"RR6","StockBRisk":"RR6","StockCRisk":"RR6","BondLRisk":"RR6","BondMRisk":"RR6","BondSARisk":"RR6","RspDeduDateF":"2019-10-26","ActNo":"00100412345678","IPigNo":"CEVT-P60-98-xx","IPigType":"xxxxxxxxxxxxxx","IPigDESC":"夢想","PortfolioLevel":"6","IRR":"5.2","IRRTragetDollar":"320000","Special":"N","Over70":"N","CusType":"5","TargetDollar":"300000","Invest_Year":"30"}}}
B73: 068 | C73: 商品應用部 | D73: 財富信託科 | E73: TWTXN00073 | F73: 智能理財系統 | G73: ibrain | H73: Inv014_A | I73: 新增ETF投組申購交易 ETFPortfolioBuyCreate | J73: 新增ETF投組申購交易 | K73: Y | M73: 1 | N73: 45009 | O73: Callee | P73: 程式無異動，故不需另行開發 | Q73: {"RqHeader":{"ChlName":"MAPP","ChlEJNo":"MMA-ETF-BUY-Create-0000095798724","ChlSendTime":"2016-09-29T16:25:20","CustomerID":"53948659","CustomerIDCheckcode":"0","ChlIP":"127.0.0.1","Language":""},"SvcRq":{"Rq":{"CalSeqNo":"2018122400000001","InitialEffectiveDate":"2018/12/24","MaturityDate":"2038/12/31","RSPDeduDate":"06","AccountNo":"01500312345678","TrustAccount":"01502012345678","RspDeduDateF":"2019-10-26","ActNo":"00100412345678","IPigNo":"CEVT-P60-98-xx","IPigType":"xxxxxxxxxxxxxx","IPigDESC":"夢想","PortfolioLevel":"6",}}} | R73: {"RsHeader":{"RsStat":{"RsStatCode":"SUCCESS","Desc":"新增ETF投組申購交易成功"},"ChlEJNo":"MMA-ETF-BUY-Create-0000095798724","RqTime":"2016-09-29T16:25:20","RsTime":"2016-09-29T16:35:20"},"SvcRs":{"RsCollect":{"CalSeqNo":"2018122400000001","Stock_Ratio":"50","Bond_Ratio":"50","StockA_ID":"VTI","StockB_ID":"VEA","StockC_ID":"","BondL_ID":"VGLT","BondM_ID":"VGIT","BondS_ID":"VGSH","StockA_Name":"先鋒整體股市ETF","StockB_Name":"先鋒富時股市ETF","StockC_Name":"","BondL_Name":"先鋒長期政府公債","BondM_Name":"先鋒中期政府公債","BondS_Name":"先鋒短期政府公債","StockA_Ratio":"34","StockB_Ratio":"21","StockC_Ratio":"0","BondL_Ratio":"28","BondM_Ratio":"10","BondS_Ratio":"7","InitialEffectiveDate":"2018/12/24","MaturityDate":"20381231","PFName":"退休規劃","Currency":"TWD","InitialDollar":"300000","RSPDollar":"5000","RSPDeduDate":"06","AccountNo":"01500312345678","TrustAccount":"01502012345678","StockARisk":"RR6","StockBRisk":"RR6","StockCRisk":"RR6","BondLRisk":"RR6","BondMRisk":"RR6","BondSARisk":"RR6","RspDeduDateF":"2019-10-26","ActNo":"00100412345678","IPigNo":"CEVT-P60-98-xx","IPigType":"xxxxxxxxxxxxxx","IPigDESC":"夢想","PortfolioLevel":"6","IRR":"5.2""PortfolioLevel":"6","IRR":"5.2","IRRTragetDollar":"320000","CusType":"5","TargetDollar":"300000","InvestYear":"30",}}}
B74: 069 | C74: 商品應用部 | D74: 財富信託科 | E74: TWTXN00073 | F74: 智能理財系統 | G74: ibrain | H74: Inv015_A | I74: 取得ETF投組解約資料 ETFPortfolioRedemGet | J74: 取得ETF投組解約資料 | K74: Y | M74: 1 | N74: 44993 | O74: Callee | Q74: {"RqHeader":{"ChlName":"MAPP","ChlEJNo":"MMA-ETF-REDEM-Get-0000095798724","ChlSendTime":"2016-09-29T16:25:20","CustomerID":"53948659","CustomerIDCheckcode":"0","ChlIP":"127.0.0.1","Language":""},"SvcRq":{"Rq":{"AISeqNo":"123456"}}} | R74: {"RsHeader":{"RsStat":{"RsStatCode":"SUCCESS","Desc":"取得成功"},"ChlEJNo":"MMA-ETF-REDEM-Get-0000095798724","RqTime":"2016-09-29T16:25:20","RsTime":"2016-09-29T16:35:20"},"SvcRs":{"RsCollect":{"AISeqNo":"123456","RedemEffectiveDate":"2018/12/25","PFName":"退休規劃123456","InitialDate":"2018/12/01","MaturityDate":"2019/12/31","InvestYears":"5","Currency":"TWD","TargetDollar":"500000","TotalInvestDollar":"50000","TotalPV":"60000","NetRatio":"20","StockRatio":"50","BondRatio":"50","ManageFee":"5000","ActNo":"00100412345678","IPigNo":"CEVT-P60-98-xx","IPigDESC":"夢想"},"ETFDetail":[{"MarketID":"01","MarketName":"美國市場","ETFID":"VTI","ETFName":"先鋒整體股市ETF","PValue":"140","Unit":"2.54"},{"MarketID":"02","MarketName":"已開發股市","ETFID":"VEA","ETFName":"先鋒富時股市ETF","PValue":"60","UNIT":"3.54"},{"MarketID":"04","MarketName":"長期公債","ETFID":"VGLT","ETFName":"先鋒長期政府公債","PValue":"140","UNIT":"2.54"},{"MarketID":"05","MarketName":"中期公債","ETFID":"VGSH","ETFName":"先鋒中期政府公債","PValue":"140","UNIT":"2.54"},{"MarketID":"06","MarketName":"短期公債","ETFID":"VGSH","ETFName":"先鋒短期政府公債","PValue":"140","UNIT":"2.54"}]}}
B75: 070 | C75: 商品應用部 | D75: 財富信託科 | E75: TWTXN00073 | F75: 智能理財系統 | G75: ibrain | H75: Inv016_A | I75: 確認ETF投組解約交易 ETFPortfolioRedemConfirm | J75: 確認ETF投組解約交易 | K75: Y | M75: 1 | N75: 45000 | O75: Callee | Q75: {"RqHeader":{"ChlName":"MAPP","ChlEJNo":"MMA-ETF-REDEM-Get-0000095798724","ChlSendTime":"2016-09-29T16:25:20","CustomerID":"53948659","CustomerIDCheckcode":"0","ChlIP":"127.0.0.1","Language":""},"SvcRq":{"Rq":{"AISeqNo":"123456","RedemEffectiveDate":"2018/12/25","EnterAccountNo":"12300312345678"}}} | R75: {"RsHeader":{"RsStat":{"RsStatCode":"SUCCESS","Desc":"確認解約成功"},"ChlEJNo":"MMA-ETF-REDEM-Get-0000095798724","RqTime":"2016-09-29T16:25:20","RsTime":"2016-09-29T16:35:20"},"SvcRs":{"RsCollect":{"AISeqNo":"123456","CreateDate":"2018/12/24","RedemEffectiveDate":"2018/12/25","PFName":"退休規劃123456","InitialDate":"2018/12/01","MaturityDate":"2019/12/31","InvestYears":"5","Currency":"TWD","TargetDollar":"500000","TotalInvestDollar":"50000","TotalPV":"60000","NetRatio":"20","StockRatio":"50","BondRatio":"50","ManageFee":"5000","EnterAccountNo":"01500312345678"},"ETFDetail":[{"MarketID":"01","MarketName":"美國市場","ETFID":"VTI","ETFName":"先鋒整體股市ETF","PValue":"140","Unit":"2.54"},{"MarketID":"02","MarketName":"已開發股市","ETFID":"VEA","ETFName":"先鋒富時股市ETF","PValue":"60","UNIT":"3.54"},{"MarketID":"04","MarketName":"長期公債","ETFID":"VGLT","ETFName":"先鋒長期政府公債","PValue":"140","UNIT":"2.54"},{"MarketID":"05","MarketName":"中期公債","ETFID":"VGSH","ETFName":"先鋒中期政府公債","PValue":"140","UNIT":"2.54"},{"MarketID":"06","MarketName":"短期公債","ETFID":"VGSH","ETFName":"先鋒短期政府公債","PValue":"140","UNIT":"2.54"}]}}
B76: 071 | C76: 商品應用部 | D76: 財富信託科 | E76: TWTXN00073 | F76: 智能理財系統 | G76: ibrain | H76: Inv017_A | I76: 新增ETF投組解約交易 ETFPortfolioRedemCreate | J76: 新增ETF投組解約交易 | K76: Y | M76: 1 | N76: 45000 | O76: Callee | Q76: {"RqHeader":{"ChlName":"MAPP","ChlEJNo":"MMA-ETF-REDEM-Get-0000095798724","ChlSendTime":"2016-09-29T16:25:20","CustomerID":"53948659","CustomerIDCheckcode":"0","ChlIP":"127.0.0.1","Language":""},"SvcRq":{"Rq":{"AISeqNo":"123456","RedemEffectiveDate":"2018/12/25","EnterAccountNo":"12300312345678"}}} | R76: {"RsHeader":{"RsStat":{"RsStatCode":"SUCCESS","Desc":"新增解約成功"},"ChlEJNo":"MMA-ETF-REDEM-Create-0000095798724","RqTime":"2016-09-29T16:25:20","RsTime":"2016-09-29T16:35:20"},"SvcRs":{"RsCollect":{"AISeqNo":"123456","CreateDate":"2018/12/24","RedemEffectiveDate":"2018/12/25","PFName":"退休規劃123456","InitialDate":"2018/12/01","MaturityDate":"2019/12/31","InvestYears":"5","Currency":"TWD","TargetDollar":"500000","TotalInvestDollar":"50000","TotalPV":"60000","NetRatio":"20","StockRatio":"50","BondRatio":"50","ManageFee":"5000","EnterAccountNo":"01500312345678"},"ETFDetail":[{"MarketID":"01","MarketName":"美國市場","ETFID":"VTI","ETFName":"先鋒整體股市ETF","PValue":"140","Unit":"2.54"},{"MarketID":"02","MarketName":"已開發股市","ETFID":"VEA","ETFName":"先鋒富時股市ETF","PValue":"60","UNIT":"3.54"},{"MarketID":"04","MarketName":"長期公債","ETFID":"VGLT","ETFName":"先鋒長期政府公債","PValue":"140","UNIT":"2.54"},{"MarketID":"05","MarketName":"中期公債","ETFID":"VGSH","ETFName":"先鋒中期政府公債","PValue":"140","UNIT":"2.54"},{"MarketID":"06","MarketName":"短期公債","ETFID":"VGSH","ETFName":"先鋒短期政府公債","PValue":"140","UNIT":"2.54"}]}}
B77: 072 | C77: 商品應用部 | D77: 財富信託科 | E77: TWTXN00073 | F77: 智能理財系統 | G77: ibrain | H77: Inv018_A | I77: 查詢庫存投資總覽投組大項 InvPortfolioData | J77: 查詢庫存投資總覽投組大項 | K77: Y | M77: 1 | N77: 44993 | O77: Callee | Q77: {"RqHeader":{"ChlName":"MAPP","ChlEJNo":"MMA-ETF-IDA1-Get-0000095798724","ChlSendTime":"2016-09-29T16:25:20","CustomerID":"53948659","CustomerIDCheckcode":"0","ChlIP":"127.0.0.1","Language":""},"SvcRq":{}} | R77: {"RsHeader":{"RsStat":{"RsStatCode":"SUCCESS","Desc":"查詢庫存投資總覽投組成功"},"ChlEJNo":"MMA-ETF-IDA1-Get-0000095798724","RqTime":"2016-09-29T16:25:20","RsTime":"2016-09-29T16:35:20"},"SvcRs":{"RsCollect":{"AllTotalInvestDollar":"891387","AllTotalPV":"987311","DataDate":"2019/01/04","Currency":"TWD","ContractMark":"N"},"ETFDetail":[{"AISeqNo":"000001","PFName":"我要買房子","TotalPV":"531899","NetRatio":"5.02%","TargetDollar":"5000000","CreateDate":"2018/10/11","TargetCompletion":"20.02","InvestDollar":"300000","StockMark":"Y","StEndDate":"2019/01/04~2040/12/31""FRStatus":"穩健達標","AlertMark":"Y"},{"AISeqNo":"000002","PFName":"我要環遊世界","TotalPV":"331899","NetRatio":"5.02%","TargetDollar":"500000","CreateDate":"2018/10/11","TargetCompletion":"80.02","InvestDollar":"90000","StockMark":"Y","StEndDate":"2019/01/04~2040/12/31""FRStatus":"穩健達標","AlertMark":"N"}]}}
B78: 073 | C78: 商品應用部 | D78: 財富信託科 | E78: TWTXN00073 | F78: 智能理財系統 | G78: ibrain | H78: Inv019_A | I78: 查詢庫存投資總覽投組明細 InvPortfolioDetail | J78: 查詢庫存投資總覽投組明細 | K78: Y | M78: 1 | N78: 44993 | O78: Callee | Q78: {"RqHeader":{"ChlName":"MAPP","ChlEJNo":"MMA-ETF-IDA2-Get-0000095798724","ChlSendTime":"2016-09-29T16:25:20","CustomerID":"A123456789","CustomerIDCheckcode":"0","ChlIP":"127.0.0.1","Language":""},"SvcRq":{"Rq":{"AISeqNo":"123456"}}} | R78: {"RsHeader":{"RsStat":{"RsStatCode":"SUCCESS","Desc":"查詢庫存投資總覽投組明細成功"},"ChlEJNo":"MMA-ETF-REDEM-Create-0000095798724","RqTime":"2016-09-29T16:25:20","RsTime":"2016-09-29T16:35:20"},"SvcRs":{"RsCollect":{"AISeqNo":"000001","PFName":"退休規劃","TrustCurrency":"TWD","TotalPV":"531899","TotalInvestDollar":"500000","NetIncome":"5000","NetRatio":"8.02%","TargetDollar":"5000000","StockMark":"Y","FRComplete":"20.02","FRStatus":"穩健達標","FRCompleteDsc":"紀律投資加上時間複利，搭配永豐銀行智能理財的密切監控與資產再平衡，才能穩健朝目標前進！","TrustAccount":"003-125-347632","StEndDate":"2019/01/04~2040/12/31","InitialDollar":"500000","RSPDollar":"10000","RSPDeduDate":"6","StockRatio":"40","BondRatio":"60","ExrateDate":"2018/11/30","ClosingRate":"29.87654","DeduChangeStatus":"-","RebalanceMark":"Y","RiskSwitchMark":"Y"},"ETFDetail":[{"MarketName":"美國股市","MarketID":"01","MarketRatio":"20.12","ETFID":"VTI","ETFName":"先鋒整體股市ETF","TrustCurrency":"TWD","NTPV":"351000","TotalUnit":"12.29522","ProductCurrency":"USD","Price":"71.12","PriceDate":"2019/01/04"},{"MarketName":"已開發股市(美國除外)","MarketID":"02","MarketRatio":"20.88","ETFID":"VTA","ETFName":"先鋒B","TrustCurrency":"TWD","NTPV":"351000","TotalUnit":"12.29522","ProductCurrency":"USD","Price":"71.12","PriceDate":"2019/01/04"},{"MarketName":"長期公債","MarketID":"04","MarketRatio":"17.00","ETFID":"VGLT","ETFName":"債券L","TrustCurrency":"TWD","NTPV":"351000","TotalUnit":"12.29522","ProductCurrency":"USD","Price":"30.12","PriceDate":"2019/01/08"},{"MarketName":"中期公債","MarketID":"05","MarketRatio":"17.00","ETFID":"VGIT","ETFName":"債券M","TrustCurrency":"TWD","NTPV":"351000","TotalUnit":"12.29522","ProductCurrency":"USD","Price":"40.12","PriceDate":"2019/01/08"},{"MarketName":"短期公債","MarketID":"06","MarketRatio":"16.00","ETFID":"VGSH","ETFName":"債券S","TrustCurrency":"TWD","NTPV":"351000","TotalUnit":"12.29522","ProductCurrency":"USD","Price":"50.12","PriceDate":"2019/01/08"},{"MarketName":"在途款項","MarketID":"99","MarketRatio":"16.00","ETFID":"","ETFName":"","TrustCurrency":"TWD","NTPV":"351000","TotalUnit":"","ProductCurrency":"","Price":"","PriceDate":""}],"InvestMonthDetail":[{"InvestYearMonth":"2019/01","DataAmt":"2100000","DataCost":"2000000","TargetDollar":"6000000"},{"InvestYearMonth":"2019/02","DataAmt":"2130000","DataCost":"2000000","TargetDollar":"6000000"}]}}
B79: 074 | C79: 商品應用部 | D79: 財富信託科 | E79: TWTXN00073 | F79: 智能理財系統 | G79: ibrain | H79: Inv020_A | I79: 查詢投組清單 PortfolioList | J79: 查詢投組清單 | K79: Y | M79: 1 | N79: 44993 | O79: Callee | Q79: {"RqHeader":{"ChlName":"MAPP","ChlEJNo":"MMA-ETF-EPIQ-Get-0000095798724","ChlSendTime":"2016-09-29T16:25:20","CustomerID":"53948659","CustomerIDCheckcode":"0","ChlIP":"127.0.0.1","Language":""},"SvcRq":{}} | R79: {"RsHeader":{"RsStat":{"RsStatCode":"SUCCESS","Desc":"查詢投組清單成功"},"ChlEJNo":"MMA-ETF-REDEM-Create-0000095798724","RqTime":"2016-09-29T16:25:20","RsTime":"2016-09-29T16:35:20"},"SvcRs":{"RsCollect1":[{"AISeqNo":"000002","PFName":"退休規劃02","EndMark":"N"},{"AISeqNo":"000003","PFName":"購屋頭期03","EndMark":"N"},{"AISeqNo":"000001","PFName":"購屋頭期01","EndMark":"Y"}],"RsCollect2":{"ContractMark":"N"}}}
B80: 075 | C80: 商品應用部 | D80: 財富信託科 | E80: TWTXN00073 | F80: 智能理財系統 | G80: ibrain | H80: Inv021_A | I80: 查詢投組交易明細大項 PortfolioDetail | J80: 查詢投組交易明細大項 | K80: Y | M80: 1 | N80: 45009 | O80: Callee | P80: 程式無異動，故不需另行開發 | Q80: {"RqHeader":{"ChlName":"MAPP","ChlEJNo":"MMA-ETF-EPIQ-Get-0000095798724","ChlSendTime":"2016-09-29T16:25:20","CustomerID":"53948659","CustomerIDCheckcode":"0","ChlIP":"127.0.0.1","Language":""},"SvcRq":{"Rq":{"AISeqNo":"123456","StartDate":"2018/06/01","EndDate":"2018/12/31"}}} | R80: {"RsHeader":{"RsStat":{"RsStatCode":"SUCCESS","Desc":"查詢投組交易明細成功"},"ChlEJNo":"MMA-ETF-REDEM-Create-0000095798724","RqTime":"2016-09-29T16:25:20","RsTime":"2016-09-29T16:35:20"},"SvcRs":{"RsCollect":[{"AISeqNo":"000003","TransOrderNo":"20180306000003","TxDate":"2018/03/06","TxType":"04","TxTypeName":"解約","TxCurrency":"TWD","TxAmt":"94972","PlRatio":"10.52%"},{"AISeqNo":"000003","TransOrderNo":"20180304000006","TxDate":"2018/03/04","TxType":"08","TxTypeName":"變更","TxCurrency":"","TxAmt":"","PlRatio":""},{"AISeqNo":"000003","TransOrderNo":"20180205000009","TxDate":"2018/02/25","TxType":"06","TxTypeName":"配息再申購","TxCurrency":"USD","TxAmt":"2272","PlRatio":""},{"AISeqNo":"000003","TransOrderNo":"20180223000008","TxDate":"2018/02/23","TxType":"05","TxTypeName":"配息","TxCurrency":"TWD","TxAmt":"2272","PlRatio":""},{"AISeqNo":"000003","TransOrderNo":"20180206000009","TxDate":"2018/02/06","TxType":"02","TxTypeName":"定時定額申購","TxCurrency":"TWD","TxAmt":"10000","PlRatio":""},{"AISeqNo":"000003","TransOrderNo":"20180106000003","TxDate":"2018/01/06","TxType":"02","TxTypeName":"定時定額申購","TxCurrency":"TWD","TxAmt":"10000","PlRatio":""},{"AISeqNo":"000003","TransOrderNo":"20180101000003","TxDate":"2018/01/01","TxType":"01","TxTypeName":"單筆申購","TxCurrency":"TWD","TxAmt":"2500000","PlRatio":""}]}}
B81: 076 | C81: 商品應用部 | D81: 財富信託科 | E81: TWTXN00073 | F81: 智能理財系統 | G81: ibrain | H81: Inv022_A | I81: 查詢單筆、定時定額交易明細 InvestmentDetail Buy | J81: 查詢單筆、定時定額交易明細 | K81: Y | M81: 1 | N81: 45009 | O81: Callee | P81: 程式無異動，故不需另行開發 | Q81: {"RsHeader":{"RsStat":{"RsStatCode":"SUCCESS","Desc":"查詢投組交易明細成功"},"ChlEJNo":"MMA-ETF-REDEM-Create-0000095798724","RqTime":"2016-09-29T16:25:20","RsTime":"2016-09-29T16:35:20"},"SvcRs":{"RsCollect":[{"AISeqNo":"000003","TransOrderNo":"20180306000003","TxDate":"2018/03/06","TxType":"04","TxTypeName":"解約","TxCurrency":"TWD","TxAmt":"94972","PlRatio":"10.52%"},{"AISeqNo":"000003","TransOrderNo":"20180304000006","TxDate":"2018/03/04","TxType":"08","TxTypeName":"變更","TxCurrency":"","TxAmt":"","PlRatio":""},{"AISeqNo":"000003","TransOrderNo":"20180205000009","TxDate":"2018/02/25","TxType":"06","TxTypeName":"配息再申購","TxCurrency":"USD","TxAmt":"2272","PlRatio":""},{"AISeqNo":"000003","TransOrderNo":"20180223000008","TxDate":"2018/02/23","TxType":"05","TxTypeName":"配息","TxCurrency":"TWD","TxAmt":"2272","PlRatio":""},{"AISeqNo":"000003","TransOrderNo":"20180206000009","TxDate":"2018/02/06","TxType":"02","TxTypeName":"定時定額申購","TxCurrency":"TWD","TxAmt":"10000","PlRatio":""},{"AISeqNo":"000003","TransOrderNo":"20180106000003","TxDate":"2018/01/06","TxType":"02","TxTypeName":"定時定額申購","TxCurrency":"TWD","TxAmt":"10000","PlRatio":""},{"AISeqNo":"000003","TransOrderNo":"20180101000003","TxDate":"2018/01/01","TxType":"01","TxTypeName":"單筆申購","TxCurrency":"TWD","TxAmt":"2500000","PlRatio":""}]}} | R81: {"RsHeader":{"RsStat":{"RsStatCode":"SUCCESS","Desc":"查詢單筆、定時定額交易明細成功"},"ChlEJNo":"MMA-ETF-REDEM-Create-0000095798724","RqTime":"2016-09-29T16:25:20","RsTime":"2016-09-29T16:35:20"},"SvcRs":{"RsCollect":{"AISeqNo":"000003","PFName":"退休規劃01","TxType":"01","TransDate":"2018/01/26","TxAmt":"5000","RspDeduDate":"","TrustCurrency":"TWD","DeduAccount":"001-018-12345678","TrustAccount":"001-020-12345678","StEndDate":"2018/01/01~2038/01/30"},"ETFDetail":[{"MarketName":"美國股市","MarketID":"01","ETFID":"VTI","ETFName":"先鋒整體股市ETF","TxClass":"買進","TrustCurrency":"TWD","TxAmt":"4000","TxDate":"2018/01/03","Unit":"50.1277","Price":"71.12","ProductCurrency":"USD","ExchangeRate":"29.62","ExrateDate":"2018/01/03"},{"MarketName":"已開發股市(美國除外)","MarketID":"02","ETFID":"VEA","ETFName":"先鋒B","TxClass":"買進","TrustCurrency":"TWD","TxAmt":"3000","TxDate":"2018/01/03","Unit":"50.1277","Price":"71.12","ProductCurrency":"USD","ExchangeRate":"29.62","ExrateDate":"2018/01/03"},{"MarketName":"長期公債","MarketID":"04","ETFID":"VGLT","ETFName":"公債L","TxClass":"買進","TrustCurrency":"TWD","TxAmt":"2000","TxDate":"2018/01/03","Unit":"50.1277","Price":"71.12","ProductCurrency":"USD","ExchangeRate":"29.62","ExrateDate":"2018/01/03"},{"MarketName":"中期公債VGIT","MarketID":"05","ETFID":"VGIT","ETFName":"中期M","TxClass":"買進","TrustCurrency":"TWD","TxAmt":"2000","TxDate":"2018/01/03","Unit":"50.1277","Price":"71.12","ProductCurrency":"USD","ExchangeRate":"29.62","ExrateDate":"2018/01/03"},{"MarketName":"短期公債","MarketID":"06","ETFID":"VGSH","ETFName":"短期S","TxClass":"買進","TrustCurrency":"TWD","TxAmt":"2000","TxDate":"2018/01/03","Unit":"50.1277","Price":"71.12","ProductCurrency":"USD","ExchangeRate":"29.62","ExrateDate":"2018/01/03"}]}}
B82: 077 | C82: 商品應用部 | D82: 財富信託科 | E82: TWTXN00073 | F82: 智能理財系統 | G82: ibrain | H82: Inv023_A | I82: 查詢解約交易明細 InvestmentDetailRedem | J82: 查詢解約交易明細 | K82: Y | M82: 1 | N82: 45009 | O82: Callee | P82: 程式無異動，故不需另行開發 | Q82: {"RqHeader":{"ChlName":"MAPP","ChlEJNo":"MMA-ETF-EPIQ-Get-0000095798724","ChlSendTime":"2016-09-29T16:25:20","CustomerID":"53948659","CustomerIDCheckcode":"0","ChlIP":"127.0.0.1","Language":""},"SvcRq":{"Rq":{"AISeqNo":"123456","TransOrderNo":"20180101000001","TxType":"04"}}} | R82: {"RsHeader":{"RsStat":{"RsStatCode":"SUCCESS","Desc":"查詢解約交易明細成功"},"ChlEJNo":"MMA-ETF-REDEM-Create-0000095798724","RqTime":"2016-09-29T16:25:20","RsTime":"2016-09-29T16:35:20"},"SvcRs":{"RsCollect":{"AISeqNo":"000003","PFName":"退休規劃01","TxypeCode":"04","TxTypeName":"解約","TxDate":"2018/01/26","DealDollar":"5000","InvestAmt":"5000","PlRatio":"14.00","ManageFee":"1200","AccountDollar":"3800","Currency":"TWD","DeduAccount":"1234567890123456","StEndDate":"2018/01/01~2038/01/30"},"ETFDetail":[{"MarketName":"美國股市","MarketID":"01","ETFID":"VTI","ETFName":"先鋒整體股市ETF","TxName":"賣出","TxAmt":"4000","TxDate":"2018/01/03","Unit":"50.1277","Price":"71.12","Currency":"USD","ExchangeRate":"29.62","ExrateDate":"2018/01/03"},{"MarketName":"已開發股市(美國除外)","MarketID":"02","ETFID":"VEA","ETFName":"先鋒B","TxName":"賣出","TxAmt":"3000","TxDate":"2018/01/03","Unit":"50.1277","Price":"71.12","Currency":"USD","ExchangeRate":"29.62","ExrateDate":"2018/01/03"},{"MarketName":"長期公債","MarketID":"04","ETFID":"VGLT","ETFName":"公債L","TxName":"賣出","TxAmt":"2000","TxDate":"2018/01/03","Unit":"50.1277","Price":"71.12","Currency":"USD","ExchangeRate":"29.62","ExrateDate":"2018/01/03"},{"MarketName":"中期公債","MarketID":"05","ETFID":"VGIT","ETFName":"中期M","TxName":"賣出","TxAmt":"2000","TxDate":"2018/01/03","Unit":"50.1277","Price":"71.12","Currency":"USD","ExchangeRate":"29.62","ExrateDate":"2018/01/03"},{"MarketName":"短期公債","MarketID":"06","ETFID":"VGSH","ETFName":"短期S","TxName":"賣出","TxAmt":"2000","TxDate":"2018/01/03","Unit":"50.1277","Price":"71.12","Currency":"USD","ExchangeRate":"29.62","ExrateDate":"2018/01/03"}]}}
B83: 078 | C83: 商品應用部 | D83: 財富信託科 | E83: TWTXN00073 | F83: 智能理財系統 | G83: ibrain | H83: Inv024_A | I83: 查詢配息入帳交易明細 InvestmentDetailDividendRecord | J83: 查詢配息入帳交易明細 | K83: Y | M83: 1 | N83: 45009 | O83: Callee | P83: 程式無異動，故不需另行開發 | Q83: {"RqHeader":{"ChlName":"MAPP","ChlEJNo":"MMA-ETF-EPIQ-Get-0000095798724","ChlSendTime":"2016-09-29T16:25:20","CustomerID":"53948659","CustomerIDCheckcode":"0","ChlIP":"127.0.0.1","Language":""},"SvcRq":{"Rq":{"AISeqNo":"123456","TransOrderNo":"20180101000001","TxType":"05"}}} | R83: {"RsHeader":{"RsStat":{"RsStatCode":"SUCCESS","Desc":"查詢配息入帳交易明細成功"},"ChlEJNo":"MMA-ETF-REDEM-Create-0000095798724","RqTime":"2016-09-29T16:25:20","RsTime":"2016-09-29T16:35:20"},"SvcRs":{"RsCollect":{"AISeqNo":"000003","PFName":"退休規劃01","TxType":"05","TxTypeName":"配息","TxDate":"2018/1/6","TrustCurrency":"TWD","TxAmt":"1080","EnterAccountNo":"001-018-00001234"},"ETFDetail":{"MarketName":"美國股市","MarketID":"01","ETFID":"VTI","ETFName":"先鋒整體股市ETF","DividendDate":"2018/1/2","DividendSettleDate":"2018/1/5","ProductCurrency":"USD","ExchangeRate":"29.62","ExrateDate":"2018/1/6"}}}
B84: 079 | C84: 商品應用部 | D84: 財富信託科 | E84: TWTXN00073 | F84: 智能理財系統 | G84: ibrain | H84: Inv025_A | I84: 查詢配息轉申購交易明細 InvestmentDetailDividendBuy | J84: 查詢配息轉申購交易明細 | K84: Y | M84: 1 | N84: 45009 | O84: Callee | P84: 程式無異動，故不需另行開發 | Q84: {"RqHeader":{"ChlName":"MAPP","ChlEJNo":"MMA-ETF-EPIQ-Get-0000095798724","ChlSendTime":"2016-09-29T16:25:20","CustomerID":"53948659","CustomerIDCheckcode":"0","ChlIP":"127.0.0.1","Language":""},"SvcRq":{"Rq":{"AISeqNo":"123456","TransOrderNo":"20180101000001","TxType":"06"}}} | R84: {"RsHeader":{"RsStat":{"RsStatCode":"SUCCESS","Desc":"查詢配息轉申購交易明細成功"},"ChlEJNo":"MMA-ETF-REDEM-Create-0000095798724","RqTime":"2016-09-29T16:25:20","RsTime":"2016-09-29T16:35:20"},"SvcRs":{"RsCollect":{"AISeqNo":"000003","PFName":"退休規劃01","TxType":"06","BuyTxDate":"2018/1/6","Currency":"TWD","TxAmt":"2722","TrustAccount":"001-020-12345678","StEndDate":"2018/01/01~2038/01/30"},"ETFDetail":[{"TxClass":"配息","MarketName":"美國股市","MarketID":"01","ETFID":"VTI","ETFName":"先鋒整體股市ETF","TxAmt":"2722","DividendDate":"2018/1/2","TxDate":"2018/1/5","Unit":"","Price":"","ProductCurrency":"USD","ExchangeRate":"1","ExrateDate":"2018/1/5"},{"TxClass":"買進","MarketName":"美國股市","MarketID":"01","ETFID":"VTI","ETFName":"先鋒整體股市ETF","TxAmt":"2722","DividendDate":"","TxDate":"2018/1/2","Unit":"52.2174","Price":"71.12","ProductCurrency":"USD","ExchangeRate":"29.62","ExrateDate":"2018/1/6"}]}}
B85: 080 | C85: 商品應用部 | D85: 財富信託科 | E85: TWTXN00073 | F85: 智能理財系統 | G85: ibrain | H85: Inv026_A | I85: 查詢資產再平衡交易明細 InvestmentDetailRebalance | J85: 查詢資產再平衡交易明細 | K85: Y | M85: 1 | N85: 45009 | O85: Callee | P85: 程式無異動，故不需另行開發 | Q85: {"RqHeader":{"ChlName":"MAPP","ChlEJNo":"MMA-ETF-EPIQ-Get-0000095798724","ChlSendTime":"2016-09-29T16:25:20","CustomerID":"53948659","CustomerIDCheckcode":"0","ChlIP":"127.0.0.1","Language":""},"SvcRq":{"Rq":{"AISeqNo":"123456","TransOrderNo":"20180101000001","TxType":"01"}}} | R85: {"RsHeader":{"RsStat":{"RsStatCode":"SUCCESS","Desc":"查詢資產再平衡交易明細成功"},"ChlEJNo":"MMA-ETF-EPIQ-GET-0000095798724","RqTime":"2016-09-29T16:25:20","RsTime":"2016-09-29T16:35:20"},"SvcRs":{"RsCollect":{"AISeqNo":"000003","PFName":"退休規劃01","TxType":"01","TxTypeName":"資產再平衡","TransDate":"2018/01/26","TxAmt":"5000","TrustCurrency":"TWD","DeduAccount":"001-018-12345678","TrustAccount":"001-020-12345678","StEndDate":"2018/01/01~2038/01/30"},"ETFDetail":[{"MarketName":"美國股市","MarketID":"01","ETFID":"VTI","ETFName":"先鋒整體股市ETF","TxClass":"買進","TrustCurrency":"TWD","TxAmt":"4000","TxDate":"2018/01/03","Unit":"50.1277","Price":"71.12","ProductCurrency":"USD","ExchangeRate":"29.62","ExrateDate":"2018/01/03"},{"MarketName":"已開發股市(美國除外)","MarketID":"02","ETFID":"VEA","ETFName":"先鋒B","TxClass":"買進","TrustCurrency":"TWD","TxAmt":"3000","TxDate":"2018/01/03","Unit":"50.1277","Price":"71.12","ProductCurrency":"USD","ExchangeRate":"29.62","ExrateDate":"2018/01/03"},{"MarketName":"長期公債","MarketID":"04","ETFID":"VGLT","ETFName":"公債L","TxClass":"賣出","TrustCurrency":"TWD","TxAmt":"2000","TxDate":"2018/01/03","Unit":"50.1277","Price":"71.12","ProductCurrency":"USD","ExchangeRate":"29.62","ExrateDate":"2018/01/03"},{"MarketName":"中期公債VGIT","MarketID":"05","ETFID":"VGIT","ETFName":"中期M","TxClass":"賣出","TrustCurrency":"TWD","TxAmt":"2000","TxDate":"2018/01/03","Unit":"50.1277","Price":"71.12","ProductCurrency":"USD","ExchangeRate":"29.62","ExrateDate":"2018/01/03"},{"MarketName":"短期公債","MarketID":"06","ETFID":"VGSH","ETFName":"短期S","TxClass":"賣出","TrustCurrency":"TWD","TxAmt":"2000","TxDate":"2018/01/03","Unit":"50.1277","Price":"71.12","ProductCurrency":"USD","ExchangeRate":"29.62","ExrateDate":"2018/01/03"}]}}
B86: 081 | C86: 商品應用部 | D86: 財富信託科 | E86: TWTXN00073 | F86: 智能理財系統 | G86: ibrain | H86: Inv027_A | I86: 取得資產再平衡交易清單 RebalanceGet | J86: 取得資產再平衡交易清單 | K86: Y | M86: 1 | N86: 45009 | O86: Callee | P86: 程式無異動，故不需另行開發 | Q86: {"RqHeader":{"ChlName":"EBANK","ChlEJNo":"MMA-ETF-Rebalance-Get-0000095798724","ChlSendTime":"2019/04/2516:25:10","ChlIP":"127.0.0.1","Language":"TC","Version":"1.0","CustomerID":"A158012017","CustomerIDCheckcode":"0"},"SvcRq":{"Rq":{}}} | R86: {"RsHeader":{"RsStat":{"RsStatCode":"SUCCESS","Desc":"查詢資產再平衡-確認清單成功"},"ChlEJNo":"MMA-ETF-Rebalance-Get-0000095798724","RqTime":"2019/04/2516:25:10","RsTime":"2019/04/2516:27:30"},"SvcRs":{"RsCollect1":[{"PFName":"退休規劃","AISeqNo":"000001","RedemEffectiveDate":"2019/05/15","RebalanceNo":"000001-1905","TxTime":"","ValidTime":"2019/07/2516:26:20","RiskMark":"Y"},{"PFName":"退休規劃","AISeqNo":"000002","RedemEffectiveDate":"2019/05/15","RebalanceNo":"000002-1905","TxTime":"","ValidTime":"2019/07/2516:26:20","RiskMark":"N"}], "RsCollect2":[{"PFName":"退休規劃","AISeqNo":"000001","RebalanceNo":"000002-1904","TxTime":"2019/06-2516:26:20","ValidTime":"2019/07/2516:26:20"},{"PFName":"退休規劃","AISeqNo":"000002","RebalanceNo":"000002-1904","TxTime":"2019/06-2516:26:20","ValidTime":"2019/07/2516:26:20"}], "RsCollect3":[{"PFName":"退休規劃","AISeqNo":"000001","RebalanceNo":"000002-1904","TxTime":"","ValidTime":"2019/01/1016:26:20"},{"PFName":"退休規劃","AISeqNo":"000002","RebalanceNo":"000002-1904","TxTime":"","ValidTime":"2019/01/1216:26:20"}]}}
B87: 082 | C87: 商品應用部 | D87: 財富信託科 | E87: TWTXN00073 | F87: 智能理財系統 | G87: ibrain | H87: Inv028_A | I87: 確認資產再平衡交易 RebalanceConfirm | J87: 確認資產再平衡交易 | K87: Y | M87: 1 | N87: 45009 | O87: Callee | P87: 程式無異動，故不需另行開發 | Q87: {"RqHeader":{"ChlName":"EBANK","ChlEJNo":"MMA-ETF-Rebalance-Confirm-0000095798724","ChlSendTime":"2019/04/2516:25:10","ChlIP":"127.0.0.1","Language":"TC","Version":"1.0","CustomerID":"A158012017","CustomerIDCheckcode":"0"},"SvcRq":{"Rq":{"AISeqNo":"000143","RedemEffectiveDate":"2019/05/15"}}} | R87: {"RsHeader":{"RsStat":{"RsStatCode":"SUCCESS","Desc":"確認資產再平衡項目成功"},"ChlEJNo":"MMA-ETF-Rebalance-Confirm-0000095798724","RqTime":"2019/04/2516:25:10","RsTime":"2019/04/2516:27:30"},"SvcRs":{"RsCollect":{"ValidTime":"2019/04/2516:25:10","InitialDate":"2019/04/2516:25:10","MaturityDate":"2022-04/2516:25:10","InvYears":"35","TargetDollar":"10000000","TotalInvestDollar":"932000","TotalPV":"891387","PLRatio":"4.36","PLCalDate":"2018-01/1200:00:00","RedemEffectiveDate":"2018-01/1200:00:00","ResubEffectiveDate":"2019/01/1200:00:00","Currency":"TWD","PFStockRatio":"43","ResubStockRatio":"57","PFBondRatio":"45","ResubBondRatio":"55","RR6Check":"Y","ProductPI":"N","CustomerRiskLevel":"N","ProductYear":"Y","InvestYear":"Y","HasRspDollar":"1""Special":"Y","Over70":"Y"},"ETFDetail":[{"MarketName":"美國股市","MarketID":"01","ETFID":"VTI","ETFName":"先鋒整體股市ETF","Ntpv":"184259","MarketRatio":"35.40","ResubMarketRatio":"33.40","PortfolioLevel":"RR6"},{"MarketName":"已開發股市(美國除外)","MarketID":"02","ETFID":"VEA","ETFName":"先鋒富時已開發股市ETF","Ntpv":"112536","MarketRatio":"21.62","ResubMarketRatio":"23.62","PortfolioLevel":"RR6"},{"MarketName":"已開發股市(美國除外)","MarketID":"04","ETFID":"VGLT","ETFName":"先鋒長期政府公債","Ntpv":"139902","MarketRatio":"26.87","ResubMarketRatio":"26.87","PortfolioLevel":"RR6"}]}}
B88: 083 | C88: 商品應用部 | D88: 財富信託科 | E88: TWTXN00073 | F88: 智能理財系統 | G88: ibrain | H88: Inv029_A | I88: 新增資產再平衡交易 RebalanceCreate | J88: 新增資產再平衡交易 | K88: Y | M88: 1 | N88: 45009 | O88: Callee | P88: 程式無異動，故不需另行開發 | Q88: {"RqHeader":{"ChlName":"EBANK","ChlEJNo":"MMA-ETF-Rebalance-Create-0000095798724","ChlSendTime":"2019/04/2516:25:10","ChlIP":"127.0.0.1","Language":"TC","Version":"1.0","CustomerID":"A158012017","CustomerIDCheckcode":"0"},"SvcRq":{"Rq":{"AISeqNo":"000001","RedemEffectiveDate":"2019/04/2516:25:10"}}} | R88: {"RsHeader":{"RsStat":{"RsStatCode":"SUCCESS","Desc":"新增資產再平衡項目成功"},"ChlEJNo":"MMA-ETF-Rebalance-Create-0000095798724","RqTime":"2019/04/2516:25:10","RsTime":"2019/04/2516:27:30"},"SvcRs":{"RsCollect":{"ValidTime":"2019/04/2516:25:10","InitialDate":"2019/04/2516:25:10","MaturityDate":"2022-04/2516:25:10","InvYears":"35","TargetDollar":"10000000","TotalInvestDollar":"932000","TotalPV":"891387","PLRatio":"4.36","PLCalDate":"2018-01/1200:00:00","RedemEffectiveDate":"2018-01/1200:00:00","ResubEffectiveDate":"2019/01/1200:00:00","Currency":"TWD","PFStockRatio":"43","ResubStockRatio":"57","PFBondRatio":"45","ResubBondRatio":"55"},"ETFDetail":[{"MarketName":"美國股市","MarketID":"01","ETFID":"VTI","ETFName":"先鋒整體股市ETF","Ntpv":"184259","MarketRatio":"35.40","ResubMarketRatio":"33.40","RiskLevel":"RR6"},{"MarketName":"已開發股市(美國除外)","MarketID":"02","ETFID":"VEA","ETFName":"先鋒富時已開發股市ETF","Ntpv":"112536","MarketRatio":"21.62","ResubMarketRatio":"23.62","RiskLevel":"RR6"},{"MarketName":"已開發股市(美國除外)","MarketID":"04","ETFID":"VGLT","ETFName":"先鋒長期政府公債","Ntpv":"139902","MarketRatio":"26.87","ResubMarketRatio":"26.87","RiskLevel":"RR6"}]}}
B89: 084 | C89: 商品應用部 | D89: 財富信託科 | E89: TWTXN00073 | F89: 智能理財系統 | G89: ibrain | H89: Inv030_A | I89: 檢核本行投資屬性問卷2019 funCheckRisk2019 | J89: 檢核本行投資屬性問卷2019 | K89: Y | M89: 1 | N89: 45009 | O89: Callee | P89: 程式無異動，故不需另行開發 | Q89: {"RqHeader":{"ChlName":"MAPP","ChlEJNo":"MMA-AI-ETF-GET2019-0000095798724","ChlSendTime":"2016-09-29T16:25:20","CustomerID":"A102240601","CustomerIDCheckcode":"0","ChlIP":"127.0.0.1","Language":""},"SvcRq":{"Rq":{"CustomerID":"A102240601","CustomerIDCheckcode":"0"}}} | R89: {"RsHeader":{"RsStat":{"RsStatCode":"SUCCESS","Desc":"取得檢核本行投資屬性問卷成功"},"ChlEJNo":"MMA-AI-ETF-GET2019-0000095798724","RqTime":"2016-09-29T16:25:20","RsTime":"2016-09-29T16:35:20"},"SvcRs":{"RsCollect":{"RC2016":"Y","ManlevelOut":"RR5","DefaultGainPoint":"30","DefaultLossPoint":"30","F_ETFFG":"Y","KYCEndDate":"2018/01/01","Email":"abc@sinopac.com","F_ETFFlag":"Y","ContactLost":"Y",}}}
B90: 085 | C90: 商品應用部 | D90: 財富信託科 | E90: TWTXN00073 | F90: 智能理財系統 | G90: ibrain | H90: Inv031_A | I90: 收費查詢 DeductionManageFee | J90: 收費查詢 | K90: Y | M90: 1 | N90: 45009 | O90: Callee | P90: 程式無異動，故不需另行開發 | Q90: {"RqHeader":{"ChlName":"MAPP","ChlEJNo":"MMA-AI-ETF-DMFee-0000095798724","ChlSendTime":"2016-09-29T16:25:20","CustomerID":"A102240601","CustomerIDCheckcode":"0","ChlIP":"127.0.0.1","Language":""},"SvcRq":{"Rq":{"AISeqNo":"000006","StartDate":"2018/07/01","EndDate":"2019/06/30"}}} | R90: {"RsHeader":{"RsStat":{"RsStatCode":"SUCCESS","Desc":"收費查詢成功"},"ChlEJNo":"MMA-ETF-DMFee-0000095798724","RqTime":"2016-09-29T16:25:20","RsTime":"2016-09-29T16:35:20"},"SvcRs":{"RsCollect1":[{"AISeqNo":"000003","PFName":"我的A計畫","ManageFee":"2500","UnManageFee":"2500","Currency":"TWD","FeeDetail":[{"ManageFeeDate":"2019年07月","CurrentManageFee":"3000","CurrentDeductionAmount":"2000","DeductionAccountNo":"1234567890123456"},{"ManageFeeDate":"2019年06月","CurrentManageFee":"1500","CurrentDeductionAmount":"0","DeductionAccountNo":"1234567890123456"}]},{"AISeqNo":"000002","PFName":"我的B計畫","ManageFee":"500","UnManageFee":"0","Currency":"TWD","FeeDetail":[{"ManageFeeDate":"2019年07月","CurrentManageFee":"3000","CurrentDeductionAmount":"2000","DeductionAccountNo":"1234567890123456"},{"ManageFeeDate":"2019年06月","CurrentManageFee":"1500","CurrentDeductionAmount":"0","DeductionAccountNo":"1234567890123456"}]},{"AISeqNo":"000001","PFName":"我的C計畫","ManageFee":"5000","UnManageFee":"1500","Currency":"TWD","FeeDetail":[{"ManageFeeDate":"2019年07月","CurrentManageFee":"3000","CurrentDeductionAmount":"2000","DeductionAccountNo":"1234567890123456"},{"ManageFeeDate":"2019年06月","CurrentManageFee":"1500","CurrentDeductionAmount":"0","DeductionAccountNo":"1234567890123456"}]}],, "RsCollect2":{"ContractMark":"N"}}}
B91: 086 | C91: 商品應用部 | D91: 財富信託科 | E91: TWTXN00073 | F91: 智能理財系統 | G91: ibrain | H91: Inv032_A | I91: 訊息通知查詢 MsgNoticeList | J91: 訊息通知查詢 | K91: Y | M91: 1 | N91: 45009 | O91: Callee | P91: 程式無異動，故不需另行開發 | Q91: {"RqHeader":{"ChlName":"MAPP","ChlEJNo":"MMA-AI-ETF-DMFee-0000095798724","ChlSendTime":"2016-09-29T16:25:20","CustomerID":"A102240601","CustomerIDCheckcode":"0","ChlIP":"127.0.0.1","Language":""},"SvcRq":{"Rq":{"AISeqNo":"000006","StartDate":"2018/07/01","EndDate":"2019/06/30"}}} | R91: {"RsHeader":{"RsStat":{"RsStatCode":"SUCCESS","Desc":"訊息通知查詢成功"},"ChlEJNo":"MMA-ETF-DMFee-0000095798724","RqTime":"2016-09-29T16:25:20","RsTime":"2016-09-29T16:35:20"},"SvcRs":{"AISeqNo":"000001","PFName":"我的計畫","RsCollect1":[{"NOTICE_DATE":"2019/01/10","NOTICE_TYPE":"申購成功","PUSH_MSG_TEXT":"您的投資組合退休規劃01於2019年1月6日申購成功。"},{"NOTICE_DATE":"2019/02/01","NOTICE_TYPE":"申購成功","PUSH_MSG_TEXT":"您的投資組合退休規劃01於2019年1月6日解約成功。"}],"RsCollect2":[{"NOTICE_DATE":"2019/01/03","NOTICE_TYPE":"Rebalance通知","PUSH_MSG_TEXT":"您的投資組合退休規劃02，經本行檢視不用執行資產再平衡。"},{"NOTICE_DATE":"2019/01/12","NOTICE_TYPE":"Rebalance通知","PUSH_MSG_TEXT":"因您未於有效期限內確認投資組合退休規劃02之資產再平衡內容，故本行無法執行資產再平衡。"}]}}
B92: 087 | C92: 商品應用部 | D92: 財富信託科 | E92: TWTXN00073 | F92: 智能理財系統 | G92: ibrain | H92: Inv033_A | I92: 取得ETF投組變更資料 DeduChangeGet | J92: 取得ETF投組變更資料 | K92: Y | M92: 1 | N92: 44993 | O92: Callee | Q92: {"RqHeader":{"ChlName":"MAPP","ChlEJNo":"MMA-ETF-REDEM-Get-0000095798724","ChlSendTime":"2016-09-29T16:25:20","CustomerID":"53948659","CustomerIDCheckcode":"0","ChlIP":"127.0.0.1","Language":""},"SvcRq":{"Rq":{"AISeqNo":"123456","DeduChangeType":"1"}}} | R92: {"RsHeader":{"RsStat":{"RsStatCode":"SUCCESS","Desc":"取得ETF投組變更資料成功"},"ChlEJNo":"MMA-ETF-REDEM-Get-0000095798724","RqTime":"2016-09-29T16:25:20","RsTime":"2016-09-29T16:35:20"},"SvcRs":{"RsCollection":{"AISeqNo":"123456","DeduChangeType":"1","RSPDeduDate":"06","RSPDollar":"6000","AccountNo":"01500312345678","CreateDate":"2019/12/12","Currency":"TWD","MinDollar":"3000","RiskMark":"N",}}}驗證發生錯誤{"RsHeader":{"RsStat":{"RsStatCode":"FAIL","Desc":"取得ETF投組變更資料錯誤"},"ChlEJNo":"MMA-ETF-REDEM-Get-0000095798724","RqTime":"2016-09-29T16:25:20","RsTime":"2016-09-29T16:26:38"},"SvcRs":{}}
B93: 088 | C93: 商品應用部 | D93: 財富信託科 | E93: TWTXN00073 | F93: 智能理財系統 | G93: ibrain | H93: Inv034_A | I93: 確認ETF投組變更資料 DeduChangeConfirm | J93: 確認ETF投組變更資料 | K93: Y | M93: 1 | N93: 44993 | O93: Callee | Q93: {"RqHeader":{"ChlName":"MAPP","ChlEJNo":"MMA-ETF-REDEM-Get-0000095798724","ChlSendTime":"2016-09-29T16:25:20","CustomerID":"53948659","CustomerIDCheckcode":"0","ChlIP":"127.0.0.1","Language":""},"SvcRq":{"Rq":{"AISeqNo":"123456","DeduChangeType":"1(或2)","RSPDeduDate":"","RSPDollar":"","AccountNo":"","CreateDate":"2019/01/29"}}}DeduChangeType=3{"RqHeader":{"ChlName":"MAPP","ChlEJNo":"MMA-ETF-REDEM-Get-0000095798724","ChlSendTime":"2016-09-29T16:25:20","CustomerID":"53948659","CustomerIDCheckcode":"0","ChlIP":"127.0.0.1","Language":""},"SvcRq":{"Rq":{"AISeqNo":"123456","DeduChangeType":"3","RSPDeduDate":"06","RSPDollar":"5000","AccountNo":"01500312345678","CreateDate":"2019/01/29"}}} | R93: {"RsHeader":{"RsStat":{"RsStatCode":"SUCCESS","Desc":"確認ETF投組變更資料成功"},"ChlEJNo":"MMA-ETF-REDEM-Get-0000095798724","RqTime":"2016-09-29T16:25:20","RsTime":"2016-09-29T16:35:20"},"SvcRs":{"RsCollection":{"AISeqNo":"123456","StEndDate":"2016/01/01~2051/12/31","RSPDeduDate":"06","Pvalue":"94792","DeduChangeType":"1","RSPDollar":"6000","AccountNo":"01500312345678","CreateDate":"2019/01/29","DeduChangeDate":"2019/02/06","Currency":"TWD","PFName":"購屋頭期(00001)", "Special":"Y"}}}
B94: 089 | C94: 商品應用部 | D94: 財富信託科 | E94: TWTXN00073 | F94: 智能理財系統 | G94: ibrain | H94: Inv035_A | I94: 新增ETF投組變更交易 DeduChangeCreate | J94: 新增ETF投組變更交易 | K94: Y | M94: 1 | N94: 44993 | O94: Callee | Q94: {"RqHeader":{"ChlName":"MAPP","ChlEJNo":"MMA-ETF-REDEM-Get-0000095798724","ChlSendTime":"2016-09-29T16:25:20","CustomerID":"53948659","CustomerIDCheckcode":"0","ChlIP":"127.0.0.1","Language":""},"SvcRq":{"Rq":{"AISeqNo":"123456","DeduChangeType":"1(或2)","RSPDeduDate":"","RSPDollar":"","AccountNo":"","CreateDate":"2019/01/29","DeduChangeDate":"2019/02/06"}}}DeduChangeType=3{"RqHeader":{"ChlName":"MAPP","ChlEJNo":"MMA-ETF-REDEM-Get-0000095798724","ChlSendTime":"2016-09-29T16:25:20","CustomerID":"53948659","CustomerIDCheckcode":"0","ChlIP":"127.0.0.1","Language":""},"SvcRq":{"Rq":{"AISeqNo":"123456","DeduChangeType":"3","RSPDeduDate":"06","RSPDollar":"6000","AccountNo":"01500312345678","CreateDate":"2019/01/29","DeduChangeDate":"2019/02/06"}}} | R94: {"RsHeader":{"RsStat":{"RsStatCode":"SUCCESS","Desc":"新增ETF投組變更交易成功"},"ChlEJNo":"MMA-ETF-REDEM-Get-0000095798724","RqTime":"2016-09-29T16:25:20","RsTime":"2016-09-29T16:35:20"},"SvcRs":{"RsCollection":{"AISeqNo":"123456","StEndDate":"2016/01/01~2051/12/31","RSPDeduDate":"06","Pvalue":"94792","DeduChangeType":"1","RSPDollar":"6000","AccountNo":"01500312345678","CreateDate":"2019/01/29","DeduChangeDate":"2019/01/30","Currency":"TWD""PFName":"購屋頭期(00001)"}}}
B95: 090 | C95: 商品應用部 | D95: 財富信託科 | E95: TWTXN00073 | F95: 智能理財系統 | G95: ibrain | H95: Inv036_A | I95: 查詢存活投組清單 DeduChangePortfolioLiveList | J95: 查詢存活投組清單 | K95: Y | M95: 1 | N95: 45009 | O95: Callee | P95: 程式無異動，故不需另行開發 | Q95: {"RqHeader":{"ChlName":"MAPP","ChlEJNo":"MMA-ETF-EPIQ-Get-0000095798724","ChlSendTime":"2016-09-29T16:25:20","CustomerID":"53948659","CustomerIDCheckcode":"0","ChlIP":"127.0.0.1","Language":""},"SvcRq":{}} | R95: {"RsHeader":{"RsStat":{"RsStatCode":"SUCCESS","Desc":"查詢存活投組清單成功"},"ChlEJNo":"MMA-ETF-REDEM-Create-0000095798724","RqTime":"2016-09-29T16:25:20","RsTime":"2016-09-29T16:35:20"},"SvcRs":{"RsCollect1":[{"AISeqNo":"000002","PFName":"退休規劃02",},{"AISeqNo":"000003","PFName":"購屋頭期03"},{"AISeqNo":"000001","PFName":"購屋頭期01"}],, "RsCollect2":{"ContractMark":"N"}}}
B96: 091 | C96: 商品應用部 | D96: 財富信託科 | E96: TWTXN00073 | F96: 智能理財系統 | G96: ibrain | H96: Inv037_A | I96: 調整計畫清單 AdjustPlanGet | J96: 調整計畫清單 | K96: Y | M96: 1 | N96: 44993 | O96: Callee | Q96: {"RqHeader":{"ChlName":"EBANK","ChlEJNo":"MMA-ETF-Adjust-Get-0000095798724","ChlSendTime":"2019/04/2516:25:10","ChlIP":"127.0.0.1","Language":"TC","Version":"1.0","CustomerID":"A158012017","CustomerIDCheckcode":"0"},"SvcRq":{"Rq":{}}} | R96: {"RsHeader":{"RsStat":{"RsStatCode":"SUCCESS","Desc":"查詢調整計畫-清單成功"},"ChlEJNo":"MMA-ETF-Adjust-Get-0000095798724","RqTime":"2019/04/2516:25:10","RsTime":"2019/04/2516:27:30"},"SvcRs":{"RsCollect1":[{"PFName":"退休規劃000001","AISeqNo":"000001","AdjustDate":"XX年XX月","AdjustDateCount":"5","AdjustRSP":"8000","AdjustTargetDollar":"8000000","AdjustInitialDollar":"10000","DeduChangeType":"1","AccountNo":"01500312345678","ActNo":"00100412345678","IPigNo":"CEVT-P60-98-xx","IPigDESC":"夢想"},{"PFName":"退休規劃000002","AISeqNo":"000002","AdjustDate":"2023/03/01","AdjustDateCount":"XX年XX月","AdjustRSP":"8000","AdjustTargetDollar":"8000000","AdjustInitialDollar":"10000","DeduChangeType":"1","AccountNo":"01500312345678","ActNo":"","IPigNo":"","IPigDESC":""}], "RsCollect2":[{"PFName":"退休規劃","AISeqNo":"000004","AdjustNo":"000002-1904","TxTime":"2019/06-2516:26:20"},{"PFName":"退休規劃","AISeqNo":"000005","AdjustNo":"000002-1905","TxTime":"2019/06-2516:26:20"}]}}
B97: 092 | C97: 商品應用部 | D97: 財富信託科 | E97: TWTXN00073 | F97: 智能理財系統 | G97: ibrain | H97: Inv038_A | I97: 調整計畫確認 AdjustPlanConfirm | J97: 調整計畫確認 | K97: Y | M97: 1 | N97: 44993 | O97: Callee | Q97: {"RqHeader":{"ChlName":"MAPP","ChlEJNo":"MMA-ETF-Adjust-Confirm-0000095798724","ChlSendTime":"2016-09-29T16:25:20","CustomerID":"53948659","CustomerIDCheckcode":"0","ChlIP":"127.0.0.1","Language":""},"SvcRq":{"Rq":{"AISeqNo":"123456","AdjustType":"1","AdjustDate":"2023/03/01","AdjustDateCount":"XX年XX月","AdjustRSP":"8000","AdjustTargetDollar":"3000000","AdjustInitialDollar":"100000","AccountNo":"1234567890123456","TrustAccount":"1234567890123456","DeduChangeType":"1","DeduChangeTypeConfirm":"2"}}} | R97: {"RsHeader":{"RsStat":{"RsStatCode":"SUCCESS","Desc":"確認ETF投組調整計畫成功"},"ChlEJNo":"MMA-ETF-REDEM-Get-0000095798724","RqTime":"2016-09-29T16:25:20","RsTime":"2016-09-29T16:35:20"},"SvcRs":{"RsCollection":{"AISeqNo":"123456","PFName":"購屋頭期(00001)","AdjustType":"4","RspDeduDate":"16","InitialEffectiveDate":"2016/01/01","MaturityDate":"2019/01/31","InitialDollarType":"38000”,"RSPDollarType":"5000","Invest_Years":"10","DeduChangeType":"4","AdjustDate":"2023/03/01","AdjustDateCount":"XX年XX月","AdjustRSP":"8000","AdjustTargetDollar":"3000000","AdjustInitialDollar":"100000","Stock_Ratio":"50","Bond_Ratio":"50","StockA_ID":"VTI","StockB_ID":"VEA","StockC_ID":"","BondL_ID":"VGLT","BondM_ID":"VGIT","BondS_ID":"VGSH","StockA_Name":"先鋒整體股市ETF","StockB_Name":"先鋒富時股市ETF","StockC_Name":"","BondL_Name":"先鋒長期政府公債","BondM_Name":"先鋒中期政府公債","BondS_Name":"先鋒短期政府公債","StockA_Ratio":"34","StockB_Ratio":"21","StockC_Ratio":"0","BondL_Ratio":"28","BondM_Ratio":"10","BondS_Ratio":"7","MaturityDateAfter":"2019/06/31","Createdate":"2019/12/12","AccountNo":"1234567890123456","TrustAccount":"1234567890123456","RR6Check":"Y","ProductPI":"N","CustomerRiskLevel":"N","ProductYear":"Y","InvestYear":"Y"}}}
B98: 093 | C98: 商品應用部 | D98: 財富信託科 | E98: TWTXN00073 | F98: 智能理財系統 | G98: ibrain | H98: Inv039_A | I98: 調整計畫結果 AdjustPlanCreate | J98: 調整計畫結果 | K98: Y | M98: 1 | N98: 44993 | O98: Callee | Q98: {"RqHeader":{"ChlName":"MAPP","ChlEJNo":"MMA-ETF-Adjust-Create-0000095798724","ChlSendTime":"2016-09-29T16:25:20","CustomerID":"53948659","CustomerIDCheckcode":"0","ChlIP":"127.0.0.1","Language":""},"SvcRq":{"Rq":{"AISeqNo":"123456","AdjustType":"4","AdjustDate":"OO年OO月","AdjustDateCount":"5","AdjustRSP":"8000","AdjustTargetDollar":"3000000","AdjustInitialDollar":"100000","AccountNo":"0123456789123456","TrustAccount":"0123456789123456","DeduChangeType":"1"}}} | R98: {"RsHeader":{"RsStat":{"RsStatCode":"SUCCESS","Desc":"確認ETF投組調整計畫成功"},"ChlEJNo":"MMA-ETF-REDEM-Create-0000095798724","RqTime":"2016-09-29T16:25:20","RsTime":"2016-09-29T16:35:20"},"SvcRs":{"RsCollection":{"AISeqNo":"123456","PFName":"購屋頭期(00001)","AdjustType":"4","InitialEffectiveDate":"2016/01/01","MaturityDate":"2019/01/31","InitialDollarType":"38000”,"RSPDollarType":"5000","DeduChangeType":"4","AdjustDate":"OO年OO月","AdjustDateCount":"5","AdjustRSP":"8000","AdjustTargetDollar":"3000000","AdjustInitialDollar":"100000","Stock_Ratio":"50","Bond_Ratio":"50","StockA_ID":"VTI","StockB_ID":"VEA","StockC_ID":"","BondL_ID":"VGLT","BondM_ID":"VGIT","BondS_ID":"VGSH","StockA_Name":"先鋒整體股市ETF","StockB_Name":"先鋒富時股市ETF","StockC_Name":"","BondL_Name":"先鋒長期政府公債","BondM_Name":"先鋒中期政府公債","BondS_Name":"先鋒短期政府公債","StockA_Ratio":"34","StockB_Ratio":"21","StockC_Ratio":"0","BondL_Ratio":"28","BondM_Ratio":"10","BondS_Ratio":"7","AccountNo":"01500312345678","TrustAccount":"01500312345678","MaturityDateAfter":"2019/01/31","Createdate":"2019/12/12","DeduChangeType":"1"}}}
B99: 094 | C99: 商品應用部 | D99: 財富信託科 | E99: TWTXN00073 | F99: 智能理財系統 | G99: ibrain | H99: Inv040_A | I99: 簽署投顧約_確認客戶資料表 AdvisorGetCIF | J99: 簽署投顧約_確認客戶資料表 | K99: Y | M99: 1 | N99: 45009 | O99: Callee | P99: 程式無異動，故不需另行開發 | Q99: {"RqHeader":{"MsgID":"","ChlName":"EBANK","ChlEJNo":"MMA-AI_G_ConPdf-0000739377890","ChlSendTime":"2019-12-20T16:53:04","ChlIP":"10.11.161.121","Language":"TC","Verion":null,"CustomerID":"N151412163","CustomerIDCheckcode":"0"},"SvcRq":{"Rq":{}}} | R99: {"RsHeader":{"RsStat":{"RsStatCode":"SUCCESS","Desc":"(投顧委任契約_客戶CIF資料)成功回傳 "},"ChlEJNo":"MMA-AI_AdvisorCif-0002495722774","RqTime":"2022-08-24T10:55:22","RsTime":"2022/08/24 10:55:26"},"SvcRs":{"RsCollect":{"Loss_Mark":"0","CreateDate":"2022/08/01","PI_Mark":"NP00","VerifyNo":14300},"CIFDetail":{"Cust_Id":"B151609433","Birthday":"1990/07/13","EMail":"BANK@SINOPAC.COM","ChName":"中文姓名680289","Gender":"1","AreaNO":"TW","RegAddress1":"台北市松山區市民大道6段151號","PosAddress1":"台北市中山區建國北路二段9-1號","Tel_1":"886-02-87612288","Tel_3":"886-09-11222333","Fax":null,"Manager_Name":null,"Benefit_Id":null,"Benefit_Name":null,"Sector":null,"Industry":null,"Contractor":null,"Contractor_Phone":null,"Auth_Id":null,"Auth_Name":null}}}
B100: 095 | C100: 商品應用部 | D100: 財富信託科 | E100: TWTXN00073 | F100: 智能理財系統 | G100: ibrain | H100: Inv041_A | I100: 簽署投顧約_確認客戶資料表 AdvisorGenCustInfoPDF | J100: 簽署投顧約_確認客戶資料表 | K100: Y | M100: 1 | N100: 45009 | O100: Callee | P100: 程式無異動，故不需另行開發 | Q100: {"RqHeader":{"MsgID":"","ChlName":"MWEB","ChlEJNo":"MMA-AI_GenCustInfoPDF-0000739990446","ChlSendTime":"2020-09-29T18:37:57","ChlIP":"10.11.32.145","Language":"TC","Verion":null,"CustomerID":"27416733","CustomerIDCheckcode":"0"},"SvcRq":{"Rq":{"VerifyNo":"1354"}}} | R100: {"RsHeader":{"RsStat":{"RsStatCode":"SUCCESS","Desc":"產生客戶簽署投顧契約資料表成功"},"ChlEJNo":"MMA-AI_G_ConPdf-0000739377890","RqTime":"2019-12-20T16:53:04","RsTime":"2020/09/17 11:48:35"},"SvcRs":{"CustInfoPDF":"JVBERi0xLjQKJeLjz9MKMiAwIG9iago8PC9MZW5ndGggNDkvRmlsdGVyL0ZsYXRlRGVjb2RlPj5zdHJlYW0KeJwr5HIK4TI2U7AwMFMISeFyDeEK5CpUMFQwAEIImZyroB+RZqjgkq8QyAUA6qIJ8gplbmRzdHJlYW0KZW5kb2JqCjQgMCBvYmoKPDwvVHlwZS9QYWdlL01lZGlhQm94WzAgMCA1OTUgODQyXS9SZXNvdXJjZXM8PC9YT2JqZWN0PDwvWGYxIDEgMCBSPj4+Pi9Db250ZW50cyAyIDAgUi9QYXJlbnQgMyAwIFI+PgplbmRvYmoKNiAwIG9iago8PC9MZW5ndGggNDkvRmlsdGVyL0ZsYXRlRGVjb2RlPj5zdHJlYW0KeJwr5HIK4TI2UG8Ofj8qSaB1/rwfLnIebh37f/9d+rbHnGmIdfy7+vJpiHX1+wX3d+Pz7PRPN0fs3XPvbf629fZ9nXyeILTbPfX2Jf75XXaeZ78KgT8jwlT4M8OfKe/C6dLH++1z728/7VnzufSfbp/DrZft31PKZ1eTrfH2wf7MF+efbaz4PXIrv3++2699o/V9g/L7J/rvjznv3VM1ueRvsc7PLgc86UdS6XB+dTZp9Gu/YCKwtzzMPzxuedbJ9JZj90jpUHu36daJ9U++9Ptr//tN2/yX+xrxPNuX27/sH2vWS7bvy8Z79O/YufH3OTJ8fua8pN9v5/5w61/vWfe+T/+b3/6LXrn/+nj3yfxlndMPumztvXdvN3fNrkvbQEI5955ty43hn2nCfatYt86+P/b7t2A1dldQdw/Fw1IiIzM7VURFQitWZqZOAMEc2pmZkRvuQImbLmFM3UzJkzM7OXOXJFb0bljBmzKzlH5lwz51g554wZmXOuscacLUeuXHO6/8Pzd/fKvVzuhXvhYj8/n+/nPM9zz3Ne/+ece/2g412hefe0stfYMr3PVdk6h49onkqNozK1Vcuz4sMqv0DjyKrHir1Nem+lhdre07Ep+0z1ms/X8g/Z69KKger9o5Wm47XeA1pPjl5b7czUsbHm/oiOT5q3x22xKCa6PbSwMDAwMCBuIAowMDAwMjE1NTgwIDAwMDAwIG4gCjAwMDAyMTU2MjYgMDAwMDAgbiAKdHJhaWxlcgo8PC9TaXplIDI4L1Jvb3QgMjYgMCBSL0luZm8gMjcgMCBSL0lEIFs8ZjA3OWM0ZTQ4YTNiMDYwNmZkYzNjYTY3MGVhODE0ZWU+PGYwNzljNGU0OGEzYjA2MDZmZGMzY2E2NzBlYTgxNGVlPl0+PgolaVRleHQtNS41LjUKc3RhcnR4cmVmCjIxNTc4OQolJUVPRgoL"}}
B101: 096 | C101: 商品應用部 | D101: 財富信託科 | E101: TWTXN00073 | F101: 智能理財系統 | G101: ibrain | H101: Inv042_A | I101: 確認簽署投顧委任契約 AdvisorSignContract | J101: 確認簽署投顧委任契約 | K101: Y | M101: 1 | N101: 45009 | O101: Callee | P101: 程式無異動，故不需另行開發 | Q101: {"RqHeader":{"MsgID":"","ChlName":"EBANK","ChlEJNo":"MMA-AI_G_ConPdf-0000739377890","ChlSendTime":"2019-12-20T16:53:04","ChlIP":"10.11.161.121","Language":"TC","Verion":null,"CustomerID":"N151412163","CustomerIDCheckcode":"0"},"SvcRq":{"Rq":{"VerifyNo":"3","ReturnURL":"https://mma.sinopac.com/mma/mymma/myasset/mma_assets_summary.aspx"}}} | R101: {"RsHeader":{"RsStat":{"RsStatCode":"SUCCESS","Desc":"確認簽屬客戶投顧委任契約成功"},"ChlEJNo":"MMA-AI_SignContract-0002147604683","RqTime":"2021-04-19T14:56:49","RsTime":"2021/04/19 14:56:51"},"SvcRs":{"TWID_TOKEN":"26fd86eb6eb1470b97b2b401418aed191cd0a9e1","BusinessNo":"IBRAIN1","ApiVersion":"1.0","HashKeyNo":"1","VerifyNo":"ibrain_4449","IdentifyNo":"f5262c5882f4298b769e652829bb47df58369f382ee545485cf717442f674896"}}
B102: 097 | C102: 商品應用部 | D102: 財富信託科 | E102: TWTXN00073 | F102: 智能理財系統 | G102: ibrain | H102: Inv043_A | I102: 新增簽署投顧約 AdvisorSignContractFinish | J102: 新增簽署投顧約 | K102: Y | M102: 1 | N102: 45009 | O102: Callee | P102: 程式無異動，故不需另行開發 | Q102: {"RqHeader":{"MsgID":"","ChlName":"EBANK","ChlEJNo":"MMA-AI_G_ConPdf-0000739377890","ChlSendTime":"2019-12-20T16:53:04","ChlIP":"10.11.161.121","Language":"TC","Verion":null,"CustomerID":"N151412163","CustomerIDCheckcode":"0"},"SvcRq":{"Rq":{"TWID_TOKEN":"fjrfiwoef-ewjui58787"}}} | R102: {"RsHeader":{"RsStat":{"RsStatCode":"SUCCESS","Desc":"新增簽屬客戶投顧委任契約成功"},"ChlEJNo":"MMA-AI_SignContractFinish-0002147604684","RqTime":"2021-04-19T14:57:15","RsTime":"2021/04/19 14:57:27"},"SvcRs":{"HighRiskMark":"N"}}
B103: 098 | C103: 商品應用部 | D103: 財富信託科 | E103: TWTXN00073 | F103: 智能理財系統 | G103: ibrain | H103: Inv044_A | I103: 檢核客戶是否簽署投顧契約 AdvisorContractCheck | J103: 檢核客戶是否簽署投顧契約 | K103: Y | M103: 1 | N103: 45009 | O103: Callee | P103: 程式無異動，故不需另行開發 | Q103: {"RqHeader":{"MsgID":"","ChlName":"EBANK","ChlEJNo":"MMA-AI_ChkDif-0000739377890","ChlSendTime":"2019-12-20T16:53:04","ChlIP":"10.11.161.121","Language":"TC","Verion":null,"CustomerID":"N151412163","CustomerIDCheckcode":"0"},"SvcRq":{"Rq":{}}} | R103: {"RsHeader":{"RsStat":{"RsStatCode":"SUCCESS","Desc":"查詢客戶是否簽署投顧契約成功"},"ChlEJNo":"MMA-ChkAdvContract-0000095798724","RqTime":"2019/04/2516:25:10","RsTime":"2019/04/2516:27:30"},"SvcRs":{{"SignStatus":"0","CONTRACT_NO":"202000000001","TWID_TOKEN":"fjrfiwoef-ewjui58787","RiskMark":"Y"}}
B104: 099 | C104: 商品應用部 | D104: 財富信託科 | E104: TWTXN00073 | F104: 智能理財系統 | G104: ibrain | H104: Inv045_A | I104: 取得投組風險屬性轉換清單 RiskSwitchGet | J104: 取得投組風險屬性轉換清單 | K104: Y | M104: 1 | N104: 44993 | O104: Callee | Q104: {"RqHeader":{"MsgID":"","ChlName":"EBANK","ChlEJNo":"MMA-AI_RiskSwitchGet-0000739377890","ChlSendTime":"2019-12-20T16:53:04","ChlIP":"10.11.161.121","Language":"TC","Verion":null,"CustomerID":"N151412163","CustomerIDCheckcode":"0"},"SvcRq":{"Rq":{}}} | R104: {"RsHeader":{"RsStat":{"RsStatCode":"SUCCESS","Desc":"查詢投資風險屬性-確認清單成功"},"ChlEJNo":"MMA-RiskSwitchGet-0000095798724","RqTime":"2019/04/2516:25:10","RsTime":"2019/04/2516:27:30"},"SvcRs":{RsCollect": {"RiskLevelMark":"親愛的客戶您好，\n本商品風險等級為RR4成長型，依照您目前的投資屬性等級，ibrAin將無法為您提供投資顧問服務。\n如有任何問題，請撥打客服專線(02)2505-9999"},"RsCollect1":[{"PFName":"退休規劃","AISeqNo":"000001","RiskLevel":"5","PortfolioLevel":"6","PortfolioLevel4":"4","PortfolioLevel5":"5"},{"PFName":"退休規劃","AISeqNo":"000002","RiskLevel":"4","PortfolioLevel":"5","PortfolioLevel4":"4""PortfolioLevel5":""}],"RsCollect2":[{"PFName":"退休規劃","AISeqNo":"000001","PortfolioLevel":"","PortfolioLevelAfter":"5","PortfolioLevelBefore":"4","TradeDate":"2020/09/1516:20:20"}]}}
B105: 100 | C105: 商品應用部 | D105: 財富信託科 | E105: TWTXN00073 | F105: 智能理財系統 | G105: ibrain | H105: Inv046_A | I105: 確認投組風險屬性轉換 RiskSwitchConfirm | J105: 確認投組風險屬性轉換 | K105: Y | M105: 1 | N105: 44993 | O105: Callee | Q105: {"RqHeader":{"ChlName":"EBANK","ChlEJNo":"MMA-RiskSwitchConfirm-0000095798724","ChlSendTime":"2019/04/2516:25:10","ChlIP":"127.0.0.1","Language":"TC","Version":"1.0","CustomerID":"A158012017","CustomerIDCheckcode":"0"},"SvcRq":{"Rq":{"AISeqNo":"000143","PortfolioLevelAfter":"4"}}} | R105: {"RsHeader":{"RsStat":{"RsStatCode":"SUCCESS","Desc":"確認投資風險屬性成功"},"ChlEJNo":"MMA-RiskSwitchConfirm-0000095798724","RqTime":"2019/04/2516:25:10","RsTime":"2019/04/2516:27:30"},"SvcRs":{"AISeqNo":"000035","Over70":"N", "Special":"N", "HasRspDollar":"N", "RR6Check":"N", "ProductPI":"N", "CustomerRiskLevel":"N", "ProductYear":"N", "InvestYear":"N""StockAName":"VTI先鋒整體股市ETF","StockBName":"VEA先鋒富時已開發股市ETF","StockCName":"","BondLName":"SPTL投資組合長期美國公債ETF","BondMName":"SCHR美國中期公債ETF","BondSName":"SCHO短期美國公債ETF","PortfoiolLevelBefore":"6","PortfoiolLevelAfter":"4","StockARatioBefore":"10.00","StockARatioAfter":"8.00","StockBRatioBefore":"5.00","StockBRatioAfter":"4.00","StockCRatioBefore":"0.00","StockCRatioAfter":"0.00","BondLRatioBefore":"20.00","BondLRatioAfter":"22.00","BondMRatioBefore":"20.00","BondMRatioAfter":"22.00","BondSRatioBefore":"45.00","BondSRatioAfter":"46.00","StockAName":"先鋒整體股市ETF","StockBName":"先鋒富時已開發股市ETF","StockCName":"","BondLName":"投資組合長期美國公債ETF","BondMName":"美國中期公債ETF","BondSName":"短期美國公債ETF","PortfoiolLevelBefore":"6","PortfoiolLevelAfter":"5","Currency":"TWD","StockARatioBefore":"10.00","StockARatioAfter":"8.00","StockBRatioBefore":"5.00","StockBRatioAfter":"4.00","StockCRatioBefore":"0.00","StockCRatioAfter":"0.00","BondLRatioBefore":"20.00","BondLRatioAfter":"22.00","BondMRatioBefore":"20.00","BondMRatioAfter":"22.00","BondSRatioBefore":"45.00","BondSRatioAfter":"46.00","StockAPV":"15000","StockBPV":"16000","StockCPV":"0","BondLPV":"20000","BondMPV":"21000","BondSPV":"25000","TotalPV":"100000","TotalStockRatio":"100","TotalBondRatio":"100","TotalUnStockDollar":"0","PFNanme":"XXXXXXX","Currency":"TWD","CusType":"5","StockAID":"VTI","StockBID":"VEA","StockCID":"","BondLID":"SPTL","BondMID":"SCHR","BondSID":"SCHO"}}
B106: 101 | C106: 商品應用部 | D106: 財富信託科 | E106: TWTXN00073 | F106: 智能理財系統 | G106: ibrain | H106: Inv047_A | I106: 新增投組風險屬性轉換 RiskSwitchCreate | J106: 新增投組風險屬性轉換 | K106: Y | M106: 1 | N106: 45000 | O106: Callee | Q106: {"RqHeader":{"ChlName":"EBANK","ChlEJNo":"MMA-RiskSwitchCreate-0000095798724","ChlSendTime":"2019/04/2516:25:10","ChlIP":"127.0.0.1","Language":"TC","Version":"1.0","CustomerID":"A158012017","CustomerIDCheckcode":"0"},"SvcRq":{"Rq":{"AISeqNo":"000143","PortfolioLevelAfter":"4","AgreeMark":"1","StockRatioAfter":"28.00","BondRatioAfter":"72.00","StockARatioAfter":"8.00","StockBRatioAfter":"4.00","StockCRatioAfter":"0.00","BondLRatioAfter":"22.00","BondMRatioAfter":"22.00","BondSRatioAfter":"46.00"}}} | R106: {"RsHeader":{"RsStat":{"RsStatCode":"SUCCESS","Desc":"投資風險屬性交易結果成功"},"ChlEJNo":"MMA-RiskSwitchCreate-0000095798724","RqTime":"2019/04/2516:25:10","RsTime":"2019/04/2516:27:30"},"SvcRs":{"StockAName":"先鋒整體股市ETF","StockBName":"先鋒富時已開發股市ETF","StockCName":"","BondLName":"投資組合長期美國公債ETF","BondMName":"美國中期公債ETF","BondSName":"短期美國公債ETF","PortfoiolLevelBefore":"6","PortfoiolLevelAfter":"4","Currency":"TWD","StockRatioBefore":"80.00","StockRatioAfter":"70.00","BondRatioBefore":"20.00","BondRatioAfter":"30.00","StockARatioBefore":"10.00","StockARatioAfter":"8.00","StockBRatioBefore":"5.00","StockBRatioAfter":"4.00","StockCRatioBefore":"0.00","StockCRatioAfter":"0.00","BondLRatioBefore":"20.00","BondLRatioAfter":"22.00","BondMRatioBefore":"20.00","BondMRatioAfter":"22.00","BondSRatioBefore":"45.00","BondSRatioAfter":"46.00","StockAPV":"15000","StockBPV":"16000","StockCPV":"0","BondLPV":"20000","BondMPV":"21000","BondSPV":"25000","TotalPV":"100000","TotalStockRatio":"100","TotalBondRatio":"100","AgreeMark":"1","ToTalUnStockDollar":"1","PFNanme":"XXXXXXX","CusType":"5","StockAID":"VTI","StockBID":"VEA","StockCID":"","BondLID":"SPTL","BondMID":"SCHR","BondSID":"SCHO"}}
B107: 102 | C107: 商品應用部 | D107: 財富信託科 | E107: TWTXN00073 | F107: 智能理財系統 | G107: ibrain | H107: Inv048_A | I107: 撲滿Projection 表 funGetProjection/forpig | J107: 撲滿Projection 表 | K107: Y | M107: 1 | N107: 45009 | O107: Callee | P107: 程式無異動，故不需另行開發 | Q107: {“RqHeader”:{“MsgID”:””,“ChlName”:”MAPP”,“ChlEJNo”:”MMA-AI_GPP-0000095798724”,“ChlSendTime”:”2016-09-29T16:25:20”,“ChlIP”:”127.0.0.1”,“Language”:”TC”,“Version”:”1.0”,“CustomerID”:”A123456789”,“CustomerIDCheckcode”:”1”},“SvcRq”:{“Rq”:{“InitialDollar”:”500000”,“RSPDollar”:”5000”,“TargetDollar”:”2000000”,“InvestYear”:”5”}}} | R107: {“RsHeader”:{“RsStat”:{“RsStatCode”:“SUCCESS”,“Desc”:“Projection回傳，”},“ChlEJNo”:“MMA-AI_GPP-0000095798724”,“RqTime”:“2016-09-29T16:25:20”,“RsTime”:“2016-09-29T16:35:20”},“SvcRs”:{"RsCollect1":{“Situation1”:[{“years”:“0”,“FixedMoney”:“4500000”},{“years”:“1”,“FixedMoney”:“4600000”},{“years”:“2”,“FixedMoney”:“4700000”},{“years”:“3”,“FixedMoney”:“4800000”},{“years”:“4”,“FixedMoney”:“4900000”}],“Situation2”:[{“years”:“0”,“LivingMoney”:“4500000”},{“years”:“1”,“LivingMoney”:“4600000”},{“years”:“2”,“LivingMoney”:“4700000”},{“years”:“3”,“LivingMoney”:“4800000”},{“years”:“4”,“LivingMoney”:“4900000”}],“Situation3”:[{“years”:“0”,“ibrAinMoney”:“4500000”},{“years”:“1”,“ibrAinMoney”:“4600000”},{“years”:“2”,“ibrAinMoney”:“4700000”},{“years”:“3”,“ibrAinMoney”:“4800000”},{“years”:“4”,“ibrAinMoney”:“4900000”]}}}
B108: 103 | C108: 商品應用部 | D108: 財富信託科 | E108: TWTXN00073 | F108: 智能理財系統 | G108: ibrain | H108: Inv049_A | I108: GetContractPdf 下載客戶簽屬投顧委任契約 | J108: 下載客戶簽屬投顧委任契約PDFDownloadContractPDF | K108: Y | M108: 1 | N108: 45009 | O108: Callee | P108: 程式無異動，故不需另行開發 | Q108: {"RqHeader":{"MsgID":"","ChlName":"EBANK","ChlEJNo":"MMA-AI_DownloadContract-0002495710982","ChlSendTime":"2022-08-29T16:31:48","ChlIP":"10.11.190.10","Language":"TC","Verion":null,"CustomerID":"F257067453","CustomerIDCheckcode":"0"},"SvcRq":{"Rq":{"TWID_TOKEN":"e243ad0d1fee4f7ea27c42c234aae6878a13c927"}}} | R108: bianary data
B109: 104 | C109: 商品應用部 | D109: 財富信託科 | E109: TWTXN00059 | F109: 財富交易網銀系統 | G109: iFund | H109: Inv001_F | I109: funGetAllCertificate | J109: 基金庫存總覽 | K109: Y | M109: 1 | N109: 45000 | O109: Callee | Q109: <?xmlversion="1.0"encoding="UTF-8"?><IFUND><RqHeader><MsgID>funGetAllCertificate</MsgID><ChlName>EBANK</ChlName><ChlEJNo>MMA-FUND_gCert-0000130692803</ChlEJNo><ChlSendTime>2012-08-29T11:10:21</ChlSendTime><CustomerID>H221544507</CustomerID><CustomerIDCheckcode>0</CustomerIDCheckcode><ChlIP>127.0.0.1</ChlIP><Language></Language></RqHeader><SvcRq><Rq><CustomerID>H221544507</CustomerID><CustomerIDCheckcode>0</CustomerIDCheckcode><SortType>1</SortType></Rq></SvcRq></IFUND> | R109: <?xmlversion="1.0"encoding="UTF-8"?><IFUND><RsHeader><RsStat><RsStatCode>SUCCESS</RsStatCode><Desc>查詢個人所有憑證資料成功</Desc></RsStat><ChlEJNo>MMA-FUND_gCert-0000130692803</ChlEJNo><RqTime>2012-08-29T14:32:34</RqTime><RsTime>2012-08-29T14:32:40</RsTime><CustomerID>H221544507</CustomerID><CustomerIDCheckcode>0</CustomerIDCheckcode></RsHeader><SvcRs><Rs><certificateBranchNo>024</certificateBranchNo><certificateFundID>78S</certificateFundID><certificateSeqNo>02000060</certificateSeqNo><enteredBankNo>807</enteredBankNo><enteredAccountNo>02400400109682</enteredAccountNo><deductionBankNo></deductionBankNo><deductionAccountNo></deductionAccountNo><trustBeginningDate>2009/07/26</trustBeginningDate><trustEndDate>2024/07/26</trustEndDate><transactionDate>2020/02/06</transactionDate><totalUnit>82.72000</totalUnit><avgNav>14.97000</avgNav><avgNavCur>USD</avgNavCur><redemNav>20.4</redemNav><redemNavCur>USD</redemNavCur><buyDealRate>29.98</buyDealRate><buyDealRateCur>USD</buyDealRateCur><totalDollar>77038.00000</totalDollar><totalDollarCur>TWD</totalDollarCur><assetValue>50591</assetValue><assetValueCur>TWD</assetValueCur><revenue>-26447</revenue><revenueCur>TWD</revenueCur><ratio>-34.330</ratio><gainPoint>20</gainPoint><lossPoint>20</lossPoint><emailMark>1</emailMark><stockMark>1</stockMark><wthdrwFg>0</wthdrwFg><deductionSourceNo>0</deductionSourceNo><deductionDay></deductionDay><deductionDollar>0</deductionDollar><suspenseBeginMonth></suspenseBeginMonth><suspenseEndMonth></suspenseEndMonth><insurePromotionNo>00</insurePromotionNo><insurePromotionName>一般信託</insurePromotionName><insureCompanyID></insureCompanyID><insureCompanyName></insureCompanyName><insurantID></insurantID><insurantIDCheckCode></insurantIDCheckCode><insurantName></insurantName><IBTMark>0</IBTMark><gainAutoMark>0</gainAutoMark><lossAutoMark>0</lossAutoMark><autoVarMark>0</autoVarMark><upperRatio>0</upperRatio><downRatio>0</downRatio><upperDollar>0</upperDollar><downDollar>0</downDollar><TotalCashDist>0</TotalCashDist><TotalCashDistCur>TWD</TotalCashDistCur><CashDistRatio>-34.330</CashDistRatio><ChAbbr>(百元基金)貝萊德歐洲特別時機基金HEDGEDA2(美元)</ChAbbr><Loan_Mark>-</Loan_Mark></Rs><Rs><certificateBranchNo></certificateBranchNo><certificateFundID>770</certificateFundID><certificateSeqNo></certificateSeqNo><enteredBankNo></enteredBankNo><enteredAccountNo></enteredAccountNo><deductionBankNo></deductionBankNo><deductionAccountNo></deductionAccountNo><trustBeginningDate></trustBeginningDate><trustEndDate></trustEndDate><transactionDate></transactionDate><totalUnit></totalUnit><avgNav></avgNav><avgNavCur></avgNavCur><redemNav>27.42</redemNav><redemNavCur>USD</redemNavCur><buyDealRate></buyDealRate><buyDealRateCur></buyDealRateCur><totalDollar>660000</totalDollar><totalDollarCur>TWD</totalDollarCur><assetValue>16349</assetValue><assetValueCur>TWD</assetValueCur><revenue>TWD</revenue><revenueCur>TWD</revenueCur><ratio>-97.52</ratio><gainPoint></gainPoint><lossPoint></lossPoint><emailMark></emailMark><stockMark></stockMark><wthdrwFg></wthdrwFg><deductionSourceNo></deductionSourceNo><deductionDay></deductionDay><deductionDollar></deductionDollar><suspenseBeginMonth></suspenseBeginMonth><suspenseEndMonth></suspenseEndMonth><insurePromotionNo></insurePromotionNo><insurePromotionName></insurePromotionName><insureCompanyID></insureCompanyID><insureCompanyName></insureCompanyName><insurantID></insurantID><insurantIDCheckCode></insurantIDCheckCode><insurantName></insurantName><IBTMark></IBTMark><gainAutoMark></gainAutoMark><lossAutoMark></lossAutoMark><autoVarMark></autoVarMark><upperRatio></upperRatio><downRatio></downRatio><upperDollar></upperDollar><downDollar></downDollar><TotalCashDist>0</TotalCashDist><TotalCashDistCur></TotalCashDistCur><CashDistRatio>-97.52</CashDistRatio><Loan_Mark>已質借</Loan_Mark></Rs></SvcRs></IFUND>
B110: 105 | C110: 商品應用部 | D110: 財富信託科 | E110: TWTXN00059 | F110: 財富交易網銀系統 | G110: iFund | H110: Inv002_F | I110: funGetExcludeDRList | J110: 基金除權息總覽 | K110: Y | M110: 1 | N110: 45009 | O110: Callee | P110: 程式無異動，故不需另行開發 | Q110: <?xmlversion="1.0"encoding="UTF-8"?><IFUND><RqHeader><MsgID>funGetExcludeDRList</MsgID><ChlName>EBANK</ChlName><ChlEJNo>MMA-FUND_gDR-0000095798724</ChlEJNo><ChlSendTime>2012-08-29T11:10:21</ChlSendTime><CustomerID>E120120535</CustomerID><CustomerIDCheckcode>0</CustomerIDCheckcode><ChlIP>127.0.0.1</ChlIP> <Language></Language></RqHeader><SvcRq><Rq><CustomerID>E120120535</CustomerID><CustomerIDCheckcode>0</CustomerIDCheckcode><StopMark>0</StopMark></Rq></SvcRq></IFUND> | R110: <?xmlversion="1.0"encoding="utf-8"?><IFUND><RsHeader> <RsStat> <RsStatCode>SUCCESS</RsStatCode><Desc>查詢基金除權息總覽成功</Desc> </RsStat><ChlEJNo>MMA-FUND_gDR-0000095798724</ChlEJNo><RqTime>2012-08-29T11:10:21</RqTime> <RsTime>2012-08-29T11:10:21</RsTime><CustomerID>E120120535</CustomerID><CustomerIDCheckcode>0</CustomerIDCheckcode></RsHeader><SvcRs><Rs><certificateBranchNo>032</certificateBranchNo><certificateFundID>56E</certificateFundID><certificateSeqNo>40800451</certificateSeqNo><trustBranchNo>032</trustBranchNo><trustProductNo>020</trustProductNo><trustSeqNo>00000571</trustSeqNo><StopMark>0</StopMark><OffShoreType>0</OffShoreType><DividendTDollar>612.61</DividendTDollar><DividendTDollar_Cur>USD</DividendTDollar_Cur><EnteredAccountTDollar>612.61</EnteredAccountTDollar><EnteredAccountTDollar_Cur>USD</EnteredAccountTDollar_Cur><TotalUnit>807</TotalUnit><ProductOrder>1</ProductOrder><FundChAbbr>聯博全球高收益債?</FundChAbbr></Rs><SvcRs></IFUND>
B111: 106 | C111: 商品應用部 | D111: 財富信託科 | E111: TWTXN00059 | F111: 財富交易網銀系統 | G111: iFund | H111: Inv003_F | I111: funGetExcludeDividendList | J111: 基金除息明細 | K111: Y | M111: 1 | N111: 45009 | O111: Callee | P111: 程式無異動，故不需另行開發 | Q111: <?xmlversion="1.0"encoding="UTF-8"?><IFUND><RqHeader><MsgID>funGetExcludeDividendList</MsgID><ChlName>EBANK</ChlName><ChlEJNo>MMA-FUND_gXD-0000095798725</ChlEJNo><ChlSendTime>2012-09-13T11:23:32</ChlSendTime><CustomerID>E120120535</CustomerID><CustomerIDCheckcode>0</CustomerIDCheckcode><ChlIP>10.11.22.53</ChlIP><Language></Language></RqHeader><SvcRq><Rq><certificateBranchNo>032</certificateBranchNo><certificateFundID>56E</certificateFundID><certificateSeqNo>40800451</certificateSeqNo><ProductOrder>1</ProductOrder></Rq></SvcRq></IFUND> | R111: <?xmlversion="1.0"encoding="utf-8"?><IFUND><RsHeader><RsStat><RsStatCode>SUCCESS</RsStatCode><Desc>查詢基金除息明細成功</Desc></RsStat><ChlEJNo>MMA-FUND_gXD-0000095798726</ChlEJNo><RqTime>2012-09-13T11:23:32</RqTime><RsTime>2012-09-13T11:23:32</RsTime><CustomerID>E120120535</CustomerID><CustomerIDCheckcode>0</CustomerIDCheckcode></RsHeader><SvcRs><Rs><certificateBranchNo>032</certificateBranchNo><certificateFundID>56E</certificateFundID><certificateSeqNo>40800451</certificateSeqNo><DividendDate>2009/01/13</DividendDate><EnterDate>2009/01/21</EnterDate><DividendUnit>104.362</DividendUnit><Ratio>1.27000</Ratio><DividendDollar>132.54</DividendDollar><DividendDollar_Cur>EUR</DividendDollar_Cur><DividendAmount>132.54</DividendAmount><DividendAmount_Cur>EUR</DividendAmount_Cur><DealExRate>1.00000</DealExRate><DealExRate_Cur>EUR:EUR</DealExRate_Cur><TrustTax>0</TrustTax><EnteredAccountDollar>132.54</EnteredAccountDollar><EnteredAccountDollar_Cur>EUR</EnteredAccountDollar_Cur><FundChAbbr>法巴L1俄羅斯股票(歐元年配息)</FundChAbbr></Rs><SvcRs></IFUND>
B112: 107 | C112: 商品應用部 | D112: 財富信託科 | E112: TWTXN00059 | F112: 財富交易網銀系統 | G112: iFund | H112: Inv004_F | I112: funGetExcludeRightList | J112: 基金除權明細 | K112: Y | M112: 1 | N112: 45009 | O112: Callee | P112: 程式無異動，故不需另行開發 | Q112: <?xmlversion="1.0"encoding="UTF-8"?><IFUND><RqHeader><MsgID>funGetExcludeRightList</MsgID><ChlName>EBANK</ChlName><ChlEJNo>MMA-FUND_gXR-0000095798726</ChlEJNo><ChlSendTime>2012-09-13T11:23:32</ChlSendTime><CustomerID>E120120535</CustomerID><CustomerIDCheckcode>0</CustomerIDCheckcode><ChlIP>10.11.22.53</ChlIP><Language></Language></RqHeader><SvcRq><Rq><certificateBranchNo>032</certificateBranchNo><certificateFundID>X01</certificateFundID><certificateSeqNo>40700701</certificateSeqNo><ProductOrder>3</ProductOrder></Rq></SvcRq></IFUND> | R112: <?xmlversion="1.0"encoding="utf-8"?><IFUND><RsHeader><RsStat><RsStatCode>SUCCESS</RsStatCode><Desc>查詢基金除權明細成功</Desc></RsStat><ChlEJNo>MMA-FUND_gXR-0000095798726</ChlEJNo><RqTime>2012-09-13T11:23:32</RqTime><RsTime>2012-09-13T11:23:32</RsTime><CustomerID>E120120535</CustomerID><CustomerIDCheckcode>0</CustomerIDCheckcode></RsHeader><SvcRs><Rs><certificateBranchNo>032</certificateBranchNo><certificateFundID>X01</certificateFundID><certificateSeqNo>40700701</certificateSeqNo><DividendDate>2007/11/30</DividendDate><DividendUnit>375.76</DividendUnit><DistributeDate>2007/12/03</DistributeDate><Ratio>0.0896314772</Ratio><Distunit>33.68000</Distunit><FundChAbbr>富蘭克林黃金(年配權)</FundChAbbr></Rs><SvcRs></IFUND>
B113: 108 | C113: 商品應用部 | D113: 財富信託科 | E113: TWTXN00059 | F113: 財富交易網銀系統 | G113: iFund | H113: Inv005_F | I113: funGetSecurityInvDataList | J113: 查詢海外有價證券歸戶資料 | K113: N | M113: 1 | N113: 45009 | O113: Callee | P113: 程式無異動，故不需另行開發 | Q113: <?xmlversion="1.0"encoding="UTF-8"?><IFUND><RqHeader><MsgID>funGetSecurityInvDataList</MsgID><ChlName>EBANK</ChlName><ChlEJNo>MMA-FUND_gSecInv-0000130692803</ChlEJNo><ChlSendTime>2012-09-13T11:23:32</ChlSendTime><CustomerID>A100372057</CustomerID><CustomerIDCheckcode>0</CustomerIDCheckcode><ChlIP>127.0.0.1</ChlIP><Language></Language></RqHeader><SvcRq><Rq><CustomerID>A100372057</CustomerID><CustomerIDCheckcode>0</CustomerIDCheckcode><Currency>AUD</Currency></Rq></SvcRq></IFUND> | R113: <?xmlversion="1.0"encoding="utf-8"?><IFUND><RsHeader><RsStat><RsStatCode>SUCCESS</RsStatCode><Desc>查詢海外有價證券庫存成功</Desc></RsStat><ChlEJNo>MMA-FUND_gSecInv-0000130692803</ChlEJNo><RqTime>2016-09-13T11:23:32</RqTime><RsTime>2016-09-13T11:23:32</RsTime><CustomerID>A100372057</CustomerID><CustomerIDCheckcode>0</CustomerIDCheckcode></RsHeader><SvcRs><Rs><tradeIDMark>1</tradeIDMark><fundName>德意志銀行金融債券(IX)(國際版債券)</fundName><totalUnit>500000</totalUnit><exchangeCurrency>USD</exchangeCurrency><nav>102.12</nav><navDate>2017/1/1</navDate><investment>-900</investment><investmentRate>-0.18</investmentRate><trustDollar>USD511,500.00</trustDollar><assetDollar>USD510,600.00</assetDollar><trustDollarNoCur>511,500.00</trustDollarNoCur><assetDollarNoCur>510,600.00</assetDollarNoCur><certificateBranchNo>001</certificateBranchNo><certificateFundId>B01</certificateFundId><certificateSeqNo>B0300001</certificateSeqNo><faceValue>USD500,000</faceValue><buyDate>2016/1/1</buyDate><actualSubPrice>USD102.3</actualSubPrice><refBidPrice>USD102.12</refBidPrice><preInterest>USD123.15</preInterest><refExchangeRate>1</refExchangeRate><investmentWithCur>USD-900.00</investmentWithCur><refInterestReceivable>USD50.00</refInterestReceivable><totalInterstAmt>USD235.00</totalInterstAmt><totalInterestAmtNoCur>235.00</totalInterestAmtNoCur><dividendROI>-0.45%</dividendROI><actualYTM>2.13%</actualYTM><trustBeginDate>2015/3/1</trustBeginDate><maturityDate>2017/3/1</maturityDate><Loan_Mark>已質借</Loan_Mark><Mortgage_Date>2019/3/1</Mortgage_Date></Rs></SvcRs></IFUND>
B114: 109 | C114: 商品應用部 | D114: 財富信託科 | E114: TWTXN00059 | F114: 財富交易網銀系統 | G114: iFund | H114: Inv006_F | I114: funGetSecurityTxDataList | J114: 查詢海外有價證券交易資料 | K114: Y | M114: 1 | N114: 45009 | O114: Callee | P114: 程式無異動，故不需另行開發 | Q114: <?xmlversion="1.0"encoding="UTF-8"?><IFUND><RqHeader><MsgID>funGetSecurityTxDataList</MsgID><ChlName>EBANK</ChlName><ChlEJNo>MMA-FUND_gSecTx-0000130692803</ChlEJNo><ChlSendTime>2013-06-27T11:10:21</ChlSendTime><CustomerID>Q221182067</CustomerID><CustomerIDCheckcode>0</CustomerIDCheckcode><ChlIP>127.0.0.1</ChlIP> <Language></Language></RqHeader><SvcRq><Rq><CustomerID>Q221182067</CustomerID><CustomerIDCheckcode>0</CustomerIDCheckcode></Rq></SvcRq></IFUND> | R114: <?xmlversion="1.0"encoding="UTF-8"?><IFUND><RsHeader><RsStat><RsStatCode>SUCCESS</RsStatCode><Desc>查詢海外有價證券交易成功</Desc></RsStat><ChlEJNo>MMA-FUND_gSecTx-0000130692803</ChlEJNo><RqTime>2013-06-27T10:01:08</RqTime><RsTime>2013-06-27T10:01:50</RsTime><CustomerID>Q221182067</CustomerID><CustomerIDCheckcode>0</CustomerIDCheckcode></RsHeader><SvcRs><Rs><distDate>2013/06/21</distDate><transTypeMark>1</transTypeMark><tradeIDMark>1</tradeIDMark><fundName>南非開發銀行金融債券</fundName><totalUnit>1900000.00000</totalUnit><price>30.25000</price><exchangeCurrency>ZAR</exchangeCurrency><fee>4310.63</fee><interest>0.00000</interest><totalAmount>579060.63</totalAmount><manageFee>0.00</manageFee><stockTax>0</stockTax><ActualFeeRate>4.96</ActualFeeRate><AnnualizedFeeRate>0.33</AnnualizedFeeRate></Rs></SvcRs></IFUND>
B115: 110 | C115: 商品應用部 | D115: 財富信託科 | E115: TWTXN00059 | F115: 財富交易網銀系統 | G115: iFund | H115: Inv007_F | I115: funGetTrustAccount | J115: 查詢個人所有信託帳戶資料 | K115: Y | M115: 1 | N115: 45009 | O115: Callee | P115: 程式無異動，故不需另行開發 | Q115: <?xmlversion="1.0"encoding="UTF-8"?><IFUND><RqHeader><MsgID>funGetTrustAccount</MsgID><ChlName>EBANK</ChlName><ChlEJNo>MMA-FUND_gTrustAcct-0000130692803</ChlEJNo><ChlSendTime>2012-09-13T11:23:32</ChlSendTime><CustomerID>A100372057</CustomerID><CustomerIDCheckcode>0</CustomerIDCheckcode><ChlIP>127.0.0.1</ChlIP></RqHeader><SvcRq><Rq><CustomerID>A100372057</CustomerID><CustomerIDCheckcode>0</CustomerIDCheckcode></Rq></SvcRq></IFUND> | R115: <?xmlversion="1.0"encoding="utf-8"?><IFUND><RsHeader><RsStat><RsStatCode>SUCCESS</RsStatCode><Desc>查詢個人所有信託帳戶成功</Desc></RsStat><ChlEJNo>MMA-FUND_gTrustAcct-0000130692803</ChlEJNo><RqTime>2012-08-29T11:10:21</RqTime><RsTime>2012-08-29T11:10:21</RsTime><CustomerID>A100372057</CustomerID><CustomerIDCheckcode>0</CustomerIDCheckcode></RsHeader><SvcRs><Rs><trustBranchNo>005</trustBranchNo><trustProductNo>020</trustProductNo><trustSeqNo>00003933</trustSeqNo><enteredBankNo>807</enteredBankNo><enteredAccountNo>00500491083446</enteredAccountNo><cardStatusMark>0</cardStatusMark><trustAuthenticateMark>0</trustAuthenticateMark><internetVarMark>0</internetVarMark><insureMark>0</insureMark></Rs><SvcRs></IFUND>
B116: 111 | C116: 商品應用部 | D116: 財富信託科 | E116: TWTXN00059 | F116: 財富交易網銀系統 | G116: iFund | H116: Inv008_F | I116: funGetDeductionHistory | J116: 查詢定時定額扣帳明細資料 | K116: Y | M116: 1 | N116: 45009 | O116: Callee | P116: 程式無異動，故不需另行開發 | Q116: <?xmlversion="1.0"encoding="UTF-8"?><IFUND><RqHeader><MsgID>funGetDeductionHistory</MsgID><ChlName>EBANK</ChlName><ChlEJNo>MMA-FUND_gDeduHist-0000095798725</ChlEJNo><ChlSendTime>2013-07-03T11:23:32</ChlSendTime><CustomerID>N221506332</CustomerID><CustomerIDCheckcode>0</CustomerIDCheckcode><ChlIP>10.11.22.53</ChlIP></RqHeader><SvcRq><Rq><certificateBranchNo>019</certificateBranchNo><certificateFundID>UF4</certificateFundID><certificateSeqNo>30700023</certificateSeqNo><beginningDate>2013/01/15</beginningDate><endDate>2013/03/01</endDate></Rq></SvcRq></IFUND> | R116: <?xmlversion="1.0"encoding="UTF-8"?><IFUND><RsHeader><RsStat><RsStatCode>SUCCESS</RsStatCode><Desc>查詢定時定額扣帳明細資料成功</Desc></RsStat><ChlEJNo>MMA-FUND_gDeduHist-0000095798725</ChlEJNo><RqTime>2013-07-03T17:23:54</RqTime><RsTime>2013-07-03T17:24:08</RsTime><CustomerID>N221506332</CustomerID><CustomerIDCheckcode>0</CustomerIDCheckcode></RsHeader><SvcRs><Rs><certificateBranchNo>019</certificateBranchNo><certificateFundID>UF4</certificateFundID><certificateSeqNo>30700023</certificateSeqNo><deductionDate>2013/01/29</deductionDate><unit>238.1</unit><nav>21.00000</nav><navCur>TWD</navCur><deductionBankNo>807</deductionBankNo><deductionAccountNo>01900400086003</deductionAccountNo><deductionDollar>5000.00000</deductionDollar><deductionDollarCur>TWD</deductionDollarCur><fee>29.00000</fee><feeCur>TWD</feeCur><deductionMark>Y</deductionMark><deductionDay>2013/01/29</deductionDay><dealExchangeRate>1.00000</dealExchangeRate></Rs></SvcRs></IFUND>
B117: 112 | C117: 商品應用部 | D117: 財富信託科 | E117: TWTXN00059 | F117: 財富交易網銀系統 | G117: iFund | H117: Inv009_F | I117: funGetAllStructuredNote | J117: 查詢個人所有Structured Note資料 | K117: Y | M117: 1 | N117: 45009 | O117: Callee | P117: 程式無異動，故不需另行開發 | Q117: <?xmlversion="1.0"encoding="UTF-8"?><IFUND><RqHeader><MsgID>funGetAllStructuredNote</MsgID><ChlName>EBANK</ChlName><ChlEJNo>MMA-FUND_gStructNote-0000130692803</ChlEJNo><ChlSendTime>2012-09-13T11:23:32</ChlSendTime><CustomerID>Y100984761</CustomerID><CustomerIDCheckcode>0</CustomerIDCheckcode><ChlIP>127.0.0.1</ChlIP><Language></Language></RqHeader><SvcRq><Rq><CustomerID>Y100984761</CustomerID><CustomerIDCheckcode>0</CustomerIDCheckcode></Rq></SvcRq></IFUND> | R117: <?xmlversion="1.0"encoding="utf-8"?><IFUND><RsHeader><RsStat><RsStatCode>SUCCESS</RsStatCode><Desc>查詢個人所有StructuredNote成功</Desc></RsStat><ChlEJNo>MMA-FUND_gStructNote-0000130692803</ChlEJNo><RqTime>2012-08-29T11:10:21</RqTime><RsTime>2012-08-29T11:10:21</RsTime><CustomerID>Y100984761</CustomerID><CustomerIDCheckcode>0</CustomerIDCheckcode></RsHeader><SvcRs><Rs><certificateBranchNo>005</certificateBranchNo><certificateFundID>SG3</certificateFundID><certificateSeqNo>60400261</certificateSeqNo><deductionBankNo>807</deductionBankNo><deductionAccountNo>00500800008895</deductionAccountNo><trustBeginningDate>2004/02/27</trustBeginningDate><trustEndDate>2014/03/17</trustEndDate><totalUnit>1000.00000</totalUnit><avgNav>100.00000</avgNav><avgNavCur>USD</avgNavCur><redemNav>95.98</redemNav><redemNavCur>USD</redemNavCur><buyDealRate>1</buyDealRate><buyDealRateCur>USD</buyDealRateCur><totalDollar>100000.00000</totalDollar><totalDollarCur>USD</totalDollarCur><assetValue>95980</assetValue><assetValueCur>USD</assetValueCur><revenue>-4020</revenue><revenueCur>USD</revenueCur><ratio>0</ratio><stockMark>2</stockMark><emailMark>0</emailMark><noteName>SG加速還本S2</noteName><insurePromotionNo>00</insurePromotionNo><insurePromotionName>一般信託</insurePromotionName><insureCompanyID></insureCompanyID><insureCompanyName></insureCompanyName><insurantID></insurantID><insurantIDCheckCode></insurantIDCheckCode><transactionDate>2013/01/28</transactionDate><TotalCashDist>13428.21</TotalCashDist><TotalCashDistCur>USD</TotalCashDistCur><CashDistRatio>13.43</CashDistRatio></Rs><SvcRs></IFUND>
B118: 113 | C118: 商品應用部 | D118: 財富信託科 | E118: TWTXN00059 | F118: 財富交易網銀系統 | G118: iFund | H118: Inv010_F | I118: funGetAllDeadCertificate | J118: 查詢個人已終止之基金明細資料 | K118: Y | M118: 1 | N118: 45009 | O118: Callee | P118: 程式無異動，故不需另行開發 | Q118: <?xmlversion="1.0"encoding="UTF-8"?><IFUND><RqHeader><MsgID>funGetAllDeadCertificate</MsgID><ChlName>EBANK</ChlName><ChlEJNo>MMA-FUND_gDeadCert-0000095798725</ChlEJNo><ChlSendTime>2013-07-03T11:23:32</ChlSendTime><CustomerID>G200697468</CustomerID><CustomerIDCheckcode>0</CustomerIDCheckcode><ChlIP>10.11.22.53</ChlIP><Language></Language></RqHeader><SvcRq><Rq><customerID>G200697468</customerID><customerIDCheckCode>0</customerIDCheckCode><dateFrom>2013/04/01</dateFrom><dateTo>2013/06/01</dateTo></Rq></SvcRq></IFUND> | R118: <?xmlversion="1.0"encoding="UTF-8"?><IFUND><RsHeader><RsStat><RsStatCode>SUCCESS</RsStatCode><Desc>查詢個人已終止之基金明細資料成功</Desc></RsStat><ChlEJNo>MMA-FUND_gDeadCert-0000095798725</ChlEJNo><RqTime>2013-07-04T16:12:16</RqTime><RsTime>2013-07-04T16:12:29</RsTime><CustomerID>G200697468</CustomerID><CustomerIDCheckcode>0</CustomerIDCheckcode></RsHeader><SvcRs><Rs><certificateBranchNo>119</certificateBranchNo><certificateFundID>598</certificateFundID><certificateSeqNo>41000329</certificateSeqNo><ChAbbr></ChAbbr><enteredBankNo>807</enteredBankNo><enteredAccountNo>11900800003613</enteredAccountNo><deductionBankNo></deductionBankNo><deductionAccountNo></deductionAccountNo><trustBeginningDate>2010/04/29</trustBeginningDate><trustEndDate>2013/05/03</trustEndDate><totalUnit>8260.669</totalUnit><avgNav>4.62</avgNav><avgNavCur>USD</avgNavCur><redemNav>0</redemNav><redemNavCur>USD</redemNavCur><buyDealRate>0</buyDealRate><buyDealRateCur>USD:USD</buyDealRateCur><totalDollar>0</totalDollar><totalDollarCur>USD</totalDollarCur><assetValue>0</assetValue><assetValueCur>USD</assetValueCur><revenue>0</revenue><revenueCur>USD</revenueCur><ratio>0</ratio><stockMark>N</stockMark><deleteMark>3</deleteMark><insurePromotionNo>00</insurePromotionNo><insurePromotionName>一般信託</insurePromotionName><insureCompanyID></insureCompanyID><insureCompanyName></insureCompanyName><insurantID></insurantID><insurantIDCheckCode></insurantIDCheckCode><insurantName></insurantName></Rs></SvcRs></IFUND>
B119: 114 | C119: 商品應用部 | D119: 財富信託科 | E119: TWTXN00059 | F119: 財富交易網銀系統 | G119: iFund | H119: Inv011_F | I119: funGetMethodCertificateList | J119: 查詢個人所有特殊投資法憑證資料 | K119: Y | M119: 1 | N119: 45009 | O119: Callee | P119: 程式無異動，故不需另行開發 | Q119: <?xmlversion="1.0"encoding="UTF-8"?><IFUND><RqHeader><MsgID>funGetMethodCertificateList</MsgID><ChlName>EBANK</ChlName><ChlEJNo>MMA-FUND_gMeghodCert-0000095798725</ChlEJNo><ChlSendTime>2013-07-03T11:23:32</ChlSendTime><CustomerID>A100383041</CustomerID><CustomerIDCheckcode>0</CustomerIDCheckcode><ChlIP>10.11.22.53</ChlIP></RqHeader><SvcRq><Rq><CustomerID>A100383041</CustomerID><CustomerIDCheckcode>0</CustomerIDCheckcode></Rq></SvcRq></IFUND> | R119: <?xmlversion="1.0"encoding="UTF-8"?><IFUND><RsHeader><RsStat><RsStatCode>SUCCESS</RsStatCode><Desc>查詢個人所有特殊投資法憑證資料成功</Desc></RsStat><ChlEJNo>MMA-FUND_gMeghodCert-0000095798725</ChlEJNo><RqTime>2013-07-11T11:10:07</RqTime><RsTime>2013-07-11T11:10:53</RsTime><CustomerID>A100383041</CustomerID><CustomerIDCheckcode>0</CustomerIDCheckcode></RsHeader><SvcRs><Rs><certificateBranchNo>010</certificateBranchNo><certificateFundID>S62</certificateFundID><certificateSeqNo>01000313</certificateSeqNo><enteredBankNo>807</enteredBankNo><enteredAccountNo>01000400073872</enteredAccountNo><deductionBankNo>807</deductionBankNo><deductionAccountNo>17500400602485</deductionAccountNo><trustBeginningDate>2010/04/23</trustBeginningDate><refNavDate>2013/06/27</refNavDate><totalUnit>0</totalUnit><avgNav>11.57</avgNav><avgNavCur>USD</avgNavCur><redemNav>12.37</redemNav><redemNavCur>USD</redemNavCur><totalDollar>0</totalDollar><totalDollarCur>TWD</totalDollarCur><assetValue>0</assetValue><assetValueCur>TWD</assetValueCur><revenue>0</revenue><revenueCur>TWD</revenueCur><ratio>0</ratio><stockMark>1</stockMark><customerID>A100383041</customerID><customerIDCheckCode>0</customerIDCheckCode><stopGainPoint>0</stopGainPoint><totalRatio>0</totalRatio><totalRevenue>0</totalRevenue><totalRevenueCur></totalRevenueCur><methodNo>01</methodNo><methodSeqNo>43066</methodSeqNo><targetMark>0</targetMark><redemMark>0</redemMark><buyDealRate>29.946</buyDealRate><fundName></fundName><switchMark>1</switchMark><stopGainPoint2>0</stopGainPoint2><stopGainPoint3>15</stopGainPoint3><stopLossPoint>0</stopLossPoint><targetStopGainPoint>0</targetStopGainPoint><targetStopLossPoint>0</targetStopLossPoint></Rs><Rs><certificateBranchNo>010</certificateBranchNo><certificateFundID>770</certificateFundID><certificateSeqNo>01000314</certificateSeqNo><enteredBankNo>807</enteredBankNo><enteredAccountNo>01000400073872</enteredAccountNo><deductionBankNo>807</deductionBankNo><deductionAccountNo>17500400602485</deductionAccountNo><trustBeginningDate>2010/04/23</trustBeginningDate><refNavDate>2013/06/27</refNavDate><totalUnit>187.75</totalUnit><avgNav>35.073</avgNav><avgNavCur>USD</avgNavCur><redemNav>26.12</redemNav><redemNavCur>USD</redemNavCur><totalDollar>200000</totalDollar><totalDollarCur>TWD</totalDollarCur><assetValue>146856</assetValue><assetValueCur>TWD</assetValueCur><revenue>-53144</revenue><revenueCur>TWD</revenueCur><ratio>-26.572</ratio><stockMark>1</stockMark><customerID>A100383041</customerID><customerIDCheckCode>0</customerIDCheckCode><stopGainPoint>0</stopGainPoint><totalRatio>0</totalRatio><totalRevenue>0</totalRevenue><totalRevenueCur></totalRevenueCur><methodNo>01</methodNo><methodSeqNo>43066</methodSeqNo><targetMark>1</targetMark><redemMark>0</redemMark><buyDealRate>29.946</buyDealRate><fundName></fundName><switchMark>1</switchMark><stopGainPoint2>0</stopGainPoint2><stopGainPoint3>15</stopGainPoint3><stopLossPoint>0</stopLossPoint><targetStopGainPoint>0</targetStopGainPoint><targetStopLossPoint>0</targetStopLossPoint></Rs><Rs><certificateBranchNo>010</certificateBranchNo><certificateFundID>770</certificateFundID><certificateSeqNo>01000315</certificateSeqNo><enteredBankNo>807</enteredBankNo><enteredAccountNo>01000400073872</enteredAccountNo><deductionBankNo>807</deductionBankNo><deductionAccountNo>17500400602485</deductionAccountNo><trustBeginningDate>2010/04/23</trustBeginningDate><refNavDate>2013/06/27</refNavDate><totalUnit>187.92</totalUnit><avgNav>35.05911</avgNav><avgNavCur>USD</avgNavCur><redemNav>26.12</redemNav><redemNavCur>USD</redemNavCur><totalDollar>200000</totalDollar><totalDollarCur>TWD</totalDollarCur><assetValue>146989</assetValue><assetValueCur>TWD</assetValueCur><revenue>-53011</revenue><revenueCur>TWD</revenueCur><ratio>-26.506</ratio><stockMark>1</stockMark><customerID>A100383041</customerID><customerIDCheckCode>0</customerIDCheckCode><stopGainPoint>0</stopGainPoint><totalRatio>0</totalRatio><totalRevenue>0</totalRevenue><totalRevenueCur></totalRevenueCur><methodNo>01</methodNo><methodSeqNo>43066</methodSeqNo><targetMark>1</targetMark><redemMark>0</redemMark><buyDealRate>29.946</buyDealRate><fundName></fundName><switchMark>1</switchMark><stopGainPoint2>0</stopGainPoint2><stopGainPoint3>15</stopGainPoint3><stopLossPoint>0</stopLossPoint><targetStopGainPoint>0</targetStopGainPoint><targetStopLossPoint>0</targetStopLossPoint></Rs><Rs><certificateBranchNo>010</certificateBranchNo><certificateFundID>770</certificateFundID><certificateSeqNo>01000316</certificateSeqNo><enteredBankNo>807</enteredBankNo><enteredAccountNo>01000400073872</enteredAccountNo><deductionBankNo>807</deductionBankNo><deductionAccountNo>17500400602485</deductionAccountNo><trustBeginningDate>2010/04/23</trustBeginningDate><refNavDate>2013/06/27</refNavDate><totalUnit>190.35</totalUnit><avgNav>34.63162</avgNav><avgNavCur>USD</avgNavCur><redemNav>26.12</redemNav><redemNavCur>USD</redemNavCur><totalDollar>200000</totalDollar><totalDollarCur>TWD</totalDollarCur><assetValue>148890</assetValue><assetValueCur>TWD</assetValueCur><revenue>-51110</revenue><revenueCur>TWD</revenueCur><ratio>-25.555</ratio><stockMark>0</stockMark><customerID>A100383041</customerID><customerIDCheckCode>0</customerIDCheckCode><stopGainPoint>0</stopGainPoint><totalRatio>0</totalRatio><totalRevenue>0</totalRevenue><totalRevenueCur></totalRevenueCur><methodNo>01</methodNo><methodSeqNo>43066</methodSeqNo><targetMark>1</targetMark><redemMark>0</redemMark><buyDealRate>29.946</buyDealRate><fundName></fundName><switchMark>1</switchMark><stopGainPoint2>0</stopGainPoint2><stopGainPoint3>15</stopGainPoint3><stopLossPoint>0</stopLossPoint><targetStopGainPoint>0</targetStopGainPoint><targetStopLossPoint>0</targetStopLossPoint></Rs><Rs><certificateBranchNo></certificateBranchNo><certificateFundID></certificateFundID><certificateSeqNo></certificateSeqNo><enteredBankNo></enteredBankNo><enteredAccountNo></enteredAccountNo><deductionBankNo></deductionBankNo><deductionAccountNo></deductionAccountNo><trustBeginningDate></trustBeginningDate><refNavDate></refNavDate><totalUnit></totalUnit><avgNav></avgNav><avgNavCur></avgNavCur><redemNav></redemNav><redemNavCur></redemNavCur><totalDollar></totalDollar><totalDollarCur></totalDollarCur><assetValue></assetValue><assetValueCur></assetValueCur><revenue></revenue><revenueCur></revenueCur><ratio></ratio><stockMark></stockMark><customerID></customerID><customerIDCheckCode></customerIDCheckCode><stopGainPoint></stopGainPoint><totalRatio>-26.211</totalRatio><totalRevenue>-157265</totalRevenue><totalRevenueCur>TWD</totalRevenueCur><methodNo></methodNo><methodSeqNo></methodSeqNo><targetMark></targetMark><redemMark></redemMark><buyDealRate></buyDealRate><fundName></fundName><switchMark></switchMark><stopGainPoint2></stopGainPoint2><stopGainPoint3></stopGainPoint3><stopLossPoint></stopLossPoint><targetStopGainPoint></targetStopGainPoint><targetStopLossPoint></targetStopLossPoint></Rs></SvcRs></IFUND>
B120: 115 | C120: 商品應用部 | D120: 財富信託科 | E120: TWTXN00059 | F120: 財富交易網銀系統 | G120: iFund | H120: Inv012_F | I120: funGetCustDeduList | J120: 取得基金庫存試算資料 | K120: Y | M120: 1 | N120: 45009 | O120: Callee | P120: 程式無異動，故不需另行開發 | Q120: <?xmlversion="1.0"encoding="UTF-8"?><IFUND><RqHeader><MsgID>funGetCustDeduList</MsgID><ChlName>EBANK</ChlName><ChlEJNo>MMA-FUND_gCustDedu-0000095798725</ChlEJNo><ChlSendTime>2013-07-03T11:23:32</ChlSendTime><CustomerID>G220728026</CustomerID><CustomerIDCheckcode>0</CustomerIDCheckcode><ChlIP>10.11.22.53</ChlIP></RqHeader><SvcRq><Rq><CustomerID>G220728026</CustomerID><CustomerIDCheckcode>0</CustomerIDCheckcode></Rq></SvcRq></IFUND> | R120: <?xmlversion="1.0"encoding="UTF-8"?><IFUND><RsHeader><RsStat><RsStatCode>SUCCESS</RsStatCode><Desc>取得基金庫存試算資料成功</Desc></RsStat><ChlEJNo>MMA-FUND_gCustDedu-0000095798725</ChlEJNo><RqTime>2013-08-22T14:53:26</RqTime><RsTime>2013-08-22T14:53:28</RsTime><CustomerID>G220728026</CustomerID><CustomerIDCheckcode>0</CustomerIDCheckcode></RsHeader><SvcRs><Rs><currencyID>AUD</currencyID><deduDollar6></deduDollar6><deduDollarbyCard>0</deduDollarbyCard><capital>6493.99</capital><totalDollar>6584.97</totalDollar><profit>-1.382</profit></Rs><Rs><currencyID>EUR</currencyID><deduDollar6>01,200/05,200/09,200/13,200/15,200</deduDollar6><deduDollarbyCard>0</deduDollarbyCard><capital>7579.45</capital><totalDollar>8617</totalDollar><profit>-12.041</profit></Rs><Rs><currencyID>TWD</currencyID><deduDollar6>06,29000/16,18000/18,5000</deduDollar6><deduDollarbyCard>0</deduDollarbyCard><capital>9674978</capital><totalDollar>9818211</totalDollar><profit>-1.459</profit></Rs><Rs><currencyID>USD</currencyID><deduDollar6>10,300</deduDollar6><deduDollarbyCard>0</deduDollarbyCard><capital>16317.24</capital><totalDollar>14769.09</totalDollar><profit>10.482</profit></Rs><Rs><currencyID>ZAR</currencyID><deduDollar6>19,1000/24,1000</deduDollar6><deduDollarbyCard>0</deduDollarbyCard><capital>13302.3</capital><totalDollar>13600</totalDollar><profit>-2.189</profit></Rs></SvcRs></IFUND>
B121: 116 | C121: 商品應用部 | D121: 財富信託科 | E121: TWTXN00059 | F121: 財富交易網銀系統 | G121: iFund | H121: Inv013_F | I121: fundGetAllTargetType | J121: 取得全部目標用途 | K121: Y | M121: 1 | N121: 45009 | O121: Callee | P121: 程式無異動，故不需另行開發 | Q121: <?xmlversion="1.0"encoding="UTF-8"?><IFUND><RqHeader><MsgID>fundGetAllTargetType</MsgID><ChlName>EBANK</ChlName><ChlEJNo>MMA-FUND_gTarget-0000095798725</ChlEJNo><ChlSendTime>2013-07-03T11:23:32</ChlSendTime><CustomerID>A100383041</CustomerID><CustomerIDCheckcode>0</CustomerIDCheckcode><ChlIP>10.11.22.53</ChlIP></RqHeader><SvcRq><Rq><CustomerID>A100383041</CustomerID><CustomerIDCheckcode>0</CustomerIDCheckcode></Rq></SvcRq></IFUND> | R121: <?xmlversion="1.0"encoding="UTF-8"?><IFUND><RsHeader><RsStat><RsStatCode>SUCCESS</RsStatCode><Desc>取得全部目標用途成功</Desc></RsStat><ChlEJNo>MMA-FUND_gTarget-0000095798725</ChlEJNo><RqTime>2013-07-11T11:10:07</RqTime><RsTime>2013-07-11T11:10:53</RsTime><CustomerID>A100383041</CustomerID><CustomerIDCheckcode>0</CustomerIDCheckcode></RsHeader><SvcRs><Rs><targetType>0</targetType><targetName>全部</targetName></Rs><Rs><targetType>1</targetType><targetName>退休金</targetName></Rs><Rs><targetType>2</targetType><targetName>子女教育金</targetName></Rs><Rs><targetType>3</targetType><targetName>購車</targetName></Rs><Rs><targetType>4</targetType><targetName>置屋</targetName></Rs><Rs><targetType>5</targetType><targetName>旅遊</targetName></Rs></SvcRs></IFUND>驗證發生錯誤<?xmlversion="1.0"encoding="UTF-8"?><IFUND><RsHeader><RsStat><RsStatCode>FAIL</RsStatCode><Desc>取得全部目標用途錯誤</Desc></RsStat><ChlEJNo>MMA-FUND_gTarget-0000095798725</ChlEJNo><RqTime>2013-07-11T11:10:07</RqTime><RsTime>2013-07-11T11:10:53</RsTime><CustomerID>A100383041</CustomerID><CustomerIDCheckcode>0</CustomerIDCheckcode></RsHeader><SvcRs><Rs></Rs></SvcRs></IFUND>
... B135: 130 | C135: 商品應用部 | D135: 財富信託科 | E135: TWTXN00059 | F135: 財富交易網銀系統 | G135: iFund | H135: Inv027_F | I135: funGetTransactionStatus | J135: 開關帳狀態查詢 | K135: Y | M135: 1 | N135: 45009 | O135: Callee | P135: 程式無異動，故不需另行開發 | Q135: <?xmlversion="1.0"encoding="UTF-8"?><IFUND><RqHeader><MsgID>funGetTransactionStatus</MsgID><ChlName>EBANK</ChlName><ChlEJNo>MMA-FUND_gTrs-0000095798724</ChlEJNo><ChlSendTime>2012-08-29T11:10:21</ChlSendTime><CustomerID></CustomerID><CustomerIDCheckcode></CustomerIDCheckcode><ChlIP>127.0.0.1</ChlIP></RqHeader><SvcRq><Rq></Rq></SvcRq></IFUND> | R135: <?xmlversion="1.0"encoding="utf-8"?><IFUND><RsHeader><RsStat><RsStatCode>SUCCESS</RsStatCode><Desc>查詢開關帳狀態成功</Desc></RsStat><ChlEJNo>MMA-FUND_gTrs-0000095798724</ChlEJNo><RqTime>2012-08-29T11:10:21</RqTime><RsTime>2012-08-29T11:10:21</RsTime><CustomerID>E120120535</CustomerID><CustomerIDCheckcode>0</CustomerIDCheckcode></RsHeader><SvcRs><Rs><TransStatus></TransStatus></Rs><SvcRs></IFUND>
B136: 131 | C136: 商品應用部 | D136: 財富信託科 | E136: TWTXN00059 | F136: 財富交易網銀系統 | G136: iFund | H136: Inv028_F | I136: funGetCurrencySum | J136: 幣別投資加總查詢 | K136: Y | M136: 1 | N136: 44986 | O136: Callee | Q136: <?xmlversion="1.0"encoding="UTF-8"?><IFUND><RqHeader><MsgID>funGetCurrencySum</MsgID><ChlName>EBANK</ChlName><ChlEJNo>MMA-FUND-gCurSum-0000095798724</ChlEJNo><ChlSendTime>2012-08-29T11:10:21</ChlSendTime><CustomerID>A122131774</CustomerID><CustomerIDCheckcode>0</CustomerIDCheckcode><ChlIP>127.0.0.1</ChlIP><Language></Language></RqHeader><SvcRq><Rq></Rq></SvcRq></IFUND> | R136: <?xmlversion="1.0"encoding="utf-8"?><IFUND><RsHeader><RsStat><RsStatCode>SUCCESS</RsStatCode><Desc>查詢幣別投資加總成功</Desc></RsStat><ChlEJNo>MMA-FUND_gCurSum-0000095798724</ChlEJNo><RqTime>2012-08-29T11:10:21</RqTime><RsTime>2012-08-29T11:10:21</RsTime><CustomerID>E120120535</CustomerID><CustomerIDCheckcode>0</CustomerIDCheckcode></RsHeader><SvcRs><Rs><Currency></Currency><TrustDollar></TrustDollar><AssetDollar></AssetDollar><MTrustDollar></MTrustDollar><MAssetDollar></MAssetDollar></Rs><SvcRs></IFUND>
B137: 132 | C137: 商品應用部 | D137: 財富信託科 | E137: TWTXN00059 | F137: 財富交易網銀系統 | G137: iFund | H137: Inv029_F | I137: funGetMethodList | J137: 效投憑證組合查詢 | K137: Y | M137: 1 | N137: 44986 | O137: Callee | Q137: <?xmlversion="1.0"encoding="UTF-8"?><IFUND><RqHeader><MsgID>funGetMethodList</MsgID><ChlName>EBANK</ChlName><ChlEJNo>MMA-FUND-gMethList-0000095798724</ChlEJNo><ChlSendTime>2012-08-29T11:10:21</ChlSendTime><CustomerID>A122131774</CustomerID><CustomerIDCheckcode>0</CustomerIDCheckcode><ChlIP>127.0.0.1</ChlIP><Language></Language></RqHeader><SvcRq><Rq><Currency></Currency></Rq></SvcRq></IFUND> | R137: <?xmlversion="1.0"encoding="utf-8"?><IFUND><RsHeader><RsStat><RsStatCode>SUCCESS</RsStatCode><Desc>查詢效投憑證組合成功</Desc></RsStat><ChlEJNo>MMA-FUND_gMethList-0000095798724</ChlEJNo><RqTime>2012-08-29T11:10:21</RqTime><RsTime>2012-08-29T11:10:21</RsTime><CustomerID>E120120535</CustomerID><CustomerIDCheckcode>0</CustomerIDCheckcode><Language></Language></RsHeader><SvcRs><Rs><certificateBranchNo>010</certificateBranchNo><certificateFundID>S62</certificateFundID><certificateSeqNo>01000313</certificateSeqNo><totalDollar>0</totalDollar><totalDollarCur>TWD</totalDollarCur><assetValue>0</assetValue><assetValueCur></assetValueCur><totalRatio>0</totalRatio><totalRevenue>0</totalRevenue><methodNo>01</methodNo><methodSeqNo>43066</methodSeqNo><Inv_Type></Inv_Type><Inv_TypeDesc></Inv_TypeDesc><targetMark>0</targetMark><redemMark></redemMark><fundName></fundName></Rs></SvcRs></IFUND>
